Workbook
Name _1억원: '[1]Master sheet'!$AH$13
Name _2019PAX: '[1]Master sheet'!$M$16
Name USDKRW: '[1]Master sheet'!$AH$12
Name WATD_2021: [2]!Table23[[#All],[IATA Code]:[Total cargo 2019]]
Name WATD_2023: '[2]WATD 2022'!$I$2:$AM$2679
Name WATD2019: [2]!Table24[[#All],[IATA Code]:[Total cargo 2017]]

Sheet Pax Demand
A1: top | B1: mid | C1: low | D1: decimal | E1: changeable | F1: 변수설명 | G1: Ref_Index | H1: =I1-1 | I1: =J1-1 | J1: =K1-1 | K1: =L1-1 | L1: =M1-1 | M1: =N1-1 | N1: =O1-1 | O1: =P1-1 | P1: =Q1-1 | Q1: =ref!B4 | R1: =Q1+1 | S1: =R1+1 | T1: =S1+1 | U1: =T1+1 | V1: =U1+1 | W1: =V1+1 | X1: =W1+1 | Y1: =X1+1 | ... BA1: =AZ1+1
A2: General Index | B2: Passenger Index | C2: Annual Passengers📝 | D2: float0 | E2: O | F2: 연간여객 | H2: =VLOOKUP($F2,raw_data_pax!$1:$1048576,MATCH(H$1,raw_data_pax!$1:$1,0),FALSE) | I2: =VLOOKUP($F2,raw_data_pax!$1:$1048576,MATCH(I$1,raw_data_pax!$1:$1,0),FALSE) | J2: =VLOOKUP($F2,raw_data_pax!$1:$1048576,MATCH(J$1,raw_data_pax!$1:$1,0),FALSE) | K2: =VLOOKUP($F2,raw_data_pax!$1:$1048576,MATCH(K$1,raw_data_pax!$1:$1,0),FALSE) | L2: =VLOOKUP($F2,raw_data_pax!$1:$1048576,MATCH(L$1,raw_data_pax!$1:$1,0),FALSE) | M2: =VLOOKUP($F2,raw_data_pax!$1:$1048576,MATCH(M$1,raw_data_pax!$1:$1,0),FALSE) | N2: =VLOOKUP($F2,raw_data_pax!$1:$1048576,MATCH(N$1,raw_data_pax!$1:$1,0),FALSE) | O2: =VLOOKUP($F2,raw_data_pax!$1:$1048576,MATCH(O$1,raw_data_pax!$1:$1,0),FALSE) | ... Q2: =VLOOKUP($F2,raw_data_pax!$1:$1048576,MATCH(Q$1,raw_data_pax!$1:$1,0),FALSE) | R2: =HLOOKUP(R1,'Final (total_pax)'!$1:$4,4,FALSE) | S2: =HLOOKUP(S1,'Final (total_pax)'!$1:$4,4,FALSE) | T2: =HLOOKUP(T1,'Final (total_pax)'!$1:$4,4,FALSE) | U2: =HLOOKUP(U1,'Final (total_pax)'!$1:$4,4,FALSE) | V2: =HLOOKUP(V1,'Final (total_pax)'!$1:$4,4,FALSE) | W2: =HLOOKUP(W1,'Final (total_pax)'!$1:$4,4,FALSE) | X2: =HLOOKUP(X1,'Final (total_pax)'!$1:$4,4,FALSE) | Y2: =HLOOKUP(Y1,'Final (total_pax)'!$1:$4,4,FALSE) | ... BA2: =HLOOKUP(BA1,'Final (total_pax)'!$1:$4,4,FALSE)
C3: International Passengers | D3: float0 | F3: International여객 | H3: =VLOOKUP($F3,raw_data_pax!$1:$1048576,MATCH(H$1,raw_data_pax!$1:$1,0),FALSE) | I3: =VLOOKUP($F3,raw_data_pax!$1:$1048576,MATCH(I$1,raw_data_pax!$1:$1,0),FALSE) | J3: =VLOOKUP($F3,raw_data_pax!$1:$1048576,MATCH(J$1,raw_data_pax!$1:$1,0),FALSE) | K3: =VLOOKUP($F3,raw_data_pax!$1:$1048576,MATCH(K$1,raw_data_pax!$1:$1,0),FALSE) | L3: =VLOOKUP($F3,raw_data_pax!$1:$1048576,MATCH(L$1,raw_data_pax!$1:$1,0),FALSE) | M3: =VLOOKUP($F3,raw_data_pax!$1:$1048576,MATCH(M$1,raw_data_pax!$1:$1,0),FALSE) | N3: =VLOOKUP($F3,raw_data_pax!$1:$1048576,MATCH(N$1,raw_data_pax!$1:$1,0),FALSE) | O3: =VLOOKUP($F3,raw_data_pax!$1:$1048576,MATCH(O$1,raw_data_pax!$1:$1,0),FALSE) | ... Q3: =VLOOKUP($F3,raw_data_pax!$1:$1048576,MATCH(Q$1,raw_data_pax!$1:$1,0),FALSE) | R3: =R2*R9 | S3: =S2*S9 | T3: =T2*T9 | U3: =U2*U9 | V3: =V2*V9 | W3: =W2*W9 | X3: =X2*X9 | Y3: =Y2*Y9 | ... BA3: =BA2*BA9
C4: Domestic Passengers | D4: float0 | F4: Domestic여객 | H4: =VLOOKUP($F4,raw_data_pax!$1:$1048576,MATCH(H$1,raw_data_pax!$1:$1,0),FALSE) | I4: =VLOOKUP($F4,raw_data_pax!$1:$1048576,MATCH(I$1,raw_data_pax!$1:$1,0),FALSE) | J4: =VLOOKUP($F4,raw_data_pax!$1:$1048576,MATCH(J$1,raw_data_pax!$1:$1,0),FALSE) | K4: =VLOOKUP($F4,raw_data_pax!$1:$1048576,MATCH(K$1,raw_data_pax!$1:$1,0),FALSE) | L4: =VLOOKUP($F4,raw_data_pax!$1:$1048576,MATCH(L$1,raw_data_pax!$1:$1,0),FALSE) | M4: =VLOOKUP($F4,raw_data_pax!$1:$1048576,MATCH(M$1,raw_data_pax!$1:$1,0),FALSE) | N4: =VLOOKUP($F4,raw_data_pax!$1:$1048576,MATCH(N$1,raw_data_pax!$1:$1,0),FALSE) | O4: =VLOOKUP($F4,raw_data_pax!$1:$1048576,MATCH(O$1,raw_data_pax!$1:$1,0),FALSE) | ... Q4: =VLOOKUP($F4,raw_data_pax!$1:$1048576,MATCH(Q$1,raw_data_pax!$1:$1,0),FALSE) | R4: =R2-R3 | S4: =S2-S3 | T4: =T2-T3 | U4: =U2-U3 | V4: =V2-V3 | W4: =W2-W3 | X4: =X2-X3 | Y4: =Y2-Y3 | ... BA4: =BA2-BA3
C5: Long_haul Passengers | D5: float0 | F5: Long_haul여객 | H5: =VLOOKUP($F5,raw_data_pax!$1:$1048576,MATCH(H$1,raw_data_pax!$1:$1,0),FALSE) | I5: =VLOOKUP($F5,raw_data_pax!$1:$1048576,MATCH(I$1,raw_data_pax!$1:$1,0),FALSE) | J5: =VLOOKUP($F5,raw_data_pax!$1:$1048576,MATCH(J$1,raw_data_pax!$1:$1,0),FALSE) | K5: =VLOOKUP($F5,raw_data_pax!$1:$1048576,MATCH(K$1,raw_data_pax!$1:$1,0),FALSE) | L5: =VLOOKUP($F5,raw_data_pax!$1:$1048576,MATCH(L$1,raw_data_pax!$1:$1,0),FALSE) | M5: =VLOOKUP($F5,raw_data_pax!$1:$1048576,MATCH(M$1,raw_data_pax!$1:$1,0),FALSE) | N5: =VLOOKUP($F5,raw_data_pax!$1:$1048576,MATCH(N$1,raw_data_pax!$1:$1,0),FALSE) | O5: =VLOOKUP($F5,raw_data_pax!$1:$1048576,MATCH(O$1,raw_data_pax!$1:$1,0),FALSE) | ... Q5: =VLOOKUP($F5,raw_data_pax!$1:$1048576,MATCH(Q$1,raw_data_pax!$1:$1,0),FALSE) | R5: =R2*R10 | S5: =S2*S10 | T5: =T2*T10 | U5: =U2*U10 | V5: =V2*V10 | W5: =W2*W10 | X5: =X2*X10 | Y5: =Y2*Y10 | ... BA5: =BA2*BA10
C6: Short_haul Passengers | D6: float0 | F6: Short_haul여객 | H6: =VLOOKUP($F6,raw_data_pax!$1:$1048576,MATCH(H$1,raw_data_pax!$1:$1,0),FALSE) | I6: =VLOOKUP($F6,raw_data_pax!$1:$1048576,MATCH(I$1,raw_data_pax!$1:$1,0),FALSE) | J6: =VLOOKUP($F6,raw_data_pax!$1:$1048576,MATCH(J$1,raw_data_pax!$1:$1,0),FALSE) | K6: =VLOOKUP($F6,raw_data_pax!$1:$1048576,MATCH(K$1,raw_data_pax!$1:$1,0),FALSE) | L6: =VLOOKUP($F6,raw_data_pax!$1:$1048576,MATCH(L$1,raw_data_pax!$1:$1,0),FALSE) | M6: =VLOOKUP($F6,raw_data_pax!$1:$1048576,MATCH(M$1,raw_data_pax!$1:$1,0),FALSE) | N6: =VLOOKUP($F6,raw_data_pax!$1:$1048576,MATCH(N$1,raw_data_pax!$1:$1,0),FALSE) | O6: =VLOOKUP($F6,raw_data_pax!$1:$1048576,MATCH(O$1,raw_data_pax!$1:$1,0),FALSE) | ... Q6: =VLOOKUP($F6,raw_data_pax!$1:$1048576,MATCH(Q$1,raw_data_pax!$1:$1,0),FALSE) | R6: =R2-R5 | S6: =S2-S5 | T6: =T2-T5 | U6: =U2-U5 | V6: =V2-V5 | W6: =W2-W5 | X6: =X2-X5 | Y6: =Y2-Y5 | ... BA6: =BA2-BA5
C7: Normal Passengers | D7: float0 | F7: 정규여객 | H7: =VLOOKUP($F7,raw_data_pax!$1:$1048576,MATCH(H$1,raw_data_pax!$1:$1,0),FALSE) | I7: =VLOOKUP($F7,raw_data_pax!$1:$1048576,MATCH(I$1,raw_data_pax!$1:$1,0),FALSE) | J7: =VLOOKUP($F7,raw_data_pax!$1:$1048576,MATCH(J$1,raw_data_pax!$1:$1,0),FALSE) | K7: =VLOOKUP($F7,raw_data_pax!$1:$1048576,MATCH(K$1,raw_data_pax!$1:$1,0),FALSE) | L7: =VLOOKUP($F7,raw_data_pax!$1:$1048576,MATCH(L$1,raw_data_pax!$1:$1,0),FALSE) | M7: =VLOOKUP($F7,raw_data_pax!$1:$1048576,MATCH(M$1,raw_data_pax!$1:$1,0),FALSE) | N7: =VLOOKUP($F7,raw_data_pax!$1:$1048576,MATCH(N$1,raw_data_pax!$1:$1,0),FALSE) | O7: =VLOOKUP($F7,raw_data_pax!$1:$1048576,MATCH(O$1,raw_data_pax!$1:$1,0),FALSE) | ... Q7: =VLOOKUP($F7,raw_data_pax!$1:$1048576,MATCH(Q$1,raw_data_pax!$1:$1,0),FALSE) | R7: =R2*R11 | S7: =S2*S11 | T7: =T2*T11 | U7: =U2*U11 | V7: =V2*V11 | W7: =W2*W11 | X7: =X2*X11 | Y7: =Y2*Y11 | ... BA7: =BA2*BA11
C8: Charter Passengers | D8: float0 | F8: 전세기여객 | H8: =VLOOKUP($F8,raw_data_pax!$1:$1048576,MATCH(H$1,raw_data_pax!$1:$1,0),FALSE) | I8: =VLOOKUP($F8,raw_data_pax!$1:$1048576,MATCH(I$1,raw_data_pax!$1:$1,0),FALSE) | J8: =VLOOKUP($F8,raw_data_pax!$1:$1048576,MATCH(J$1,raw_data_pax!$1:$1,0),FALSE) | K8: =VLOOKUP($F8,raw_data_pax!$1:$1048576,MATCH(K$1,raw_data_pax!$1:$1,0),FALSE) | L8: =VLOOKUP($F8,raw_data_pax!$1:$1048576,MATCH(L$1,raw_data_pax!$1:$1,0),FALSE) | M8: =VLOOKUP($F8,raw_data_pax!$1:$1048576,MATCH(M$1,raw_data_pax!$1:$1,0),FALSE) | N8: =VLOOKUP($F8,raw_data_pax!$1:$1048576,MATCH(N$1,raw_data_pax!$1:$1,0),FALSE) | O8: =VLOOKUP($F8,raw_data_pax!$1:$1048576,MATCH(O$1,raw_data_pax!$1:$1,0),FALSE) | ... Q8: =VLOOKUP($F8,raw_data_pax!$1:$1048576,MATCH(Q$1,raw_data_pax!$1:$1,0),FALSE) | R8: =R2-R7 | S8: =S2-S7 | T8: =T2-T7 | U8: =U2-U7 | V8: =V2-V7 | W8: =W2-W7 | X8: =X2-X7 | Y8: =Y2-Y7 | ... BA8: =BA2-BA7
C9: International Passengers(%)📝 | D9: percent0 | E9: O | G9: =IFERROR(SUMIF($H$159:$Q$159,"O",H9:Q9)/COUNTIFS($H$159:$Q$159,"O",H9:Q9,"<>0"),0) | H9: =H3/H2 | I9: =I3/I2 | J9: =J3/J2 | K9: =K3/K2 | L9: =L3/L2 | M9: =M3/M2 | N9: =N3/N2 | O9: =O3/O2 | ... Q9: =Q3/Q2 | R9: =G9 | S9: =R9 | T9: =S9 | U9: =T9 | V9: =U9 | W9: =V9 | X9: =W9 | Y9: =X9 | Z9: =Y9 | ... BA9: =AZ9
C10: Longhaul Passengers(%)📝 | D10: percent0 | E10: O | G10: =IFERROR(SUMIF($H$159:$Q$159,"O",H10:Q10)/COUNTIFS($H$159:$Q$159,"O",H10:Q10,"<>0"),0) | H10: =H5/H2 | I10: =I5/I2 | J10: =J5/J2 | K10: =K5/K2 | L10: =L5/L2 | M10: =M5/M2 | N10: =N5/N2 | O10: =O5/O2 | ... Q10: =Q5/Q2 | R10: =G10 | S10: =R10 | T10: =S10 | U10: =T10 | V10: =U10 | W10: =V10 | X10: =W10 | Y10: =X10 | Z10: =Y10 | ... BA10: =AZ10
C11: Regular Passengers(%)📝 | D11: percent0 | E11: O | G11: =IFERROR(SUMIF($H$159:$Q$159,"O",H11:Q11)/COUNTIFS($H$159:$Q$159,"O",H11:Q11,"<>0"),0) | H11: =H7/H2 | I11: =I7/I2 | J11: =J7/J2 | K11: =K7/K2 | L11: =L7/L2 | M11: =M7/M2 | N11: =N7/N2 | O11: =O7/O2 | ... Q11: =Q7/Q2 | R11: =G11 | S11: =R11 | T11: =S11 | U11: =T11 | V11: =U11 | W11: =V11 | X11: =W11 | Y11: =X11 | Z11: =Y11 | ... BA11: =AZ11
C12: Total Seats | D12: float0 | H12: =H13*H20 | I12: =I13*I20 | J12: =J13*J20 | K12: =K13*K20 | L12: =L13*L20 | M12: =M13*M20 | N12: =N13*N20 | O12: =O13*O20 | ... BA12: =BA13*BA20
C13: Average Seats Per Aircraft | D13: float0 | F13: 대당좌석수 | H13: =VLOOKUP($F13,raw_data_pax!$1:$1048576,MATCH(H$1,raw_data_pax!$1:$1,0),FALSE) | I13: =VLOOKUP($F13,raw_data_pax!$1:$1048576,MATCH(I$1,raw_data_pax!$1:$1,0),FALSE) | J13: =VLOOKUP($F13,raw_data_pax!$1:$1048576,MATCH(J$1,raw_data_pax!$1:$1,0),FALSE) | K13: =VLOOKUP($F13,raw_data_pax!$1:$1048576,MATCH(K$1,raw_data_pax!$1:$1,0),FALSE) | L13: =VLOOKUP($F13,raw_data_pax!$1:$1048576,MATCH(L$1,raw_data_pax!$1:$1,0),FALSE) | M13: =VLOOKUP($F13,raw_data_pax!$1:$1048576,MATCH(M$1,raw_data_pax!$1:$1,0),FALSE) | N13: =VLOOKUP($F13,raw_data_pax!$1:$1048576,MATCH(N$1,raw_data_pax!$1:$1,0),FALSE) | O13: =VLOOKUP($F13,raw_data_pax!$1:$1048576,MATCH(O$1,raw_data_pax!$1:$1,0),FALSE) | ... Q13: =VLOOKUP($F13,raw_data_pax!$1:$1048576,MATCH(Q$1,raw_data_pax!$1:$1,0),FALSE) | R13: =SUMPRODUCT(R51:R54,R31:R34) | S13: =SUMPRODUCT(S51:S54,S31:S34) | T13: =SUMPRODUCT(T51:T54,T31:T34) | U13: =SUMPRODUCT(U51:U54,U31:U34) | V13: =SUMPRODUCT(V51:V54,V31:V34) | W13: =SUMPRODUCT(W51:W54,W31:W34) | X13: =SUMPRODUCT(X51:X54,X31:X34) | Y13: =SUMPRODUCT(Y51:Y54,Y31:Y34) | ... BA13: =SUMPRODUCT(BA51:BA54,BA31:BA34)
C14: Load Factor(%)📝 | D14: percent0 | E14: O | F14: 탑승율 | G14: =SUMIF($H$160:$Q$160,"O",H14:Q14)/COUNTIFS($H$160:$Q$160,"O",H14:Q14,"<>0") | H14: =VLOOKUP($F14,raw_data_pax!$1:$1048576,MATCH(H$1,raw_data_pax!$1:$1,0),FALSE) | I14: =VLOOKUP($F14,raw_data_pax!$1:$1048576,MATCH(I$1,raw_data_pax!$1:$1,0),FALSE) | J14: =VLOOKUP($F14,raw_data_pax!$1:$1048576,MATCH(J$1,raw_data_pax!$1:$1,0),FALSE) | K14: =VLOOKUP($F14,raw_data_pax!$1:$1048576,MATCH(K$1,raw_data_pax!$1:$1,0),FALSE) | L14: =VLOOKUP($F14,raw_data_pax!$1:$1048576,MATCH(L$1,raw_data_pax!$1:$1,0),FALSE) | M14: =VLOOKUP($F14,raw_data_pax!$1:$1048576,MATCH(M$1,raw_data_pax!$1:$1,0),FALSE) | N14: =VLOOKUP($F14,raw_data_pax!$1:$1048576,MATCH(N$1,raw_data_pax!$1:$1,0),FALSE) | O14: =VLOOKUP($F14,raw_data_pax!$1:$1048576,MATCH(O$1,raw_data_pax!$1:$1,0),FALSE) | ... Q14: =VLOOKUP($F14,raw_data_pax!$1:$1048576,MATCH(Q$1,raw_data_pax!$1:$1,0),FALSE) | R14: =G14 | S14: =R14 | T14: =S14 | U14: =T14 | V14: =U14 | W14: =V14 | X14: =W14 | Y14: =X14 | Z14: =Y14 | ... BA14: =AZ14
C15: Average Passengers Per Aircraft | D15: float0 | F15: 대당여객 | H15: =VLOOKUP($F15,raw_data_pax!$1:$1048576,MATCH(H$1,raw_data_pax!$1:$1,0),FALSE) | I15: =VLOOKUP($F15,raw_data_pax!$1:$1048576,MATCH(I$1,raw_data_pax!$1:$1,0),FALSE) | J15: =VLOOKUP($F15,raw_data_pax!$1:$1048576,MATCH(J$1,raw_data_pax!$1:$1,0),FALSE) | K15: =VLOOKUP($F15,raw_data_pax!$1:$1048576,MATCH(K$1,raw_data_pax!$1:$1,0),FALSE) | L15: =VLOOKUP($F15,raw_data_pax!$1:$1048576,MATCH(L$1,raw_data_pax!$1:$1,0),FALSE) | M15: =VLOOKUP($F15,raw_data_pax!$1:$1048576,MATCH(M$1,raw_data_pax!$1:$1,0),FALSE) | N15: =VLOOKUP($F15,raw_data_pax!$1:$1048576,MATCH(N$1,raw_data_pax!$1:$1,0),FALSE) | O15: =VLOOKUP($F15,raw_data_pax!$1:$1048576,MATCH(O$1,raw_data_pax!$1:$1,0),FALSE) | ... Q15: =VLOOKUP($F15,raw_data_pax!$1:$1048576,MATCH(Q$1,raw_data_pax!$1:$1,0),FALSE) | R15: =R13*R14 | S15: =S13*S14 | T15: =T13*T14 | U15: =U13*U14 | V15: =V13*V14 | W15: =W13*W14 | X15: =X13*X14 | Y15: =Y13*Y14 | ... BA15: =BA13*BA14
C16: Annual Transfer Passengers | D16: float0 | F16: 연간환승승객 | H16: =VLOOKUP($F16,raw_data_pax!$1:$1048576,MATCH(H$1,raw_data_pax!$1:$1,0),FALSE) | I16: =VLOOKUP($F16,raw_data_pax!$1:$1048576,MATCH(I$1,raw_data_pax!$1:$1,0),FALSE) | J16: =VLOOKUP($F16,raw_data_pax!$1:$1048576,MATCH(J$1,raw_data_pax!$1:$1,0),FALSE) | K16: =VLOOKUP($F16,raw_data_pax!$1:$1048576,MATCH(K$1,raw_data_pax!$1:$1,0),FALSE) | L16: =VLOOKUP($F16,raw_data_pax!$1:$1048576,MATCH(L$1,raw_data_pax!$1:$1,0),FALSE) | M16: =VLOOKUP($F16,raw_data_pax!$1:$1048576,MATCH(M$1,raw_data_pax!$1:$1,0),FALSE) | N16: =VLOOKUP($F16,raw_data_pax!$1:$1048576,MATCH(N$1,raw_data_pax!$1:$1,0),FALSE) | O16: =VLOOKUP($F16,raw_data_pax!$1:$1048576,MATCH(O$1,raw_data_pax!$1:$1,0),FALSE) | ... Q16: =VLOOKUP($F16,raw_data_pax!$1:$1048576,MATCH(Q$1,raw_data_pax!$1:$1,0),FALSE) | R16: =R2*R17 | S16: =S2*S17 | T16: =T2*T17 | U16: =U2*U17 | V16: =V2*V17 | W16: =W2*W17 | X16: =X2*X17 | Y16: =Y2*Y17 | ... BA16: =BA2*BA17
C17: Transfer Rate(%)📝 | D17: percent0 | E17: O | F17: 환승율 | G17: =IFERROR(SUMIF($H$161:$Q$161,"O",H17:Q17)/COUNTIFS($H$161:$Q$161,"O",H17:Q17,"<>0"),0) | H17: =VLOOKUP($F17,raw_data_pax!$1:$1048576,MATCH(H$1,raw_data_pax!$1:$1,0),FALSE) | I17: =VLOOKUP($F17,raw_data_pax!$1:$1048576,MATCH(I$1,raw_data_pax!$1:$1,0),FALSE) | J17: =VLOOKUP($F17,raw_data_pax!$1:$1048576,MATCH(J$1,raw_data_pax!$1:$1,0),FALSE) | K17: =VLOOKUP($F17,raw_data_pax!$1:$1048576,MATCH(K$1,raw_data_pax!$1:$1,0),FALSE) | L17: =VLOOKUP($F17,raw_data_pax!$1:$1048576,MATCH(L$1,raw_data_pax!$1:$1,0),FALSE) | M17: =VLOOKUP($F17,raw_data_pax!$1:$1048576,MATCH(M$1,raw_data_pax!$1:$1,0),FALSE) | N17: =VLOOKUP($F17,raw_data_pax!$1:$1048576,MATCH(N$1,raw_data_pax!$1:$1,0),FALSE) | O17: =VLOOKUP($F17,raw_data_pax!$1:$1048576,MATCH(O$1,raw_data_pax!$1:$1,0),FALSE) | ... Q17: =VLOOKUP($F17,raw_data_pax!$1:$1048576,MATCH(Q$1,raw_data_pax!$1:$1,0),FALSE) | R17: =G17 | S17: =R17 | T17: =S17 | U17: =T17 | V17: =U17 | W17: =V17 | X17: =W17 | Y17: =X17 | Z17: =Y17 | ... BA17: =AZ17
C18: Average Crew Per Aircraft | D18: float0 | F18: 대당승무원 | H18: =VLOOKUP($F18,raw_data_pax!$1:$1048576,MATCH(H$1,raw_data_pax!$1:$1,0),FALSE) | I18: =VLOOKUP($F18,raw_data_pax!$1:$1048576,MATCH(I$1,raw_data_pax!$1:$1,0),FALSE) | J18: =VLOOKUP($F18,raw_data_pax!$1:$1048576,MATCH(J$1,raw_data_pax!$1:$1,0),FALSE) | K18: =VLOOKUP($F18,raw_data_pax!$1:$1048576,MATCH(K$1,raw_data_pax!$1:$1,0),FALSE) | L18: =VLOOKUP($F18,raw_data_pax!$1:$1048576,MATCH(L$1,raw_data_pax!$1:$1,0),FALSE) | M18: =VLOOKUP($F18,raw_data_pax!$1:$1048576,MATCH(M$1,raw_data_pax!$1:$1,0),FALSE) | N18: =VLOOKUP($F18,raw_data_pax!$1:$1048576,MATCH(N$1,raw_data_pax!$1:$1,0),FALSE) | O18: =VLOOKUP($F18,raw_data_pax!$1:$1048576,MATCH(O$1,raw_data_pax!$1:$1,0),FALSE) | ... Q18: =VLOOKUP($F18,raw_data_pax!$1:$1048576,MATCH(Q$1,raw_data_pax!$1:$1,0),FALSE) | R18: =IFERROR(SUMPRODUCT(R35:R38,R65:R68)/SUM(R35:R38),0) | S18: =IFERROR(SUMPRODUCT(S35:S38,S65:S68)/SUM(S35:S38),0) | T18: =IFERROR(SUMPRODUCT(T35:T38,T65:T68)/SUM(T35:T38),0) | U18: =IFERROR(SUMPRODUCT(U35:U38,U65:U68)/SUM(U35:U38),0) | V18: =IFERROR(SUMPRODUCT(V35:V38,V65:V68)/SUM(V35:V38),0) | W18: =IFERROR(SUMPRODUCT(W35:W38,W65:W68)/SUM(W35:W38),0) | X18: =IFERROR(SUMPRODUCT(X35:X38,X65:X68)/SUM(X35:X38),0) | Y18: =IFERROR(SUMPRODUCT(Y35:Y38,Y65:Y68)/SUM(Y35:Y38),0) | ... BA18: =IFERROR(SUMPRODUCT(BA35:BA38,BA65:BA68)/SUM(BA35:BA38),0)
C19: Crew Ratio(%) | D19: percent0 | F19: 승무원비율 | H19: =VLOOKUP($F19,raw_data_pax!$1:$1048576,MATCH(H$1,raw_data_pax!$1:$1,0),FALSE) | I19: =VLOOKUP($F19,raw_data_pax!$1:$1048576,MATCH(I$1,raw_data_pax!$1:$1,0),FALSE) | J19: =VLOOKUP($F19,raw_data_pax!$1:$1048576,MATCH(J$1,raw_data_pax!$1:$1,0),FALSE) | K19: =VLOOKUP($F19,raw_data_pax!$1:$1048576,MATCH(K$1,raw_data_pax!$1:$1,0),FALSE) | L19: =VLOOKUP($F19,raw_data_pax!$1:$1048576,MATCH(L$1,raw_data_pax!$1:$1,0),FALSE) | M19: =VLOOKUP($F19,raw_data_pax!$1:$1048576,MATCH(M$1,raw_data_pax!$1:$1,0),FALSE) | N19: =VLOOKUP($F19,raw_data_pax!$1:$1048576,MATCH(N$1,raw_data_pax!$1:$1,0),FALSE) | O19: =VLOOKUP($F19,raw_data_pax!$1:$1048576,MATCH(O$1,raw_data_pax!$1:$1,0),FALSE) | ... Q19: =VLOOKUP($F19,raw_data_pax!$1:$1048576,MATCH(Q$1,raw_data_pax!$1:$1,0),FALSE) | R19: =IFERROR(R18/R15,0) | S19: =IFERROR(S18/S15,0) | T19: =IFERROR(T18/T15,0) | U19: =IFERROR(U18/U15,0) | V19: =IFERROR(V18/V15,0) | W19: =IFERROR(W18/W15,0) | X19: =IFERROR(X18/X15,0) | Y19: =IFERROR(Y18/Y15,0) | ... BA19: =IFERROR(BA18/BA15,0)
B20: Passenger Flight Index | C20: Annual Movements | D20: float0 | F20: 연간운항 | H20: =VLOOKUP($F20,raw_data_pax!$1:$1048576,MATCH(H$1,raw_data_pax!$1:$1,0),FALSE) | I20: =VLOOKUP($F20,raw_data_pax!$1:$1048576,MATCH(I$1,raw_data_pax!$1:$1,0),FALSE) | J20: =VLOOKUP($F20,raw_data_pax!$1:$1048576,MATCH(J$1,raw_data_pax!$1:$1,0),FALSE) | K20: =VLOOKUP($F20,raw_data_pax!$1:$1048576,MATCH(K$1,raw_data_pax!$1:$1,0),FALSE) | L20: =VLOOKUP($F20,raw_data_pax!$1:$1048576,MATCH(L$1,raw_data_pax!$1:$1,0),FALSE) | M20: =VLOOKUP($F20,raw_data_pax!$1:$1048576,MATCH(M$1,raw_data_pax!$1:$1,0),FALSE) | N20: =VLOOKUP($F20,raw_data_pax!$1:$1048576,MATCH(N$1,raw_data_pax!$1:$1,0),FALSE) | O20: =VLOOKUP($F20,raw_data_pax!$1:$1048576,MATCH(O$1,raw_data_pax!$1:$1,0),FALSE) | ... Q20: =VLOOKUP($F20,raw_data_pax!$1:$1048576,MATCH(Q$1,raw_data_pax!$1:$1,0),FALSE) | R20: =IFERROR(R2/R15,0) | S20: =IFERROR(S2/S15,0) | T20: =IFERROR(T2/T15,0) | U20: =IFERROR(U2/U15,0) | V20: =IFERROR(V2/V15,0) | W20: =IFERROR(W2/W15,0) | X20: =IFERROR(X2/X15,0) | Y20: =IFERROR(Y2/Y15,0) | ... BA20: =IFERROR(BA2/BA15,0)
C21: Average Taxiing Time Per Aircraft(min) | D21: float0 | F21: 대당택싱평균 | H21: =VLOOKUP($F21,raw_data_pax!$1:$1048576,MATCH(H$1,raw_data_pax!$1:$1,0),FALSE) | I21: =VLOOKUP($F21,raw_data_pax!$1:$1048576,MATCH(I$1,raw_data_pax!$1:$1,0),FALSE) | J21: =VLOOKUP($F21,raw_data_pax!$1:$1048576,MATCH(J$1,raw_data_pax!$1:$1,0),FALSE) | K21: =VLOOKUP($F21,raw_data_pax!$1:$1048576,MATCH(K$1,raw_data_pax!$1:$1,0),FALSE) | L21: =VLOOKUP($F21,raw_data_pax!$1:$1048576,MATCH(L$1,raw_data_pax!$1:$1,0),FALSE) | M21: =VLOOKUP($F21,raw_data_pax!$1:$1048576,MATCH(M$1,raw_data_pax!$1:$1,0),FALSE) | N21: =VLOOKUP($F21,raw_data_pax!$1:$1048576,MATCH(N$1,raw_data_pax!$1:$1,0),FALSE) | O21: =VLOOKUP($F21,raw_data_pax!$1:$1048576,MATCH(O$1,raw_data_pax!$1:$1,0),FALSE) | ... Q21: =VLOOKUP($F21,raw_data_pax!$1:$1048576,MATCH(Q$1,raw_data_pax!$1:$1,0),FALSE)
C22: Average PeakTime TurnAround Standing Time(min) | D22: float0 | F22: 피크시간 턴어라운드편 평균주기시간(분) | H22: =VLOOKUP($F22,raw_data_pax!$1:$1048576,MATCH(H$1,raw_data_pax!$1:$1,0),FALSE) | I22: =VLOOKUP($F22,raw_data_pax!$1:$1048576,MATCH(I$1,raw_data_pax!$1:$1,0),FALSE) | J22: =VLOOKUP($F22,raw_data_pax!$1:$1048576,MATCH(J$1,raw_data_pax!$1:$1,0),FALSE) | K22: =VLOOKUP($F22,raw_data_pax!$1:$1048576,MATCH(K$1,raw_data_pax!$1:$1,0),FALSE) | L22: =VLOOKUP($F22,raw_data_pax!$1:$1048576,MATCH(L$1,raw_data_pax!$1:$1,0),FALSE) | M22: =VLOOKUP($F22,raw_data_pax!$1:$1048576,MATCH(M$1,raw_data_pax!$1:$1,0),FALSE) | N22: =VLOOKUP($F22,raw_data_pax!$1:$1048576,MATCH(N$1,raw_data_pax!$1:$1,0),FALSE) | O22: =VLOOKUP($F22,raw_data_pax!$1:$1048576,MATCH(O$1,raw_data_pax!$1:$1,0),FALSE) | ... Q22: =VLOOKUP($F22,raw_data_pax!$1:$1048576,MATCH(Q$1,raw_data_pax!$1:$1,0),FALSE)
C23: Average PeakTIme TurnAround Ground Time(min) | D23: float0 | F23: 피크시간 턴어라운드편 평균그라운드시간(분) | H23: =VLOOKUP($F23,raw_data_pax!$1:$1048576,MATCH(H$1,raw_data_pax!$1:$1,0),FALSE) | I23: =VLOOKUP($F23,raw_data_pax!$1:$1048576,MATCH(I$1,raw_data_pax!$1:$1,0),FALSE) | J23: =VLOOKUP($F23,raw_data_pax!$1:$1048576,MATCH(J$1,raw_data_pax!$1:$1,0),FALSE) | K23: =VLOOKUP($F23,raw_data_pax!$1:$1048576,MATCH(K$1,raw_data_pax!$1:$1,0),FALSE) | L23: =VLOOKUP($F23,raw_data_pax!$1:$1048576,MATCH(L$1,raw_data_pax!$1:$1,0),FALSE) | M23: =VLOOKUP($F23,raw_data_pax!$1:$1048576,MATCH(M$1,raw_data_pax!$1:$1,0),FALSE) | N23: =VLOOKUP($F23,raw_data_pax!$1:$1048576,MATCH(N$1,raw_data_pax!$1:$1,0),FALSE) | O23: =VLOOKUP($F23,raw_data_pax!$1:$1048576,MATCH(O$1,raw_data_pax!$1:$1,0),FALSE) | ... Q23: =VLOOKUP($F23,raw_data_pax!$1:$1048576,MATCH(Q$1,raw_data_pax!$1:$1,0),FALSE)
C24: Average TurnAround Standing Time(min) | D24: float0 | F24: 턴어라운드편 평균주기시간(분) | H24: =VLOOKUP($F24,raw_data_pax!$1:$1048576,MATCH(H$1,raw_data_pax!$1:$1,0),FALSE) | I24: =VLOOKUP($F24,raw_data_pax!$1:$1048576,MATCH(I$1,raw_data_pax!$1:$1,0),FALSE) | J24: =VLOOKUP($F24,raw_data_pax!$1:$1048576,MATCH(J$1,raw_data_pax!$1:$1,0),FALSE) | K24: =VLOOKUP($F24,raw_data_pax!$1:$1048576,MATCH(K$1,raw_data_pax!$1:$1,0),FALSE) | L24: =VLOOKUP($F24,raw_data_pax!$1:$1048576,MATCH(L$1,raw_data_pax!$1:$1,0),FALSE) | M24: =VLOOKUP($F24,raw_data_pax!$1:$1048576,MATCH(M$1,raw_data_pax!$1:$1,0),FALSE) | N24: =VLOOKUP($F24,raw_data_pax!$1:$1048576,MATCH(N$1,raw_data_pax!$1:$1,0),FALSE) | O24: =VLOOKUP($F24,raw_data_pax!$1:$1048576,MATCH(O$1,raw_data_pax!$1:$1,0),FALSE) | ... Q24: =VLOOKUP($F24,raw_data_pax!$1:$1048576,MATCH(Q$1,raw_data_pax!$1:$1,0),FALSE)
C25: Average TurnAround Ground Time(min) | D25: float0 | F25: 턴어라운드편 평균그라운드시간(분) | H25: =VLOOKUP($F25,raw_data_pax!$1:$1048576,MATCH(H$1,raw_data_pax!$1:$1,0),FALSE) | I25: =VLOOKUP($F25,raw_data_pax!$1:$1048576,MATCH(I$1,raw_data_pax!$1:$1,0),FALSE) | J25: =VLOOKUP($F25,raw_data_pax!$1:$1048576,MATCH(J$1,raw_data_pax!$1:$1,0),FALSE) | K25: =VLOOKUP($F25,raw_data_pax!$1:$1048576,MATCH(K$1,raw_data_pax!$1:$1,0),FALSE) | L25: =VLOOKUP($F25,raw_data_pax!$1:$1048576,MATCH(L$1,raw_data_pax!$1:$1,0),FALSE) | M25: =VLOOKUP($F25,raw_data_pax!$1:$1048576,MATCH(M$1,raw_data_pax!$1:$1,0),FALSE) | N25: =VLOOKUP($F25,raw_data_pax!$1:$1048576,MATCH(N$1,raw_data_pax!$1:$1,0),FALSE) | O25: =VLOOKUP($F25,raw_data_pax!$1:$1048576,MATCH(O$1,raw_data_pax!$1:$1,0),FALSE) | ... Q25: =VLOOKUP($F25,raw_data_pax!$1:$1048576,MATCH(Q$1,raw_data_pax!$1:$1,0),FALSE)
C26: Average Total Standing Time(min) | D26: float0 | F26: (오버나잇, 소산 포함) 평균주기시간(분) | H26: =VLOOKUP($F26,raw_data_pax!$1:$1048576,MATCH(H$1,raw_data_pax!$1:$1,0),FALSE) | I26: =VLOOKUP($F26,raw_data_pax!$1:$1048576,MATCH(I$1,raw_data_pax!$1:$1,0),FALSE) | J26: =VLOOKUP($F26,raw_data_pax!$1:$1048576,MATCH(J$1,raw_data_pax!$1:$1,0),FALSE) | K26: =VLOOKUP($F26,raw_data_pax!$1:$1048576,MATCH(K$1,raw_data_pax!$1:$1,0),FALSE) | L26: =VLOOKUP($F26,raw_data_pax!$1:$1048576,MATCH(L$1,raw_data_pax!$1:$1,0),FALSE) | M26: =VLOOKUP($F26,raw_data_pax!$1:$1048576,MATCH(M$1,raw_data_pax!$1:$1,0),FALSE) | N26: =VLOOKUP($F26,raw_data_pax!$1:$1048576,MATCH(N$1,raw_data_pax!$1:$1,0),FALSE) | O26: =VLOOKUP($F26,raw_data_pax!$1:$1048576,MATCH(O$1,raw_data_pax!$1:$1,0),FALSE) | ... Q26: =VLOOKUP($F26,raw_data_pax!$1:$1048576,MATCH(Q$1,raw_data_pax!$1:$1,0),FALSE)
C27: Average Total Ground Time(min) | D27: float0 | F27: (오버나잇, 소산 포함) 평균그라운드시간(분) | H27: =VLOOKUP($F27,raw_data_pax!$1:$1048576,MATCH(H$1,raw_data_pax!$1:$1,0),FALSE) | I27: =VLOOKUP($F27,raw_data_pax!$1:$1048576,MATCH(I$1,raw_data_pax!$1:$1,0),FALSE) | J27: =VLOOKUP($F27,raw_data_pax!$1:$1048576,MATCH(J$1,raw_data_pax!$1:$1,0),FALSE) | K27: =VLOOKUP($F27,raw_data_pax!$1:$1048576,MATCH(K$1,raw_data_pax!$1:$1,0),FALSE) | L27: =VLOOKUP($F27,raw_data_pax!$1:$1048576,MATCH(L$1,raw_data_pax!$1:$1,0),FALSE) | M27: =VLOOKUP($F27,raw_data_pax!$1:$1048576,MATCH(M$1,raw_data_pax!$1:$1,0),FALSE) | N27: =VLOOKUP($F27,raw_data_pax!$1:$1048576,MATCH(N$1,raw_data_pax!$1:$1,0),FALSE) | O27: =VLOOKUP($F27,raw_data_pax!$1:$1048576,MATCH(O$1,raw_data_pax!$1:$1,0),FALSE) | ... Q27: =VLOOKUP($F27,raw_data_pax!$1:$1048576,MATCH(Q$1,raw_data_pax!$1:$1,0),FALSE)
C28: Maximum Takeoff Weight Per Aircraft(lb) | D28: float0 | F28: 대당최대이륙중량 | H28: =VLOOKUP($F28,raw_data_pax!$1:$1048576,MATCH(H$1,raw_data_pax!$1:$1,0),FALSE) | I28: =VLOOKUP($F28,raw_data_pax!$1:$1048576,MATCH(I$1,raw_data_pax!$1:$1,0),FALSE) | J28: =VLOOKUP($F28,raw_data_pax!$1:$1048576,MATCH(J$1,raw_data_pax!$1:$1,0),FALSE) | K28: =VLOOKUP($F28,raw_data_pax!$1:$1048576,MATCH(K$1,raw_data_pax!$1:$1,0),FALSE) | L28: =VLOOKUP($F28,raw_data_pax!$1:$1048576,MATCH(L$1,raw_data_pax!$1:$1,0),FALSE) | M28: =VLOOKUP($F28,raw_data_pax!$1:$1048576,MATCH(M$1,raw_data_pax!$1:$1,0),FALSE) | N28: =VLOOKUP($F28,raw_data_pax!$1:$1048576,MATCH(N$1,raw_data_pax!$1:$1,0),FALSE) | O28: =VLOOKUP($F28,raw_data_pax!$1:$1048576,MATCH(O$1,raw_data_pax!$1:$1,0),FALSE) | ... Q28: =VLOOKUP($F28,raw_data_pax!$1:$1048576,MATCH(Q$1,raw_data_pax!$1:$1,0),FALSE)
C29: Average Flight Distance(km) | D29: float0 | F29: 비행거리평균(km) | H29: =VLOOKUP($F29,raw_data_pax!$1:$1048576,MATCH(H$1,raw_data_pax!$1:$1,0),FALSE) | I29: =VLOOKUP($F29,raw_data_pax!$1:$1048576,MATCH(I$1,raw_data_pax!$1:$1,0),FALSE) | J29: =VLOOKUP($F29,raw_data_pax!$1:$1048576,MATCH(J$1,raw_data_pax!$1:$1,0),FALSE) | K29: =VLOOKUP($F29,raw_data_pax!$1:$1048576,MATCH(K$1,raw_data_pax!$1:$1,0),FALSE) | L29: =VLOOKUP($F29,raw_data_pax!$1:$1048576,MATCH(L$1,raw_data_pax!$1:$1,0),FALSE) | M29: =VLOOKUP($F29,raw_data_pax!$1:$1048576,MATCH(M$1,raw_data_pax!$1:$1,0),FALSE) | N29: =VLOOKUP($F29,raw_data_pax!$1:$1048576,MATCH(N$1,raw_data_pax!$1:$1,0),FALSE) | O29: =VLOOKUP($F29,raw_data_pax!$1:$1048576,MATCH(O$1,raw_data_pax!$1:$1,0),FALSE) | ... Q29: =VLOOKUP($F29,raw_data_pax!$1:$1048576,MATCH(Q$1,raw_data_pax!$1:$1,0),FALSE)
C30: Payload Per Aircraft | D30: float0 | F30: 대당유상탑재중량 | H30: =VLOOKUP($F30,raw_data_pax!$1:$1048576,MATCH(H$1,raw_data_pax!$1:$1,0),FALSE) | I30: =VLOOKUP($F30,raw_data_pax!$1:$1048576,MATCH(I$1,raw_data_pax!$1:$1,0),FALSE) | J30: =VLOOKUP($F30,raw_data_pax!$1:$1048576,MATCH(J$1,raw_data_pax!$1:$1,0),FALSE) | K30: =VLOOKUP($F30,raw_data_pax!$1:$1048576,MATCH(K$1,raw_data_pax!$1:$1,0),FALSE) | L30: =VLOOKUP($F30,raw_data_pax!$1:$1048576,MATCH(L$1,raw_data_pax!$1:$1,0),FALSE) | M30: =VLOOKUP($F30,raw_data_pax!$1:$1048576,MATCH(M$1,raw_data_pax!$1:$1,0),FALSE) | N30: =VLOOKUP($F30,raw_data_pax!$1:$1048576,MATCH(N$1,raw_data_pax!$1:$1,0),FALSE) | O30: =VLOOKUP($F30,raw_data_pax!$1:$1048576,MATCH(O$1,raw_data_pax!$1:$1,0),FALSE) | ... Q30: =VLOOKUP($F30,raw_data_pax!$1:$1048576,MATCH(Q$1,raw_data_pax!$1:$1,0),FALSE)
A31: Flight Class Index | B31: FleetMIx | C31: =C151&"FleetMix📝" | D31: percent1 | E31: O | F31: =C151&"혼합율" | G31: =IFERROR(SUMIF($H$162:$Q$162,"O",H31:Q31)/COUNTIFS($H$162:$Q$162,"O",H31:Q31,"<>0"),0) | H31: =VLOOKUP($F31,raw_data_pax!$1:$1048576,MATCH(H$1,raw_data_pax!$1:$1,0),FALSE) | I31: =VLOOKUP($F31,raw_data_pax!$1:$1048576,MATCH(I$1,raw_data_pax!$1:$1,0),FALSE) | J31: =VLOOKUP($F31,raw_data_pax!$1:$1048576,MATCH(J$1,raw_data_pax!$1:$1,0),FALSE) | K31: =VLOOKUP($F31,raw_data_pax!$1:$1048576,MATCH(K$1,raw_data_pax!$1:$1,0),FALSE) | L31: =VLOOKUP($F31,raw_data_pax!$1:$1048576,MATCH(L$1,raw_data_pax!$1:$1,0),FALSE) | M31: =VLOOKUP($F31,raw_data_pax!$1:$1048576,MATCH(M$1,raw_data_pax!$1:$1,0),FALSE) | N31: =VLOOKUP($F31,raw_data_pax!$1:$1048576,MATCH(N$1,raw_data_pax!$1:$1,0),FALSE) | O31: =VLOOKUP($F31,raw_data_pax!$1:$1048576,MATCH(O$1,raw_data_pax!$1:$1,0),FALSE) | ... Q31: =VLOOKUP($F31,raw_data_pax!$1:$1048576,MATCH(Q$1,raw_data_pax!$1:$1,0),FALSE) | R31: =G31 | S31: =R31 | T31: =S31 | U31: =T31 | V31: =U31 | W31: =V31 | X31: =W31 | Y31: =X31 | Z31: =Y31 | ... BA31: =AZ31
C32: =C152&"FleetMix📝" | D32: percent1 | E32: O | F32: =C152&"혼합율" | G32: =IFERROR(SUMIF($H$162:$Q$162,"O",H32:Q32)/COUNTIFS($H$162:$Q$162,"O",H32:Q32,"<>0"),0) | H32: =VLOOKUP($F32,raw_data_pax!$1:$1048576,MATCH(H$1,raw_data_pax!$1:$1,0),FALSE) | I32: =VLOOKUP($F32,raw_data_pax!$1:$1048576,MATCH(I$1,raw_data_pax!$1:$1,0),FALSE) | J32: =VLOOKUP($F32,raw_data_pax!$1:$1048576,MATCH(J$1,raw_data_pax!$1:$1,0),FALSE) | K32: =VLOOKUP($F32,raw_data_pax!$1:$1048576,MATCH(K$1,raw_data_pax!$1:$1,0),FALSE) | L32: =VLOOKUP($F32,raw_data_pax!$1:$1048576,MATCH(L$1,raw_data_pax!$1:$1,0),FALSE) | M32: =VLOOKUP($F32,raw_data_pax!$1:$1048576,MATCH(M$1,raw_data_pax!$1:$1,0),FALSE) | N32: =VLOOKUP($F32,raw_data_pax!$1:$1048576,MATCH(N$1,raw_data_pax!$1:$1,0),FALSE) | O32: =VLOOKUP($F32,raw_data_pax!$1:$1048576,MATCH(O$1,raw_data_pax!$1:$1,0),FALSE) | ... Q32: =VLOOKUP($F32,raw_data_pax!$1:$1048576,MATCH(Q$1,raw_data_pax!$1:$1,0),FALSE) | R32: =G32 | S32: =R32 | T32: =S32 | U32: =T32 | V32: =U32 | W32: =V32 | X32: =W32 | Y32: =X32 | Z32: =Y32 | ... BA32: =AZ32
C33: =C153&"FleetMix📝" | D33: percent1 | E33: O | F33: =C153&"혼합율" | G33: =IFERROR(SUMIF($H$162:$Q$162,"O",H33:Q33)/COUNTIFS($H$162:$Q$162,"O",H33:Q33,"<>0"),0) | H33: =VLOOKUP($F33,raw_data_pax!$1:$1048576,MATCH(H$1,raw_data_pax!$1:$1,0),FALSE) | I33: =VLOOKUP($F33,raw_data_pax!$1:$1048576,MATCH(I$1,raw_data_pax!$1:$1,0),FALSE) | J33: =VLOOKUP($F33,raw_data_pax!$1:$1048576,MATCH(J$1,raw_data_pax!$1:$1,0),FALSE) | K33: =VLOOKUP($F33,raw_data_pax!$1:$1048576,MATCH(K$1,raw_data_pax!$1:$1,0),FALSE) | L33: =VLOOKUP($F33,raw_data_pax!$1:$1048576,MATCH(L$1,raw_data_pax!$1:$1,0),FALSE) | M33: =VLOOKUP($F33,raw_data_pax!$1:$1048576,MATCH(M$1,raw_data_pax!$1:$1,0),FALSE) | N33: =VLOOKUP($F33,raw_data_pax!$1:$1048576,MATCH(N$1,raw_data_pax!$1:$1,0),FALSE) | O33: =VLOOKUP($F33,raw_data_pax!$1:$1048576,MATCH(O$1,raw_data_pax!$1:$1,0),FALSE) | ... Q33: =VLOOKUP($F33,raw_data_pax!$1:$1048576,MATCH(Q$1,raw_data_pax!$1:$1,0),FALSE) | R33: =G33 | S33: =R33 | T33: =S33 | U33: =T33 | V33: =U33 | W33: =V33 | X33: =W33 | Y33: =X33 | Z33: =Y33 | ... BA33: =AZ33
C34: =C154&"FleetMix📝" | D34: percent1 | E34: O | F34: =C154&"혼합율" | G34: =IFERROR(SUMIF($H$162:$Q$162,"O",H34:Q34)/COUNTIFS($H$162:$Q$162,"O",H34:Q34,"<>0"),0) | H34: =VLOOKUP($F34,raw_data_pax!$1:$1048576,MATCH(H$1,raw_data_pax!$1:$1,0),FALSE) | I34: =VLOOKUP($F34,raw_data_pax!$1:$1048576,MATCH(I$1,raw_data_pax!$1:$1,0),FALSE) | J34: =VLOOKUP($F34,raw_data_pax!$1:$1048576,MATCH(J$1,raw_data_pax!$1:$1,0),FALSE) | K34: =VLOOKUP($F34,raw_data_pax!$1:$1048576,MATCH(K$1,raw_data_pax!$1:$1,0),FALSE) | L34: =VLOOKUP($F34,raw_data_pax!$1:$1048576,MATCH(L$1,raw_data_pax!$1:$1,0),FALSE) | M34: =VLOOKUP($F34,raw_data_pax!$1:$1048576,MATCH(M$1,raw_data_pax!$1:$1,0),FALSE) | N34: =VLOOKUP($F34,raw_data_pax!$1:$1048576,MATCH(N$1,raw_data_pax!$1:$1,0),FALSE) | O34: =VLOOKUP($F34,raw_data_pax!$1:$1048576,MATCH(O$1,raw_data_pax!$1:$1,0),FALSE) | ... Q34: =VLOOKUP($F34,raw_data_pax!$1:$1048576,MATCH(Q$1,raw_data_pax!$1:$1,0),FALSE) | R34: =G34 | S34: =R34 | T34: =S34 | U34: =T34 | V34: =U34 | W34: =V34 | X34: =W34 | Y34: =X34 | Z34: =Y34 | ... BA34: =AZ34
B35: Movements by Class | C35: =C151&"Movements" | D35: float0 | F35: =C151&"운항횟수" | H35: =VLOOKUP($F35,raw_data_pax!$1:$1048576,MATCH(H$1,raw_data_pax!$1:$1,0),FALSE) | I35: =VLOOKUP($F35,raw_data_pax!$1:$1048576,MATCH(I$1,raw_data_pax!$1:$1,0),FALSE) | J35: =VLOOKUP($F35,raw_data_pax!$1:$1048576,MATCH(J$1,raw_data_pax!$1:$1,0),FALSE) | K35: =VLOOKUP($F35,raw_data_pax!$1:$1048576,MATCH(K$1,raw_data_pax!$1:$1,0),FALSE) | L35: =VLOOKUP($F35,raw_data_pax!$1:$1048576,MATCH(L$1,raw_data_pax!$1:$1,0),FALSE) | M35: =VLOOKUP($F35,raw_data_pax!$1:$1048576,MATCH(M$1,raw_data_pax!$1:$1,0),FALSE) | N35: =VLOOKUP($F35,raw_data_pax!$1:$1048576,MATCH(N$1,raw_data_pax!$1:$1,0),FALSE) | O35: =VLOOKUP($F35,raw_data_pax!$1:$1048576,MATCH(O$1,raw_data_pax!$1:$1,0),FALSE) | ... Q35: =VLOOKUP($F35,raw_data_pax!$1:$1048576,MATCH(Q$1,raw_data_pax!$1:$1,0),FALSE) | R35: =R20*R31 | S35: =S20*S31 | T35: =T20*T31 | U35: =U20*U31 | V35: =V20*V31 | W35: =W20*W31 | X35: =X20*X31 | Y35: =Y20*Y31 | ... BA35: =BA20*BA31
C36: =C152&"Movements" | D36: float0 | F36: =C152&"운항횟수" | H36: =VLOOKUP($F36,raw_data_pax!$1:$1048576,MATCH(H$1,raw_data_pax!$1:$1,0),FALSE) | I36: =VLOOKUP($F36,raw_data_pax!$1:$1048576,MATCH(I$1,raw_data_pax!$1:$1,0),FALSE) | J36: =VLOOKUP($F36,raw_data_pax!$1:$1048576,MATCH(J$1,raw_data_pax!$1:$1,0),FALSE) | K36: =VLOOKUP($F36,raw_data_pax!$1:$1048576,MATCH(K$1,raw_data_pax!$1:$1,0),FALSE) | L36: =VLOOKUP($F36,raw_data_pax!$1:$1048576,MATCH(L$1,raw_data_pax!$1:$1,0),FALSE) | M36: =VLOOKUP($F36,raw_data_pax!$1:$1048576,MATCH(M$1,raw_data_pax!$1:$1,0),FALSE) | N36: =VLOOKUP($F36,raw_data_pax!$1:$1048576,MATCH(N$1,raw_data_pax!$1:$1,0),FALSE) | O36: =VLOOKUP($F36,raw_data_pax!$1:$1048576,MATCH(O$1,raw_data_pax!$1:$1,0),FALSE) | ... Q36: =VLOOKUP($F36,raw_data_pax!$1:$1048576,MATCH(Q$1,raw_data_pax!$1:$1,0),FALSE) | R36: =R20*R32 | S36: =S20*S32 | T36: =T20*T32 | U36: =U20*U32 | V36: =V20*V32 | W36: =W20*W32 | X36: =X20*X32 | Y36: =Y20*Y32 | ... BA36: =BA20*BA32
C37: =C153&"Movements" | D37: float0 | F37: =C153&"운항횟수" | H37: =VLOOKUP($F37,raw_data_pax!$1:$1048576,MATCH(H$1,raw_data_pax!$1:$1,0),FALSE) | I37: =VLOOKUP($F37,raw_data_pax!$1:$1048576,MATCH(I$1,raw_data_pax!$1:$1,0),FALSE) | J37: =VLOOKUP($F37,raw_data_pax!$1:$1048576,MATCH(J$1,raw_data_pax!$1:$1,0),FALSE) | K37: =VLOOKUP($F37,raw_data_pax!$1:$1048576,MATCH(K$1,raw_data_pax!$1:$1,0),FALSE) | L37: =VLOOKUP($F37,raw_data_pax!$1:$1048576,MATCH(L$1,raw_data_pax!$1:$1,0),FALSE) | M37: =VLOOKUP($F37,raw_data_pax!$1:$1048576,MATCH(M$1,raw_data_pax!$1:$1,0),FALSE) | N37: =VLOOKUP($F37,raw_data_pax!$1:$1048576,MATCH(N$1,raw_data_pax!$1:$1,0),FALSE) | O37: =VLOOKUP($F37,raw_data_pax!$1:$1048576,MATCH(O$1,raw_data_pax!$1:$1,0),FALSE) | ... Q37: =VLOOKUP($F37,raw_data_pax!$1:$1048576,MATCH(Q$1,raw_data_pax!$1:$1,0),FALSE) | R37: =R20*R33 | S37: =S20*S33 | T37: =T20*T33 | U37: =U20*U33 | V37: =V20*V33 | W37: =W20*W33 | X37: =X20*X33 | Y37: =Y20*Y33 | ... BA37: =BA20*BA33
C38: =C154&"Movements" | D38: float0 | F38: =C154&"운항횟수" | H38: =VLOOKUP($F38,raw_data_pax!$1:$1048576,MATCH(H$1,raw_data_pax!$1:$1,0),FALSE) | I38: =VLOOKUP($F38,raw_data_pax!$1:$1048576,MATCH(I$1,raw_data_pax!$1:$1,0),FALSE) | J38: =VLOOKUP($F38,raw_data_pax!$1:$1048576,MATCH(J$1,raw_data_pax!$1:$1,0),FALSE) | K38: =VLOOKUP($F38,raw_data_pax!$1:$1048576,MATCH(K$1,raw_data_pax!$1:$1,0),FALSE) | L38: =VLOOKUP($F38,raw_data_pax!$1:$1048576,MATCH(L$1,raw_data_pax!$1:$1,0),FALSE) | M38: =VLOOKUP($F38,raw_data_pax!$1:$1048576,MATCH(M$1,raw_data_pax!$1:$1,0),FALSE) | N38: =VLOOKUP($F38,raw_data_pax!$1:$1048576,MATCH(N$1,raw_data_pax!$1:$1,0),FALSE) | O38: =VLOOKUP($F38,raw_data_pax!$1:$1048576,MATCH(O$1,raw_data_pax!$1:$1,0),FALSE) | ... Q38: =VLOOKUP($F38,raw_data_pax!$1:$1048576,MATCH(Q$1,raw_data_pax!$1:$1,0),FALSE) | R38: =R20*R34 | S38: =S20*S34 | T38: =T20*T34 | U38: =U20*U34 | V38: =V20*V34 | W38: =W20*W34 | X38: =X20*X34 | Y38: =Y20*Y34 | ... BA38: =BA20*BA34
B39: MTOW by Class | C39: =C151&"MTOW" | D39: float0 | F39: =C151&"대당최대이륙중량" | G39: =IFERROR(SUMIF($H$172:$Q$172,"O",H39:Q39)/COUNTIFS($H$172:$Q$172,"O",H39:Q39,"<>0"),0) | H39: =VLOOKUP($F39,raw_data_pax!$1:$1048576,MATCH(H$1,raw_data_pax!$1:$1,0),FALSE) | I39: =VLOOKUP($F39,raw_data_pax!$1:$1048576,MATCH(I$1,raw_data_pax!$1:$1,0),FALSE) | J39: =VLOOKUP($F39,raw_data_pax!$1:$1048576,MATCH(J$1,raw_data_pax!$1:$1,0),FALSE) | K39: =VLOOKUP($F39,raw_data_pax!$1:$1048576,MATCH(K$1,raw_data_pax!$1:$1,0),FALSE) | L39: =VLOOKUP($F39,raw_data_pax!$1:$1048576,MATCH(L$1,raw_data_pax!$1:$1,0),FALSE) | M39: =VLOOKUP($F39,raw_data_pax!$1:$1048576,MATCH(M$1,raw_data_pax!$1:$1,0),FALSE) | N39: =VLOOKUP($F39,raw_data_pax!$1:$1048576,MATCH(N$1,raw_data_pax!$1:$1,0),FALSE) | O39: =VLOOKUP($F39,raw_data_pax!$1:$1048576,MATCH(O$1,raw_data_pax!$1:$1,0),FALSE) | ... Q39: =VLOOKUP($F39,raw_data_pax!$1:$1048576,MATCH(Q$1,raw_data_pax!$1:$1,0),FALSE) | R39: =G39 | S39: =R39 | T39: =S39 | U39: =T39 | V39: =U39 | W39: =V39 | X39: =W39 | Y39: =X39 | Z39: =Y39 | ... BA39: =AZ39
C40: =C152&"MTOW" | D40: float0 | F40: =C152&"대당최대이륙중량" | G40: =IFERROR(SUMIF($H$172:$Q$172,"O",H40:Q40)/COUNTIFS($H$172:$Q$172,"O",H40:Q40,"<>0"),0) | H40: =VLOOKUP($F40,raw_data_pax!$1:$1048576,MATCH(H$1,raw_data_pax!$1:$1,0),FALSE) | I40: =VLOOKUP($F40,raw_data_pax!$1:$1048576,MATCH(I$1,raw_data_pax!$1:$1,0),FALSE) | J40: =VLOOKUP($F40,raw_data_pax!$1:$1048576,MATCH(J$1,raw_data_pax!$1:$1,0),FALSE) | K40: =VLOOKUP($F40,raw_data_pax!$1:$1048576,MATCH(K$1,raw_data_pax!$1:$1,0),FALSE) | L40: =VLOOKUP($F40,raw_data_pax!$1:$1048576,MATCH(L$1,raw_data_pax!$1:$1,0),FALSE) | M40: =VLOOKUP($F40,raw_data_pax!$1:$1048576,MATCH(M$1,raw_data_pax!$1:$1,0),FALSE) | N40: =VLOOKUP($F40,raw_data_pax!$1:$1048576,MATCH(N$1,raw_data_pax!$1:$1,0),FALSE) | O40: =VLOOKUP($F40,raw_data_pax!$1:$1048576,MATCH(O$1,raw_data_pax!$1:$1,0),FALSE) | ... Q40: =VLOOKUP($F40,raw_data_pax!$1:$1048576,MATCH(Q$1,raw_data_pax!$1:$1,0),FALSE) | R40: =G40 | S40: =R40 | T40: =S40 | U40: =T40 | V40: =U40 | W40: =V40 | X40: =W40 | Y40: =X40 | Z40: =Y40 | ... BA40: =AZ40
C41: =C153&"MTOW" | D41: float0 | F41: =C153&"대당최대이륙중량" | G41: =IFERROR(SUMIF($H$172:$Q$172,"O",H41:Q41)/COUNTIFS($H$172:$Q$172,"O",H41:Q41,"<>0"),0) | H41: =VLOOKUP($F41,raw_data_pax!$1:$1048576,MATCH(H$1,raw_data_pax!$1:$1,0),FALSE) | I41: =VLOOKUP($F41,raw_data_pax!$1:$1048576,MATCH(I$1,raw_data_pax!$1:$1,0),FALSE) | J41: =VLOOKUP($F41,raw_data_pax!$1:$1048576,MATCH(J$1,raw_data_pax!$1:$1,0),FALSE) | K41: =VLOOKUP($F41,raw_data_pax!$1:$1048576,MATCH(K$1,raw_data_pax!$1:$1,0),FALSE) | L41: =VLOOKUP($F41,raw_data_pax!$1:$1048576,MATCH(L$1,raw_data_pax!$1:$1,0),FALSE) | M41: =VLOOKUP($F41,raw_data_pax!$1:$1048576,MATCH(M$1,raw_data_pax!$1:$1,0),FALSE) | N41: =VLOOKUP($F41,raw_data_pax!$1:$1048576,MATCH(N$1,raw_data_pax!$1:$1,0),FALSE) | O41: =VLOOKUP($F41,raw_data_pax!$1:$1048576,MATCH(O$1,raw_data_pax!$1:$1,0),FALSE) | ... Q41: =VLOOKUP($F41,raw_data_pax!$1:$1048576,MATCH(Q$1,raw_data_pax!$1:$1,0),FALSE) | R41: =G41 | S41: =R41 | T41: =S41 | U41: =T41 | V41: =U41 | W41: =V41 | X41: =W41 | Y41: =X41 | Z41: =Y41 | ... BA41: =AZ41
C42: =C154&"MTOW" | D42: float0 | F42: =C154&"대당최대이륙중량" | G42: =IFERROR(SUMIF($H$172:$Q$172,"O",H42:Q42)/COUNTIFS($H$172:$Q$172,"O",H42:Q42,"<>0"),0) | H42: =VLOOKUP($F42,raw_data_pax!$1:$1048576,MATCH(H$1,raw_data_pax!$1:$1,0),FALSE) | I42: =VLOOKUP($F42,raw_data_pax!$1:$1048576,MATCH(I$1,raw_data_pax!$1:$1,0),FALSE) | J42: =VLOOKUP($F42,raw_data_pax!$1:$1048576,MATCH(J$1,raw_data_pax!$1:$1,0),FALSE) | K42: =VLOOKUP($F42,raw_data_pax!$1:$1048576,MATCH(K$1,raw_data_pax!$1:$1,0),FALSE) | L42: =VLOOKUP($F42,raw_data_pax!$1:$1048576,MATCH(L$1,raw_data_pax!$1:$1,0),FALSE) | M42: =VLOOKUP($F42,raw_data_pax!$1:$1048576,MATCH(M$1,raw_data_pax!$1:$1,0),FALSE) | N42: =VLOOKUP($F42,raw_data_pax!$1:$1048576,MATCH(N$1,raw_data_pax!$1:$1,0),FALSE) | O42: =VLOOKUP($F42,raw_data_pax!$1:$1048576,MATCH(O$1,raw_data_pax!$1:$1,0),FALSE) | ... Q42: =VLOOKUP($F42,raw_data_pax!$1:$1048576,MATCH(Q$1,raw_data_pax!$1:$1,0),FALSE) | R42: =G42 | S42: =R42 | T42: =S42 | U42: =T42 | V42: =U42 | W42: =V42 | X42: =W42 | Y42: =X42 | Z42: =Y42 | ... BA42: =AZ42
B43: Standing Time by Class | C43: =C151&"Average PeakTime TurnAround Standing Time📝" | D43: float0 | E43: O | F43: =C151&"피크시간 턴어라운드편 평균주기시간(분)" | G43: =IFERROR(SUMIF($H$173:$Q$173,"O",H43:Q43)/COUNTIFS($H$173:$Q$173,"O",H43:Q43,"<>0"),0) | H43: =VLOOKUP($F43,raw_data_pax!$1:$1048576,MATCH(H$1,raw_data_pax!$1:$1,0),FALSE) | I43: =VLOOKUP($F43,raw_data_pax!$1:$1048576,MATCH(I$1,raw_data_pax!$1:$1,0),FALSE) | J43: =VLOOKUP($F43,raw_data_pax!$1:$1048576,MATCH(J$1,raw_data_pax!$1:$1,0),FALSE) | K43: =VLOOKUP($F43,raw_data_pax!$1:$1048576,MATCH(K$1,raw_data_pax!$1:$1,0),FALSE) | L43: =VLOOKUP($F43,raw_data_pax!$1:$1048576,MATCH(L$1,raw_data_pax!$1:$1,0),FALSE) | M43: =VLOOKUP($F43,raw_data_pax!$1:$1048576,MATCH(M$1,raw_data_pax!$1:$1,0),FALSE) | N43: =VLOOKUP($F43,raw_data_pax!$1:$1048576,MATCH(N$1,raw_data_pax!$1:$1,0),FALSE) | O43: =VLOOKUP($F43,raw_data_pax!$1:$1048576,MATCH(O$1,raw_data_pax!$1:$1,0),FALSE) | ... Q43: =VLOOKUP($F43,raw_data_pax!$1:$1048576,MATCH(Q$1,raw_data_pax!$1:$1,0),FALSE) | R43: =G43 | S43: =R43 | T43: =S43 | U43: =T43 | V43: =U43 | W43: =V43 | X43: =W43 | Y43: =X43 | Z43: =Y43 | ... BA43: =AZ43
C44: =C152&"Average PeakTime TurnAround Standing Time📝" | D44: float0 | E44: O | F44: =C152&"피크시간 턴어라운드편 평균주기시간(분)" | G44: =IFERROR(SUMIF($H$173:$Q$173,"O",H44:Q44)/COUNTIFS($H$173:$Q$173,"O",H44:Q44,"<>0"),0) | H44: =VLOOKUP($F44,raw_data_pax!$1:$1048576,MATCH(H$1,raw_data_pax!$1:$1,0),FALSE) | I44: =VLOOKUP($F44,raw_data_pax!$1:$1048576,MATCH(I$1,raw_data_pax!$1:$1,0),FALSE) | J44: =VLOOKUP($F44,raw_data_pax!$1:$1048576,MATCH(J$1,raw_data_pax!$1:$1,0),FALSE) | K44: =VLOOKUP($F44,raw_data_pax!$1:$1048576,MATCH(K$1,raw_data_pax!$1:$1,0),FALSE) | L44: =VLOOKUP($F44,raw_data_pax!$1:$1048576,MATCH(L$1,raw_data_pax!$1:$1,0),FALSE) | M44: =VLOOKUP($F44,raw_data_pax!$1:$1048576,MATCH(M$1,raw_data_pax!$1:$1,0),FALSE) | N44: =VLOOKUP($F44,raw_data_pax!$1:$1048576,MATCH(N$1,raw_data_pax!$1:$1,0),FALSE) | O44: =VLOOKUP($F44,raw_data_pax!$1:$1048576,MATCH(O$1,raw_data_pax!$1:$1,0),FALSE) | ... Q44: =VLOOKUP($F44,raw_data_pax!$1:$1048576,MATCH(Q$1,raw_data_pax!$1:$1,0),FALSE) | R44: =G44 | S44: =R44 | T44: =S44 | U44: =T44 | V44: =U44 | W44: =V44 | X44: =W44 | Y44: =X44 | Z44: =Y44 | ... BA44: =AZ44
C45: =C153&"Average PeakTime TurnAround Standing Time📝" | D45: float0 | E45: O | F45: =C153&"피크시간 턴어라운드편 평균주기시간(분)" | G45: =IFERROR(SUMIF($H$173:$Q$173,"O",H45:Q45)/COUNTIFS($H$173:$Q$173,"O",H45:Q45,"<>0"),0) | H45: =VLOOKUP($F45,raw_data_pax!$1:$1048576,MATCH(H$1,raw_data_pax!$1:$1,0),FALSE) | I45: =VLOOKUP($F45,raw_data_pax!$1:$1048576,MATCH(I$1,raw_data_pax!$1:$1,0),FALSE) | J45: =VLOOKUP($F45,raw_data_pax!$1:$1048576,MATCH(J$1,raw_data_pax!$1:$1,0),FALSE) | K45: =VLOOKUP($F45,raw_data_pax!$1:$1048576,MATCH(K$1,raw_data_pax!$1:$1,0),FALSE) | L45: =VLOOKUP($F45,raw_data_pax!$1:$1048576,MATCH(L$1,raw_data_pax!$1:$1,0),FALSE) | M45: =VLOOKUP($F45,raw_data_pax!$1:$1048576,MATCH(M$1,raw_data_pax!$1:$1,0),FALSE) | N45: =VLOOKUP($F45,raw_data_pax!$1:$1048576,MATCH(N$1,raw_data_pax!$1:$1,0),FALSE) | O45: =VLOOKUP($F45,raw_data_pax!$1:$1048576,MATCH(O$1,raw_data_pax!$1:$1,0),FALSE) | ... Q45: =VLOOKUP($F45,raw_data_pax!$1:$1048576,MATCH(Q$1,raw_data_pax!$1:$1,0),FALSE) | R45: =G45 | S45: =R45 | T45: =S45 | U45: =T45 | V45: =U45 | W45: =V45 | X45: =W45 | Y45: =X45 | Z45: =Y45 | ... BA45: =AZ45
C46: =C154&"Average PeakTime TurnAround Standing Time📝" | D46: float0 | E46: O | F46: =C154&"피크시간 턴어라운드편 평균주기시간(분)" | G46: =IFERROR(SUMIF($H$173:$Q$173,"O",H46:Q46)/COUNTIFS($H$173:$Q$173,"O",H46:Q46,"<>0"),0) | H46: =VLOOKUP($F46,raw_data_pax!$1:$1048576,MATCH(H$1,raw_data_pax!$1:$1,0),FALSE) | I46: =VLOOKUP($F46,raw_data_pax!$1:$1048576,MATCH(I$1,raw_data_pax!$1:$1,0),FALSE) | J46: =VLOOKUP($F46,raw_data_pax!$1:$1048576,MATCH(J$1,raw_data_pax!$1:$1,0),FALSE) | K46: =VLOOKUP($F46,raw_data_pax!$1:$1048576,MATCH(K$1,raw_data_pax!$1:$1,0),FALSE) | L46: =VLOOKUP($F46,raw_data_pax!$1:$1048576,MATCH(L$1,raw_data_pax!$1:$1,0),FALSE) | M46: =VLOOKUP($F46,raw_data_pax!$1:$1048576,MATCH(M$1,raw_data_pax!$1:$1,0),FALSE) | N46: =VLOOKUP($F46,raw_data_pax!$1:$1048576,MATCH(N$1,raw_data_pax!$1:$1,0),FALSE) | O46: =VLOOKUP($F46,raw_data_pax!$1:$1048576,MATCH(O$1,raw_data_pax!$1:$1,0),FALSE) | ... Q46: =VLOOKUP($F46,raw_data_pax!$1:$1048576,MATCH(Q$1,raw_data_pax!$1:$1,0),FALSE) | R46: =G46 | S46: =R46 | T46: =S46 | U46: =T46 | V46: =U46 | W46: =V46 | X46: =W46 | Y46: =X46 | Z46: =Y46 | ... BA46: =AZ46
B47: Standing(Total) Time by Class | C47: =C151&"Average Peak Standing Time📝" | D47: float0 | E47: O | F47: =C151&"(오버나잇, 소산 포함) 피크시간 평균주기시간(분)" | G47: =IFERROR(SUMIF($H$173:$Q$173,"O",H47:Q47)/COUNTIFS($H$173:$Q$173,"O",H47:Q47,"<>0"),0) | H47: =VLOOKUP($F47,raw_data_pax!$1:$1048576,MATCH(H$1,raw_data_pax!$1:$1,0),FALSE) | I47: =VLOOKUP($F47,raw_data_pax!$1:$1048576,MATCH(I$1,raw_data_pax!$1:$1,0),FALSE) | J47: =VLOOKUP($F47,raw_data_pax!$1:$1048576,MATCH(J$1,raw_data_pax!$1:$1,0),FALSE) | K47: =VLOOKUP($F47,raw_data_pax!$1:$1048576,MATCH(K$1,raw_data_pax!$1:$1,0),FALSE) | L47: =VLOOKUP($F47,raw_data_pax!$1:$1048576,MATCH(L$1,raw_data_pax!$1:$1,0),FALSE) | M47: =VLOOKUP($F47,raw_data_pax!$1:$1048576,MATCH(M$1,raw_data_pax!$1:$1,0),FALSE) | N47: =VLOOKUP($F47,raw_data_pax!$1:$1048576,MATCH(N$1,raw_data_pax!$1:$1,0),FALSE) | O47: =VLOOKUP($F47,raw_data_pax!$1:$1048576,MATCH(O$1,raw_data_pax!$1:$1,0),FALSE) | ... Q47: =VLOOKUP($F47,raw_data_pax!$1:$1048576,MATCH(Q$1,raw_data_pax!$1:$1,0),FALSE) | R47: =G47 | S47: =R47 | T47: =S47 | U47: =T47 | V47: =U47 | W47: =V47 | X47: =W47 | Y47: =X47 | Z47: =Y47 | ... BA47: =AZ47
C48: =C152&"Average Peak Standing Time📝" | D48: float0 | E48: O | F48: =C152&"(오버나잇, 소산 포함) 피크시간 평균주기시간(분)" | G48: =IFERROR(SUMIF($H$173:$Q$173,"O",H48:Q48)/COUNTIFS($H$173:$Q$173,"O",H48:Q48,"<>0"),0) | H48: =VLOOKUP($F48,raw_data_pax!$1:$1048576,MATCH(H$1,raw_data_pax!$1:$1,0),FALSE) | I48: =VLOOKUP($F48,raw_data_pax!$1:$1048576,MATCH(I$1,raw_data_pax!$1:$1,0),FALSE) | J48: =VLOOKUP($F48,raw_data_pax!$1:$1048576,MATCH(J$1,raw_data_pax!$1:$1,0),FALSE) | K48: =VLOOKUP($F48,raw_data_pax!$1:$1048576,MATCH(K$1,raw_data_pax!$1:$1,0),FALSE) | L48: =VLOOKUP($F48,raw_data_pax!$1:$1048576,MATCH(L$1,raw_data_pax!$1:$1,0),FALSE) | M48: =VLOOKUP($F48,raw_data_pax!$1:$1048576,MATCH(M$1,raw_data_pax!$1:$1,0),FALSE) | N48: =VLOOKUP($F48,raw_data_pax!$1:$1048576,MATCH(N$1,raw_data_pax!$1:$1,0),FALSE) | O48: =VLOOKUP($F48,raw_data_pax!$1:$1048576,MATCH(O$1,raw_data_pax!$1:$1,0),FALSE) | ... Q48: =VLOOKUP($F48,raw_data_pax!$1:$1048576,MATCH(Q$1,raw_data_pax!$1:$1,0),FALSE) | R48: =G48 | S48: =R48 | T48: =S48 | U48: =T48 | V48: =U48 | W48: =V48 | X48: =W48 | Y48: =X48 | Z48: =Y48 | ... BA48: =AZ48
C49: =C153&"Average Peak Standing Time📝" | D49: float0 | E49: O | F49: =C153&"(오버나잇, 소산 포함) 피크시간 평균주기시간(분)" | G49: =IFERROR(SUMIF($H$173:$Q$173,"O",H49:Q49)/COUNTIFS($H$173:$Q$173,"O",H49:Q49,"<>0"),0) | H49: =VLOOKUP($F49,raw_data_pax!$1:$1048576,MATCH(H$1,raw_data_pax!$1:$1,0),FALSE) | I49: =VLOOKUP($F49,raw_data_pax!$1:$1048576,MATCH(I$1,raw_data_pax!$1:$1,0),FALSE) | J49: =VLOOKUP($F49,raw_data_pax!$1:$1048576,MATCH(J$1,raw_data_pax!$1:$1,0),FALSE) | K49: =VLOOKUP($F49,raw_data_pax!$1:$1048576,MATCH(K$1,raw_data_pax!$1:$1,0),FALSE) | L49: =VLOOKUP($F49,raw_data_pax!$1:$1048576,MATCH(L$1,raw_data_pax!$1:$1,0),FALSE) | M49: =VLOOKUP($F49,raw_data_pax!$1:$1048576,MATCH(M$1,raw_data_pax!$1:$1,0),FALSE) | N49: =VLOOKUP($F49,raw_data_pax!$1:$1048576,MATCH(N$1,raw_data_pax!$1:$1,0),FALSE) | O49: =VLOOKUP($F49,raw_data_pax!$1:$1048576,MATCH(O$1,raw_data_pax!$1:$1,0),FALSE) | ... Q49: =VLOOKUP($F49,raw_data_pax!$1:$1048576,MATCH(Q$1,raw_data_pax!$1:$1,0),FALSE) | R49: =G49 | S49: =R49 | T49: =S49 | U49: =T49 | V49: =U49 | W49: =V49 | X49: =W49 | Y49: =X49 | Z49: =Y49 | ... BA49: =AZ49
C50: =C154&"Average Peak Standing Time📝" | D50: float0 | E50: O | F50: =C154&"(오버나잇, 소산 포함) 피크시간 평균주기시간(분)" | G50: =IFERROR(SUMIF($H$173:$Q$173,"O",H50:Q50)/COUNTIFS($H$173:$Q$173,"O",H50:Q50,"<>0"),0) | H50: =VLOOKUP($F50,raw_data_pax!$1:$1048576,MATCH(H$1,raw_data_pax!$1:$1,0),FALSE) | I50: =VLOOKUP($F50,raw_data_pax!$1:$1048576,MATCH(I$1,raw_data_pax!$1:$1,0),FALSE) | J50: =VLOOKUP($F50,raw_data_pax!$1:$1048576,MATCH(J$1,raw_data_pax!$1:$1,0),FALSE) | K50: =VLOOKUP($F50,raw_data_pax!$1:$1048576,MATCH(K$1,raw_data_pax!$1:$1,0),FALSE) | L50: =VLOOKUP($F50,raw_data_pax!$1:$1048576,MATCH(L$1,raw_data_pax!$1:$1,0),FALSE) | M50: =VLOOKUP($F50,raw_data_pax!$1:$1048576,MATCH(M$1,raw_data_pax!$1:$1,0),FALSE) | N50: =VLOOKUP($F50,raw_data_pax!$1:$1048576,MATCH(N$1,raw_data_pax!$1:$1,0),FALSE) | O50: =VLOOKUP($F50,raw_data_pax!$1:$1048576,MATCH(O$1,raw_data_pax!$1:$1,0),FALSE) | ... Q50: =VLOOKUP($F50,raw_data_pax!$1:$1048576,MATCH(Q$1,raw_data_pax!$1:$1,0),FALSE) | R50: =G50 | S50: =R50 | T50: =S50 | U50: =T50 | V50: =U50 | W50: =V50 | X50: =W50 | Y50: =X50 | Z50: =Y50 | ... BA50: =AZ50
B51: Seats by Class | C51: =C151&"Seats" | D51: float0 | F51: =C151&"대당좌석수" | G51: =IFERROR(SUMIF($H$163:$Q$163,"O",H51:Q51)/COUNTIFS($H$163:$Q$163,"O",H51:Q51,"<>0"),0) | H51: =VLOOKUP($F51,raw_data_pax!$1:$1048576,MATCH(H$1,raw_data_pax!$1:$1,0),FALSE) | I51: =VLOOKUP($F51,raw_data_pax!$1:$1048576,MATCH(I$1,raw_data_pax!$1:$1,0),FALSE) | J51: =VLOOKUP($F51,raw_data_pax!$1:$1048576,MATCH(J$1,raw_data_pax!$1:$1,0),FALSE) | K51: =VLOOKUP($F51,raw_data_pax!$1:$1048576,MATCH(K$1,raw_data_pax!$1:$1,0),FALSE) | L51: =VLOOKUP($F51,raw_data_pax!$1:$1048576,MATCH(L$1,raw_data_pax!$1:$1,0),FALSE) | M51: =VLOOKUP($F51,raw_data_pax!$1:$1048576,MATCH(M$1,raw_data_pax!$1:$1,0),FALSE) | N51: =VLOOKUP($F51,raw_data_pax!$1:$1048576,MATCH(N$1,raw_data_pax!$1:$1,0),FALSE) | O51: =VLOOKUP($F51,raw_data_pax!$1:$1048576,MATCH(O$1,raw_data_pax!$1:$1,0),FALSE) | ... Q51: =VLOOKUP($F51,raw_data_pax!$1:$1048576,MATCH(Q$1,raw_data_pax!$1:$1,0),FALSE) | R51: =G51 | S51: =R51 | T51: =S51 | U51: =T51 | V51: =U51 | W51: =V51 | X51: =W51 | Y51: =X51 | Z51: =Y51 | ... BA51: =AZ51
C52: =C152&"Seats" | D52: float0 | F52: =C152&"대당좌석수" | G52: =IFERROR(SUMIF($H$163:$Q$163,"O",H52:Q52)/COUNTIFS($H$163:$Q$163,"O",H52:Q52,"<>0"),0) | H52: =VLOOKUP($F52,raw_data_pax!$1:$1048576,MATCH(H$1,raw_data_pax!$1:$1,0),FALSE) | I52: =VLOOKUP($F52,raw_data_pax!$1:$1048576,MATCH(I$1,raw_data_pax!$1:$1,0),FALSE) | J52: =VLOOKUP($F52,raw_data_pax!$1:$1048576,MATCH(J$1,raw_data_pax!$1:$1,0),FALSE) | K52: =VLOOKUP($F52,raw_data_pax!$1:$1048576,MATCH(K$1,raw_data_pax!$1:$1,0),FALSE) | L52: =VLOOKUP($F52,raw_data_pax!$1:$1048576,MATCH(L$1,raw_data_pax!$1:$1,0),FALSE) | M52: =VLOOKUP($F52,raw_data_pax!$1:$1048576,MATCH(M$1,raw_data_pax!$1:$1,0),FALSE) | N52: =VLOOKUP($F52,raw_data_pax!$1:$1048576,MATCH(N$1,raw_data_pax!$1:$1,0),FALSE) | O52: =VLOOKUP($F52,raw_data_pax!$1:$1048576,MATCH(O$1,raw_data_pax!$1:$1,0),FALSE) | ... Q52: =VLOOKUP($F52,raw_data_pax!$1:$1048576,MATCH(Q$1,raw_data_pax!$1:$1,0),FALSE) | R52: =G52 | S52: =R52 | T52: =S52 | U52: =T52 | V52: =U52 | W52: =V52 | X52: =W52 | Y52: =X52 | Z52: =Y52 | ... BA52: =AZ52
C53: =C153&"Seats" | D53: float0 | F53: =C153&"대당좌석수" | G53: =IFERROR(SUMIF($H$163:$Q$163,"O",H53:Q53)/COUNTIFS($H$163:$Q$163,"O",H53:Q53,"<>0"),0) | H53: =VLOOKUP($F53,raw_data_pax!$1:$1048576,MATCH(H$1,raw_data_pax!$1:$1,0),FALSE) | I53: =VLOOKUP($F53,raw_data_pax!$1:$1048576,MATCH(I$1,raw_data_pax!$1:$1,0),FALSE) | J53: =VLOOKUP($F53,raw_data_pax!$1:$1048576,MATCH(J$1,raw_data_pax!$1:$1,0),FALSE) | K53: =VLOOKUP($F53,raw_data_pax!$1:$1048576,MATCH(K$1,raw_data_pax!$1:$1,0),FALSE) | L53: =VLOOKUP($F53,raw_data_pax!$1:$1048576,MATCH(L$1,raw_data_pax!$1:$1,0),FALSE) | M53: =VLOOKUP($F53,raw_data_pax!$1:$1048576,MATCH(M$1,raw_data_pax!$1:$1,0),FALSE) | N53: =VLOOKUP($F53,raw_data_pax!$1:$1048576,MATCH(N$1,raw_data_pax!$1:$1,0),FALSE) | O53: =VLOOKUP($F53,raw_data_pax!$1:$1048576,MATCH(O$1,raw_data_pax!$1:$1,0),FALSE) | ... Q53: =VLOOKUP($F53,raw_data_pax!$1:$1048576,MATCH(Q$1,raw_data_pax!$1:$1,0),FALSE) | R53: =G53 | S53: =R53 | T53: =S53 | U53: =T53 | V53: =U53 | W53: =V53 | X53: =W53 | Y53: =X53 | Z53: =Y53 | ... BA53: =AZ53
C54: =C154&"Seats" | D54: float0 | F54: =C154&"대당좌석수" | G54: =IFERROR(SUMIF($H$163:$Q$163,"O",H54:Q54)/COUNTIFS($H$163:$Q$163,"O",H54:Q54,"<>0"),0) | H54: =VLOOKUP($F54,raw_data_pax!$1:$1048576,MATCH(H$1,raw_data_pax!$1:$1,0),FALSE) | I54: =VLOOKUP($F54,raw_data_pax!$1:$1048576,MATCH(I$1,raw_data_pax!$1:$1,0),FALSE) | J54: =VLOOKUP($F54,raw_data_pax!$1:$1048576,MATCH(J$1,raw_data_pax!$1:$1,0),FALSE) | K54: =VLOOKUP($F54,raw_data_pax!$1:$1048576,MATCH(K$1,raw_data_pax!$1:$1,0),FALSE) | L54: =VLOOKUP($F54,raw_data_pax!$1:$1048576,MATCH(L$1,raw_data_pax!$1:$1,0),FALSE) | M54: =VLOOKUP($F54,raw_data_pax!$1:$1048576,MATCH(M$1,raw_data_pax!$1:$1,0),FALSE) | N54: =VLOOKUP($F54,raw_data_pax!$1:$1048576,MATCH(N$1,raw_data_pax!$1:$1,0),FALSE) | O54: =VLOOKUP($F54,raw_data_pax!$1:$1048576,MATCH(O$1,raw_data_pax!$1:$1,0),FALSE) | ... Q54: =VLOOKUP($F54,raw_data_pax!$1:$1048576,MATCH(Q$1,raw_data_pax!$1:$1,0),FALSE) | R54: =G54 | S54: =R54 | T54: =S54 | U54: =T54 | V54: =U54 | W54: =V54 | X54: =W54 | Y54: =X54 | Z54: =Y54 | ... BA54: =AZ54
B55: Load Factor by Class | C55: Load Factor Adjustment By Class | D55: percent1 | R55: =R2/SUMPRODUCT(R35:R38,R51:R54,$G56:$G59) | S55: =S2/SUMPRODUCT(S35:S38,S51:S54,$G56:$G59) | T55: =T2/SUMPRODUCT(T35:T38,T51:T54,$G56:$G59) | U55: =U2/SUMPRODUCT(U35:U38,U51:U54,$G56:$G59) | V55: =V2/SUMPRODUCT(V35:V38,V51:V54,$G56:$G59) | W55: =W2/SUMPRODUCT(W35:W38,W51:W54,$G56:$G59) | X55: =X2/SUMPRODUCT(X35:X38,X51:X54,$G56:$G59) | Y55: =Y2/SUMPRODUCT(Y35:Y38,Y51:Y54,$G56:$G59) | ... BA55: =BA2/SUMPRODUCT(BA35:BA38,BA51:BA54,$G56:$G59)
C56: =C151&"Load Factor" | D56: percent1 | F56: =C151&"탑승율" | G56: =IFERROR(SUMIF($H$164:$Q$164,"O",H56:Q56)/COUNTIFS($H$164:$Q$164,"O",H56:Q56,"<>0"),0) | H56: =VLOOKUP($F56,raw_data_pax!$1:$1048576,MATCH(H$1,raw_data_pax!$1:$1,0),FALSE) | I56: =VLOOKUP($F56,raw_data_pax!$1:$1048576,MATCH(I$1,raw_data_pax!$1:$1,0),FALSE) | J56: =VLOOKUP($F56,raw_data_pax!$1:$1048576,MATCH(J$1,raw_data_pax!$1:$1,0),FALSE) | K56: =VLOOKUP($F56,raw_data_pax!$1:$1048576,MATCH(K$1,raw_data_pax!$1:$1,0),FALSE) | L56: =VLOOKUP($F56,raw_data_pax!$1:$1048576,MATCH(L$1,raw_data_pax!$1:$1,0),FALSE) | M56: =VLOOKUP($F56,raw_data_pax!$1:$1048576,MATCH(M$1,raw_data_pax!$1:$1,0),FALSE) | N56: =VLOOKUP($F56,raw_data_pax!$1:$1048576,MATCH(N$1,raw_data_pax!$1:$1,0),FALSE) | O56: =VLOOKUP($F56,raw_data_pax!$1:$1048576,MATCH(O$1,raw_data_pax!$1:$1,0),FALSE) | ... Q56: =VLOOKUP($F56,raw_data_pax!$1:$1048576,MATCH(Q$1,raw_data_pax!$1:$1,0),FALSE) | R56: =$G56*R$55 | S56: =$G56*S$55 | T56: =$G56*T$55 | U56: =$G56*U$55 | V56: =$G56*V$55 | W56: =$G56*W$55 | X56: =$G56*X$55 | Y56: =$G56*Y$55 | ... BA56: =$G56*BA$55
C57: =C152&"Load Factor" | D57: percent1 | F57: =C152&"탑승율" | G57: =IFERROR(SUMIF($H$164:$Q$164,"O",H57:Q57)/COUNTIFS($H$164:$Q$164,"O",H57:Q57,"<>0"),0) | H57: =VLOOKUP($F57,raw_data_pax!$1:$1048576,MATCH(H$1,raw_data_pax!$1:$1,0),FALSE) | I57: =VLOOKUP($F57,raw_data_pax!$1:$1048576,MATCH(I$1,raw_data_pax!$1:$1,0),FALSE) | J57: =VLOOKUP($F57,raw_data_pax!$1:$1048576,MATCH(J$1,raw_data_pax!$1:$1,0),FALSE) | K57: =VLOOKUP($F57,raw_data_pax!$1:$1048576,MATCH(K$1,raw_data_pax!$1:$1,0),FALSE) | L57: =VLOOKUP($F57,raw_data_pax!$1:$1048576,MATCH(L$1,raw_data_pax!$1:$1,0),FALSE) | M57: =VLOOKUP($F57,raw_data_pax!$1:$1048576,MATCH(M$1,raw_data_pax!$1:$1,0),FALSE) | N57: =VLOOKUP($F57,raw_data_pax!$1:$1048576,MATCH(N$1,raw_data_pax!$1:$1,0),FALSE) | O57: =VLOOKUP($F57,raw_data_pax!$1:$1048576,MATCH(O$1,raw_data_pax!$1:$1,0),FALSE) | ... Q57: =VLOOKUP($F57,raw_data_pax!$1:$1048576,MATCH(Q$1,raw_data_pax!$1:$1,0),FALSE) | R57: =$G57*R$55 | S57: =$G57*S$55 | T57: =$G57*T$55 | U57: =$G57*U$55 | V57: =$G57*V$55 | W57: =$G57*W$55 | X57: =$G57*X$55 | Y57: =$G57*Y$55 | ... BA57: =$G57*BA$55
C58: =C153&"Load Factor" | D58: percent1 | F58: =C153&"탑승율" | G58: =IFERROR(SUMIF($H$164:$Q$164,"O",H58:Q58)/COUNTIFS($H$164:$Q$164,"O",H58:Q58,"<>0"),0) | H58: =VLOOKUP($F58,raw_data_pax!$1:$1048576,MATCH(H$1,raw_data_pax!$1:$1,0),FALSE) | I58: =VLOOKUP($F58,raw_data_pax!$1:$1048576,MATCH(I$1,raw_data_pax!$1:$1,0),FALSE) | J58: =VLOOKUP($F58,raw_data_pax!$1:$1048576,MATCH(J$1,raw_data_pax!$1:$1,0),FALSE) | K58: =VLOOKUP($F58,raw_data_pax!$1:$1048576,MATCH(K$1,raw_data_pax!$1:$1,0),FALSE) | L58: =VLOOKUP($F58,raw_data_pax!$1:$1048576,MATCH(L$1,raw_data_pax!$1:$1,0),FALSE) | M58: =VLOOKUP($F58,raw_data_pax!$1:$1048576,MATCH(M$1,raw_data_pax!$1:$1,0),FALSE) | N58: =VLOOKUP($F58,raw_data_pax!$1:$1048576,MATCH(N$1,raw_data_pax!$1:$1,0),FALSE) | O58: =VLOOKUP($F58,raw_data_pax!$1:$1048576,MATCH(O$1,raw_data_pax!$1:$1,0),FALSE) | ... Q58: =VLOOKUP($F58,raw_data_pax!$1:$1048576,MATCH(Q$1,raw_data_pax!$1:$1,0),FALSE) | R58: =$G58*R$55 | S58: =$G58*S$55 | T58: =$G58*T$55 | U58: =$G58*U$55 | V58: =$G58*V$55 | W58: =$G58*W$55 | X58: =$G58*X$55 | Y58: =$G58*Y$55 | ... BA58: =$G58*BA$55
C59: =C154&"Load Factor" | D59: percent1 | F59: =C154&"탑승율" | G59: =IFERROR(SUMIF($H$164:$Q$164,"O",H59:Q59)/COUNTIFS($H$164:$Q$164,"O",H59:Q59,"<>0"),0) | H59: =VLOOKUP($F59,raw_data_pax!$1:$1048576,MATCH(H$1,raw_data_pax!$1:$1,0),FALSE) | I59: =VLOOKUP($F59,raw_data_pax!$1:$1048576,MATCH(I$1,raw_data_pax!$1:$1,0),FALSE) | J59: =VLOOKUP($F59,raw_data_pax!$1:$1048576,MATCH(J$1,raw_data_pax!$1:$1,0),FALSE) | K59: =VLOOKUP($F59,raw_data_pax!$1:$1048576,MATCH(K$1,raw_data_pax!$1:$1,0),FALSE) | L59: =VLOOKUP($F59,raw_data_pax!$1:$1048576,MATCH(L$1,raw_data_pax!$1:$1,0),FALSE) | M59: =VLOOKUP($F59,raw_data_pax!$1:$1048576,MATCH(M$1,raw_data_pax!$1:$1,0),FALSE) | N59: =VLOOKUP($F59,raw_data_pax!$1:$1048576,MATCH(N$1,raw_data_pax!$1:$1,0),FALSE) | O59: =VLOOKUP($F59,raw_data_pax!$1:$1048576,MATCH(O$1,raw_data_pax!$1:$1,0),FALSE) | ... Q59: =VLOOKUP($F59,raw_data_pax!$1:$1048576,MATCH(Q$1,raw_data_pax!$1:$1,0),FALSE) | R59: =$G59*R$55 | S59: =$G59*S$55 | T59: =$G59*T$55 | U59: =$G59*U$55 | V59: =$G59*V$55 | W59: =$G59*W$55 | X59: =$G59*X$55 | Y59: =$G59*Y$55 | ... BA59: =$G59*BA$55
B60: Transfer Rate(%) by Class | C60: Transfer Rate Adjustment By Class | D60: percent1 | R60: =IFERROR(R16/SUMPRODUCT(R35:R38,R51:R54,R56:R59,$G61:$G64),0) | S60: =IFERROR(S16/SUMPRODUCT(S35:S38,S51:S54,S56:S59,$G61:$G64),0) | T60: =IFERROR(T16/SUMPRODUCT(T35:T38,T51:T54,T56:T59,$G61:$G64),0) | U60: =IFERROR(U16/SUMPRODUCT(U35:U38,U51:U54,U56:U59,$G61:$G64),0) | V60: =IFERROR(V16/SUMPRODUCT(V35:V38,V51:V54,V56:V59,$G61:$G64),0) | W60: =IFERROR(W16/SUMPRODUCT(W35:W38,W51:W54,W56:W59,$G61:$G64),0) | X60: =IFERROR(X16/SUMPRODUCT(X35:X38,X51:X54,X56:X59,$G61:$G64),0) | Y60: =IFERROR(Y16/SUMPRODUCT(Y35:Y38,Y51:Y54,Y56:Y59,$G61:$G64),0) | ... BA60: =IFERROR(BA16/SUMPRODUCT(BA35:BA38,BA51:BA54,BA56:BA59,$G61:$G64),0)
C61: =C151&"Transfer Rate" | D61: percent1 | F61: =C151&"환승율" | G61: =IFERROR(SUMIF($H$165:$Q$165,"O",H61:Q61)/COUNTIFS($H$165:$Q$165,"O",H61:Q61,"<>0"),0) | H61: =VLOOKUP($F61,raw_data_pax!$1:$1048576,MATCH(H$1,raw_data_pax!$1:$1,0),FALSE) | I61: =VLOOKUP($F61,raw_data_pax!$1:$1048576,MATCH(I$1,raw_data_pax!$1:$1,0),FALSE) | J61: =VLOOKUP($F61,raw_data_pax!$1:$1048576,MATCH(J$1,raw_data_pax!$1:$1,0),FALSE) | K61: =VLOOKUP($F61,raw_data_pax!$1:$1048576,MATCH(K$1,raw_data_pax!$1:$1,0),FALSE) | L61: =VLOOKUP($F61,raw_data_pax!$1:$1048576,MATCH(L$1,raw_data_pax!$1:$1,0),FALSE) | M61: =VLOOKUP($F61,raw_data_pax!$1:$1048576,MATCH(M$1,raw_data_pax!$1:$1,0),FALSE) | N61: =VLOOKUP($F61,raw_data_pax!$1:$1048576,MATCH(N$1,raw_data_pax!$1:$1,0),FALSE) | O61: =VLOOKUP($F61,raw_data_pax!$1:$1048576,MATCH(O$1,raw_data_pax!$1:$1,0),FALSE) | ... Q61: =VLOOKUP($F61,raw_data_pax!$1:$1048576,MATCH(Q$1,raw_data_pax!$1:$1,0),FALSE) | R61: =$G61*R$60 | S61: =$G61*S$60 | T61: =$G61*T$60 | U61: =$G61*U$60 | V61: =$G61*V$60 | W61: =$G61*W$60 | X61: =$G61*X$60 | Y61: =$G61*Y$60 | ... BA61: =$G61*BA$60
C62: =C152&"Transfer Rate" | D62: percent1 | F62: =C152&"환승율" | G62: =IFERROR(SUMIF($H$165:$Q$165,"O",H62:Q62)/COUNTIFS($H$165:$Q$165,"O",H62:Q62,"<>0"),0) | H62: =VLOOKUP($F62,raw_data_pax!$1:$1048576,MATCH(H$1,raw_data_pax!$1:$1,0),FALSE) | I62: =VLOOKUP($F62,raw_data_pax!$1:$1048576,MATCH(I$1,raw_data_pax!$1:$1,0),FALSE) | J62: =VLOOKUP($F62,raw_data_pax!$1:$1048576,MATCH(J$1,raw_data_pax!$1:$1,0),FALSE) | K62: =VLOOKUP($F62,raw_data_pax!$1:$1048576,MATCH(K$1,raw_data_pax!$1:$1,0),FALSE) | L62: =VLOOKUP($F62,raw_data_pax!$1:$1048576,MATCH(L$1,raw_data_pax!$1:$1,0),FALSE) | M62: =VLOOKUP($F62,raw_data_pax!$1:$1048576,MATCH(M$1,raw_data_pax!$1:$1,0),FALSE) | N62: =VLOOKUP($F62,raw_data_pax!$1:$1048576,MATCH(N$1,raw_data_pax!$1:$1,0),FALSE) | O62: =VLOOKUP($F62,raw_data_pax!$1:$1048576,MATCH(O$1,raw_data_pax!$1:$1,0),FALSE) | ... Q62: =VLOOKUP($F62,raw_data_pax!$1:$1048576,MATCH(Q$1,raw_data_pax!$1:$1,0),FALSE) | R62: =$G62*R$60 | S62: =$G62*S$60 | T62: =$G62*T$60 | U62: =$G62*U$60 | V62: =$G62*V$60 | W62: =$G62*W$60 | X62: =$G62*X$60 | Y62: =$G62*Y$60 | ... BA62: =$G62*BA$60
C63: =C153&"Transfer Rate" | D63: percent1 | F63: =C153&"환승율" | G63: =IFERROR(SUMIF($H$165:$Q$165,"O",H63:Q63)/COUNTIFS($H$165:$Q$165,"O",H63:Q63,"<>0"),0) | H63: =VLOOKUP($F63,raw_data_pax!$1:$1048576,MATCH(H$1,raw_data_pax!$1:$1,0),FALSE) | I63: =VLOOKUP($F63,raw_data_pax!$1:$1048576,MATCH(I$1,raw_data_pax!$1:$1,0),FALSE) | J63: =VLOOKUP($F63,raw_data_pax!$1:$1048576,MATCH(J$1,raw_data_pax!$1:$1,0),FALSE) | K63: =VLOOKUP($F63,raw_data_pax!$1:$1048576,MATCH(K$1,raw_data_pax!$1:$1,0),FALSE) | L63: =VLOOKUP($F63,raw_data_pax!$1:$1048576,MATCH(L$1,raw_data_pax!$1:$1,0),FALSE) | M63: =VLOOKUP($F63,raw_data_pax!$1:$1048576,MATCH(M$1,raw_data_pax!$1:$1,0),FALSE) | N63: =VLOOKUP($F63,raw_data_pax!$1:$1048576,MATCH(N$1,raw_data_pax!$1:$1,0),FALSE) | O63: =VLOOKUP($F63,raw_data_pax!$1:$1048576,MATCH(O$1,raw_data_pax!$1:$1,0),FALSE) | ... Q63: =VLOOKUP($F63,raw_data_pax!$1:$1048576,MATCH(Q$1,raw_data_pax!$1:$1,0),FALSE) | R63: =$G63*R$60 | S63: =$G63*S$60 | T63: =$G63*T$60 | U63: =$G63*U$60 | V63: =$G63*V$60 | W63: =$G63*W$60 | X63: =$G63*X$60 | Y63: =$G63*Y$60 | ... BA63: =$G63*BA$60
C64: =C154&"Transfer Rate" | D64: percent1 | F64: =C154&"환승율" | G64: =IFERROR(SUMIF($H$165:$Q$165,"O",H64:Q64)/COUNTIFS($H$165:$Q$165,"O",H64:Q64,"<>0"),0) | H64: =VLOOKUP($F64,raw_data_pax!$1:$1048576,MATCH(H$1,raw_data_pax!$1:$1,0),FALSE) | I64: =VLOOKUP($F64,raw_data_pax!$1:$1048576,MATCH(I$1,raw_data_pax!$1:$1,0),FALSE) | J64: =VLOOKUP($F64,raw_data_pax!$1:$1048576,MATCH(J$1,raw_data_pax!$1:$1,0),FALSE) | K64: =VLOOKUP($F64,raw_data_pax!$1:$1048576,MATCH(K$1,raw_data_pax!$1:$1,0),FALSE) | L64: =VLOOKUP($F64,raw_data_pax!$1:$1048576,MATCH(L$1,raw_data_pax!$1:$1,0),FALSE) | M64: =VLOOKUP($F64,raw_data_pax!$1:$1048576,MATCH(M$1,raw_data_pax!$1:$1,0),FALSE) | N64: =VLOOKUP($F64,raw_data_pax!$1:$1048576,MATCH(N$1,raw_data_pax!$1:$1,0),FALSE) | O64: =VLOOKUP($F64,raw_data_pax!$1:$1048576,MATCH(O$1,raw_data_pax!$1:$1,0),FALSE) | ... Q64: =VLOOKUP($F64,raw_data_pax!$1:$1048576,MATCH(Q$1,raw_data_pax!$1:$1,0),FALSE) | R64: =$G64*R$60 | S64: =$G64*S$60 | T64: =$G64*T$60 | U64: =$G64*U$60 | V64: =$G64*V$60 | W64: =$G64*W$60 | X64: =$G64*X$60 | Y64: =$G64*Y$60 | ... BA64: =$G64*BA$60
B65: Crew by Class | C65: =C151&"Crew" | D65: float0 | F65: =C151&"대당승무원" | G65: =IFERROR(SUMIF($H$166:$Q$166,"O",H65:Q65)/COUNTIFS($H$166:$Q$166,"O",H65:Q65,"<>0"),0) | H65: =VLOOKUP($F65,raw_data_pax!$1:$1048576,MATCH(H$1,raw_data_pax!$1:$1,0),FALSE) | I65: =VLOOKUP($F65,raw_data_pax!$1:$1048576,MATCH(I$1,raw_data_pax!$1:$1,0),FALSE) | J65: =VLOOKUP($F65,raw_data_pax!$1:$1048576,MATCH(J$1,raw_data_pax!$1:$1,0),FALSE) | K65: =VLOOKUP($F65,raw_data_pax!$1:$1048576,MATCH(K$1,raw_data_pax!$1:$1,0),FALSE) | L65: =VLOOKUP($F65,raw_data_pax!$1:$1048576,MATCH(L$1,raw_data_pax!$1:$1,0),FALSE) | M65: =VLOOKUP($F65,raw_data_pax!$1:$1048576,MATCH(M$1,raw_data_pax!$1:$1,0),FALSE) | N65: =VLOOKUP($F65,raw_data_pax!$1:$1048576,MATCH(N$1,raw_data_pax!$1:$1,0),FALSE) | O65: =VLOOKUP($F65,raw_data_pax!$1:$1048576,MATCH(O$1,raw_data_pax!$1:$1,0),FALSE) | ... Q65: =VLOOKUP($F65,raw_data_pax!$1:$1048576,MATCH(Q$1,raw_data_pax!$1:$1,0),FALSE) | R65: =G65 | S65: =R65 | T65: =S65 | U65: =T65 | V65: =U65 | W65: =V65 | X65: =W65 | Y65: =X65 | Z65: =Y65 | ... BA65: =AZ65
C66: =C152&"Crew" | D66: float0 | F66: =C152&"대당승무원" | G66: =IFERROR(SUMIF($H$166:$Q$166,"O",H66:Q66)/COUNTIFS($H$166:$Q$166,"O",H66:Q66,"<>0"),0) | H66: =VLOOKUP($F66,raw_data_pax!$1:$1048576,MATCH(H$1,raw_data_pax!$1:$1,0),FALSE) | I66: =VLOOKUP($F66,raw_data_pax!$1:$1048576,MATCH(I$1,raw_data_pax!$1:$1,0),FALSE) | J66: =VLOOKUP($F66,raw_data_pax!$1:$1048576,MATCH(J$1,raw_data_pax!$1:$1,0),FALSE) | K66: =VLOOKUP($F66,raw_data_pax!$1:$1048576,MATCH(K$1,raw_data_pax!$1:$1,0),FALSE) | L66: =VLOOKUP($F66,raw_data_pax!$1:$1048576,MATCH(L$1,raw_data_pax!$1:$1,0),FALSE) | M66: =VLOOKUP($F66,raw_data_pax!$1:$1048576,MATCH(M$1,raw_data_pax!$1:$1,0),FALSE) | N66: =VLOOKUP($F66,raw_data_pax!$1:$1048576,MATCH(N$1,raw_data_pax!$1:$1,0),FALSE) | O66: =VLOOKUP($F66,raw_data_pax!$1:$1048576,MATCH(O$1,raw_data_pax!$1:$1,0),FALSE) | ... Q66: =VLOOKUP($F66,raw_data_pax!$1:$1048576,MATCH(Q$1,raw_data_pax!$1:$1,0),FALSE) | R66: =G66 | S66: =R66 | T66: =S66 | U66: =T66 | V66: =U66 | W66: =V66 | X66: =W66 | Y66: =X66 | Z66: =Y66 | ... BA66: =AZ66
C67: =C153&"Crew" | D67: float0 | F67: =C153&"대당승무원" | G67: =IFERROR(SUMIF($H$166:$Q$166,"O",H67:Q67)/COUNTIFS($H$166:$Q$166,"O",H67:Q67,"<>0"),0) | H67: =VLOOKUP($F67,raw_data_pax!$1:$1048576,MATCH(H$1,raw_data_pax!$1:$1,0),FALSE) | I67: =VLOOKUP($F67,raw_data_pax!$1:$1048576,MATCH(I$1,raw_data_pax!$1:$1,0),FALSE) | J67: =VLOOKUP($F67,raw_data_pax!$1:$1048576,MATCH(J$1,raw_data_pax!$1:$1,0),FALSE) | K67: =VLOOKUP($F67,raw_data_pax!$1:$1048576,MATCH(K$1,raw_data_pax!$1:$1,0),FALSE) | L67: =VLOOKUP($F67,raw_data_pax!$1:$1048576,MATCH(L$1,raw_data_pax!$1:$1,0),FALSE) | M67: =VLOOKUP($F67,raw_data_pax!$1:$1048576,MATCH(M$1,raw_data_pax!$1:$1,0),FALSE) | N67: =VLOOKUP($F67,raw_data_pax!$1:$1048576,MATCH(N$1,raw_data_pax!$1:$1,0),FALSE) | O67: =VLOOKUP($F67,raw_data_pax!$1:$1048576,MATCH(O$1,raw_data_pax!$1:$1,0),FALSE) | ... Q67: =VLOOKUP($F67,raw_data_pax!$1:$1048576,MATCH(Q$1,raw_data_pax!$1:$1,0),FALSE) | R67: =G67 | S67: =R67 | T67: =S67 | U67: =T67 | V67: =U67 | W67: =V67 | X67: =W67 | Y67: =X67 | Z67: =Y67 | ... BA67: =AZ67
C68: =C154&"Crew" | D68: float0 | F68: =C154&"대당승무원" | G68: =IFERROR(SUMIF($H$166:$Q$166,"O",H68:Q68)/COUNTIFS($H$166:$Q$166,"O",H68:Q68,"<>0"),0) | H68: =VLOOKUP($F68,raw_data_pax!$1:$1048576,MATCH(H$1,raw_data_pax!$1:$1,0),FALSE) | I68: =VLOOKUP($F68,raw_data_pax!$1:$1048576,MATCH(I$1,raw_data_pax!$1:$1,0),FALSE) | J68: =VLOOKUP($F68,raw_data_pax!$1:$1048576,MATCH(J$1,raw_data_pax!$1:$1,0),FALSE) | K68: =VLOOKUP($F68,raw_data_pax!$1:$1048576,MATCH(K$1,raw_data_pax!$1:$1,0),FALSE) | L68: =VLOOKUP($F68,raw_data_pax!$1:$1048576,MATCH(L$1,raw_data_pax!$1:$1,0),FALSE) | M68: =VLOOKUP($F68,raw_data_pax!$1:$1048576,MATCH(M$1,raw_data_pax!$1:$1,0),FALSE) | N68: =VLOOKUP($F68,raw_data_pax!$1:$1048576,MATCH(N$1,raw_data_pax!$1:$1,0),FALSE) | O68: =VLOOKUP($F68,raw_data_pax!$1:$1048576,MATCH(O$1,raw_data_pax!$1:$1,0),FALSE) | ... Q68: =VLOOKUP($F68,raw_data_pax!$1:$1048576,MATCH(Q$1,raw_data_pax!$1:$1,0),FALSE) | R68: =G68 | S68: =R68 | T68: =S68 | U68: =T68 | V68: =U68 | W68: =V68 | X68: =W68 | Y68: =X68 | Z68: =Y68 | ... BA68: =AZ68
A72: top | B72: mid | C72: low | D72: decimal | E72: changeable | F72: 변수설명 | G72: Ref_Index | H72: =I72-1 | I72: =J72-1 | J72: =K72-1 | K72: =L72-1 | L72: =M72-1 | M72: =N72-1 | N72: =O72-1 | O72: =P72-1 | P72: =Q72-1 | Q72: =ref!B4 | R72: =Q72+1 | S72: =R72+1 | T72: =S72+1 | U72: =T72+1 | V72: =U72+1 | W72: =V72+1 | X72: =W72+1 | Y72: =X72+1 | ... BA72: =AZ72+1
A73: Airside(ADPM) | B73: Passenger Flight Movements(ADPM) | C73: Movement PHF(%)(ADPM) | D73: percent4 | F73: ADPM/movement/all/PHF | H73: =VLOOKUP($F73,raw_data_pax!$1:$1048576,MATCH(H$1,raw_data_pax!$1:$1,0),FALSE) | I73: =VLOOKUP($F73,raw_data_pax!$1:$1048576,MATCH(I$1,raw_data_pax!$1:$1,0),FALSE) | J73: =VLOOKUP($F73,raw_data_pax!$1:$1048576,MATCH(J$1,raw_data_pax!$1:$1,0),FALSE) | K73: =VLOOKUP($F73,raw_data_pax!$1:$1048576,MATCH(K$1,raw_data_pax!$1:$1,0),FALSE) | L73: =VLOOKUP($F73,raw_data_pax!$1:$1048576,MATCH(L$1,raw_data_pax!$1:$1,0),FALSE) | M73: =VLOOKUP($F73,raw_data_pax!$1:$1048576,MATCH(M$1,raw_data_pax!$1:$1,0),FALSE) | N73: =VLOOKUP($F73,raw_data_pax!$1:$1048576,MATCH(N$1,raw_data_pax!$1:$1,0),FALSE) | O73: =VLOOKUP($F73,raw_data_pax!$1:$1048576,MATCH(O$1,raw_data_pax!$1:$1,0),FALSE) | ... Q73: =VLOOKUP($F73,raw_data_pax!$1:$1048576,MATCH(Q$1,raw_data_pax!$1:$1,0),FALSE) | R73: =0.0021*R20^(-0.183)*$G$77 | S73: =0.0021*S20^(-0.183)*$G$77 | T73: =0.0021*T20^(-0.183)*$G$77 | U73: =0.0021*U20^(-0.183)*$G$77 | V73: =0.0021*V20^(-0.183)*$G$77 | W73: =0.0021*W20^(-0.183)*$G$77 | X73: =0.0021*X20^(-0.183)*$G$77 | Y73: =0.0021*Y20^(-0.183)*$G$77 | ... BA73: =0.0021*BA20^(-0.183)*$G$77
C74: - Movement H Factor(ADPM) | D74: float1 | F74: ADPM/movement/all/H팩터 | H74: =VLOOKUP($F74,raw_data_pax!$1:$1048576,MATCH(H$1,raw_data_pax!$1:$1,0),FALSE) | I74: =VLOOKUP($F74,raw_data_pax!$1:$1048576,MATCH(I$1,raw_data_pax!$1:$1,0),FALSE) | J74: =VLOOKUP($F74,raw_data_pax!$1:$1048576,MATCH(J$1,raw_data_pax!$1:$1,0),FALSE) | K74: =VLOOKUP($F74,raw_data_pax!$1:$1048576,MATCH(K$1,raw_data_pax!$1:$1,0),FALSE) | L74: =VLOOKUP($F74,raw_data_pax!$1:$1048576,MATCH(L$1,raw_data_pax!$1:$1,0),FALSE) | M74: =VLOOKUP($F74,raw_data_pax!$1:$1048576,MATCH(M$1,raw_data_pax!$1:$1,0),FALSE) | N74: =VLOOKUP($F74,raw_data_pax!$1:$1048576,MATCH(N$1,raw_data_pax!$1:$1,0),FALSE) | O74: =VLOOKUP($F74,raw_data_pax!$1:$1048576,MATCH(O$1,raw_data_pax!$1:$1,0),FALSE) | ... Q74: =VLOOKUP($F74,raw_data_pax!$1:$1048576,MATCH(Q$1,raw_data_pax!$1:$1,0),FALSE) | R74: =1/R73/R75 | S74: =1/S73/S75 | T74: =1/T73/T75 | U74: =1/U73/U75 | V74: =1/V73/V75 | W74: =1/W73/W75 | X74: =1/X73/X75 | Y74: =1/Y73/Y75 | ... BA74: =1/BA73/BA75
C75: - Movement D Factor(ADPM) | D75: float1 | F75: ADPM/movement/all/D팩터 | G75: =SUMIF($H$168:$Q$168,"O",H75:Q75)/COUNTIFS($H$168:$Q$168,"O",H75:Q75,"<>0") | H75: =VLOOKUP($F75,raw_data_pax!$1:$1048576,MATCH(H$1,raw_data_pax!$1:$1,0),FALSE) | I75: =VLOOKUP($F75,raw_data_pax!$1:$1048576,MATCH(I$1,raw_data_pax!$1:$1,0),FALSE) | J75: =VLOOKUP($F75,raw_data_pax!$1:$1048576,MATCH(J$1,raw_data_pax!$1:$1,0),FALSE) | K75: =VLOOKUP($F75,raw_data_pax!$1:$1048576,MATCH(K$1,raw_data_pax!$1:$1,0),FALSE) | L75: =VLOOKUP($F75,raw_data_pax!$1:$1048576,MATCH(L$1,raw_data_pax!$1:$1,0),FALSE) | M75: =VLOOKUP($F75,raw_data_pax!$1:$1048576,MATCH(M$1,raw_data_pax!$1:$1,0),FALSE) | N75: =VLOOKUP($F75,raw_data_pax!$1:$1048576,MATCH(N$1,raw_data_pax!$1:$1,0),FALSE) | O75: =VLOOKUP($F75,raw_data_pax!$1:$1048576,MATCH(O$1,raw_data_pax!$1:$1,0),FALSE) | ... Q75: =VLOOKUP($F75,raw_data_pax!$1:$1048576,MATCH(Q$1,raw_data_pax!$1:$1,0),FALSE) | R75: =$G$75 | S75: =$G$75 | T75: =$G$75 | U75: =$G$75 | V75: =$G$75 | W75: =$G$75 | X75: =$G$75 | Y75: =$G$75 | ... BA75: =$G$75
C76: Movement PHF(%) Model(ADPM) | D76: percent4 | F76: 모형 | H76: =0.0021*H20^(-0.183) | I76: =0.0021*I20^(-0.183) | J76: =0.0021*J20^(-0.183) | K76: =0.0021*K20^(-0.183) | L76: =0.0021*L20^(-0.183) | M76: =0.0021*M20^(-0.183) | N76: =0.0021*N20^(-0.183) | O76: =0.0021*O20^(-0.183) | ... Q76: =0.0021*Q20^(-0.183)
C77: Movement Model PHF / Movement PHF(ADPM) | D77: percent1 | F77: 모형PHF / 실제 PHF | G77: =SUMIF($H$167:$Q$167,"O",H77:Q77)/COUNTIFS($H$167:$Q$167,"O",H77:Q77,"<>0") | H77: =H73/H76 | I77: =I73/I76 | J77: =J73/J76 | K77: =K73/K76 | L77: =L73/L76 | M77: =M73/M76 | N77: =N73/N76 | O77: =O73/O76 | ... Q77: =Q73/Q76
C78: Peak Hour Movements(ADPM) | D78: float0 | F78: ADPM/movement/all/첨두시 | H78: =VLOOKUP($F78,raw_data_pax!$1:$1048576,MATCH(H$1,raw_data_pax!$1:$1,0),FALSE) | I78: =VLOOKUP($F78,raw_data_pax!$1:$1048576,MATCH(I$1,raw_data_pax!$1:$1,0),FALSE) | J78: =VLOOKUP($F78,raw_data_pax!$1:$1048576,MATCH(J$1,raw_data_pax!$1:$1,0),FALSE) | K78: =VLOOKUP($F78,raw_data_pax!$1:$1048576,MATCH(K$1,raw_data_pax!$1:$1,0),FALSE) | L78: =VLOOKUP($F78,raw_data_pax!$1:$1048576,MATCH(L$1,raw_data_pax!$1:$1,0),FALSE) | M78: =VLOOKUP($F78,raw_data_pax!$1:$1048576,MATCH(M$1,raw_data_pax!$1:$1,0),FALSE) | N78: =VLOOKUP($F78,raw_data_pax!$1:$1048576,MATCH(N$1,raw_data_pax!$1:$1,0),FALSE) | O78: =VLOOKUP($F78,raw_data_pax!$1:$1048576,MATCH(O$1,raw_data_pax!$1:$1,0),FALSE) | ... Q78: =VLOOKUP($F78,raw_data_pax!$1:$1048576,MATCH(Q$1,raw_data_pax!$1:$1,0),FALSE) | R78: =R20*R73 | S78: =S20*S73 | T78: =T20*T73 | U78: =U20*U73 | V78: =V20*V73 | W78: =W20*W73 | X78: =X20*X73 | Y78: =Y20*Y73 | ... BA78: =BA20*BA73
C79: - Peak Hour departure Movement(ADPM) | D79: float0 | F79: ADPM/movement/d/첨두시 | H79: =MIN(VLOOKUP($F79,raw_data_pax!$1:$1048576,MATCH(H$1,raw_data_pax!$1:$1,0),FALSE),H78) | I79: =MIN(VLOOKUP($F79,raw_data_pax!$1:$1048576,MATCH(I$1,raw_data_pax!$1:$1,0),FALSE),I78) | J79: =MIN(VLOOKUP($F79,raw_data_pax!$1:$1048576,MATCH(J$1,raw_data_pax!$1:$1,0),FALSE),J78) | K79: =MIN(VLOOKUP($F79,raw_data_pax!$1:$1048576,MATCH(K$1,raw_data_pax!$1:$1,0),FALSE),K78) | L79: =MIN(VLOOKUP($F79,raw_data_pax!$1:$1048576,MATCH(L$1,raw_data_pax!$1:$1,0),FALSE),L78) | M79: =MIN(VLOOKUP($F79,raw_data_pax!$1:$1048576,MATCH(M$1,raw_data_pax!$1:$1,0),FALSE),M78) | N79: =MIN(VLOOKUP($F79,raw_data_pax!$1:$1048576,MATCH(N$1,raw_data_pax!$1:$1,0),FALSE),N78) | O79: =MIN(VLOOKUP($F79,raw_data_pax!$1:$1048576,MATCH(O$1,raw_data_pax!$1:$1,0),FALSE),O78) | ... Q79: =MIN(VLOOKUP($F79,raw_data_pax!$1:$1048576,MATCH(Q$1,raw_data_pax!$1:$1,0),FALSE),Q78) | R79: =R78*R103 | S79: =S78*S103 | T79: =T78*T103 | U79: =U78*U103 | V79: =V78*V103 | W79: =W78*W103 | X79: =X78*X103 | Y79: =Y78*Y103 | ... BA79: =BA78*BA103
C80: - Peak Hour aival Movement(ADPM) | D80: float0 | F80: ADPM/movement/a/첨두시 | H80: =MIN(VLOOKUP($F80,raw_data_pax!$1:$1048576,MATCH(H$1,raw_data_pax!$1:$1,0),FALSE),H78) | I80: =MIN(VLOOKUP($F80,raw_data_pax!$1:$1048576,MATCH(I$1,raw_data_pax!$1:$1,0),FALSE),I78) | J80: =MIN(VLOOKUP($F80,raw_data_pax!$1:$1048576,MATCH(J$1,raw_data_pax!$1:$1,0),FALSE),J78) | K80: =MIN(VLOOKUP($F80,raw_data_pax!$1:$1048576,MATCH(K$1,raw_data_pax!$1:$1,0),FALSE),K78) | L80: =MIN(VLOOKUP($F80,raw_data_pax!$1:$1048576,MATCH(L$1,raw_data_pax!$1:$1,0),FALSE),L78) | M80: =MIN(VLOOKUP($F80,raw_data_pax!$1:$1048576,MATCH(M$1,raw_data_pax!$1:$1,0),FALSE),M78) | N80: =MIN(VLOOKUP($F80,raw_data_pax!$1:$1048576,MATCH(N$1,raw_data_pax!$1:$1,0),FALSE),N78) | O80: =MIN(VLOOKUP($F80,raw_data_pax!$1:$1048576,MATCH(O$1,raw_data_pax!$1:$1,0),FALSE),O78) | ... Q80: =MIN(VLOOKUP($F80,raw_data_pax!$1:$1048576,MATCH(Q$1,raw_data_pax!$1:$1,0),FALSE),Q78) | R80: =R78*R104 | S80: =S78*S104 | T80: =T78*T104 | U80: =U78*U104 | V80: =V78*V104 | W80: =W78*W104 | X80: =X78*X104 | Y80: =Y78*Y104 | ... BA80: =BA78*BA104
A81: Terminal(ADPM) | B81: Passengers(ADPM) | C81: Passenger PHF(%)(ADPM) | D81: percent4 | F81: ADPM/total_pax/all/PHF | H81: =VLOOKUP($F81,raw_data_pax!$1:$1048576,MATCH(H$1,raw_data_pax!$1:$1,0),FALSE) | I81: =VLOOKUP($F81,raw_data_pax!$1:$1048576,MATCH(I$1,raw_data_pax!$1:$1,0),FALSE) | J81: =VLOOKUP($F81,raw_data_pax!$1:$1048576,MATCH(J$1,raw_data_pax!$1:$1,0),FALSE) | K81: =VLOOKUP($F81,raw_data_pax!$1:$1048576,MATCH(K$1,raw_data_pax!$1:$1,0),FALSE) | L81: =VLOOKUP($F81,raw_data_pax!$1:$1048576,MATCH(L$1,raw_data_pax!$1:$1,0),FALSE) | M81: =VLOOKUP($F81,raw_data_pax!$1:$1048576,MATCH(M$1,raw_data_pax!$1:$1,0),FALSE) | N81: =VLOOKUP($F81,raw_data_pax!$1:$1048576,MATCH(N$1,raw_data_pax!$1:$1,0),FALSE) | O81: =VLOOKUP($F81,raw_data_pax!$1:$1048576,MATCH(O$1,raw_data_pax!$1:$1,0),FALSE) | ... Q81: =VLOOKUP($F81,raw_data_pax!$1:$1048576,MATCH(Q$1,raw_data_pax!$1:$1,0),FALSE) | R81: =0.0021*R20^(-0.183)*$G$84 | S81: =0.0021*S20^(-0.183)*$G$84 | T81: =0.0021*T20^(-0.183)*$G$84 | U81: =0.0021*U20^(-0.183)*$G$84 | V81: =0.0021*V20^(-0.183)*$G$84 | W81: =0.0021*W20^(-0.183)*$G$84 | X81: =0.0021*X20^(-0.183)*$G$84 | Y81: =0.0021*Y20^(-0.183)*$G$84 | ... BA81: =0.0021*BA20^(-0.183)*$G$84
C82: - Passenger H Factor(ADPM) | D82: float1 | F82: ADPM/total_pax/all/H팩터 | H82: =VLOOKUP($F82,raw_data_pax!$1:$1048576,MATCH(H$1,raw_data_pax!$1:$1,0),FALSE) | I82: =VLOOKUP($F82,raw_data_pax!$1:$1048576,MATCH(I$1,raw_data_pax!$1:$1,0),FALSE) | J82: =VLOOKUP($F82,raw_data_pax!$1:$1048576,MATCH(J$1,raw_data_pax!$1:$1,0),FALSE) | K82: =VLOOKUP($F82,raw_data_pax!$1:$1048576,MATCH(K$1,raw_data_pax!$1:$1,0),FALSE) | L82: =VLOOKUP($F82,raw_data_pax!$1:$1048576,MATCH(L$1,raw_data_pax!$1:$1,0),FALSE) | M82: =VLOOKUP($F82,raw_data_pax!$1:$1048576,MATCH(M$1,raw_data_pax!$1:$1,0),FALSE) | N82: =VLOOKUP($F82,raw_data_pax!$1:$1048576,MATCH(N$1,raw_data_pax!$1:$1,0),FALSE) | O82: =VLOOKUP($F82,raw_data_pax!$1:$1048576,MATCH(O$1,raw_data_pax!$1:$1,0),FALSE) | ... Q82: =VLOOKUP($F82,raw_data_pax!$1:$1048576,MATCH(Q$1,raw_data_pax!$1:$1,0),FALSE) | R82: =1/R81/R83 | S82: =1/S81/S83 | T82: =1/T81/T83 | U82: =1/U81/U83 | V82: =1/V81/V83 | W82: =1/W81/W83 | X82: =1/X81/X83 | Y82: =1/Y81/Y83 | ... BA82: =1/BA81/BA83
C83: - Passenger D Factor(ADPM) | D83: float1 | F83: ADPM/total_pax/all/D팩터 | G83: =SUMIF($H$170:$Q$170,"O",H83:Q83)/COUNTIFS($H$170:$Q$170,"O",H83:Q83,"<>0") | H83: =VLOOKUP($F83,raw_data_pax!$1:$1048576,MATCH(H$1,raw_data_pax!$1:$1,0),FALSE) | I83: =VLOOKUP($F83,raw_data_pax!$1:$1048576,MATCH(I$1,raw_data_pax!$1:$1,0),FALSE) | J83: =VLOOKUP($F83,raw_data_pax!$1:$1048576,MATCH(J$1,raw_data_pax!$1:$1,0),FALSE) | K83: =VLOOKUP($F83,raw_data_pax!$1:$1048576,MATCH(K$1,raw_data_pax!$1:$1,0),FALSE) | L83: =VLOOKUP($F83,raw_data_pax!$1:$1048576,MATCH(L$1,raw_data_pax!$1:$1,0),FALSE) | M83: =VLOOKUP($F83,raw_data_pax!$1:$1048576,MATCH(M$1,raw_data_pax!$1:$1,0),FALSE) | N83: =VLOOKUP($F83,raw_data_pax!$1:$1048576,MATCH(N$1,raw_data_pax!$1:$1,0),FALSE) | O83: =VLOOKUP($F83,raw_data_pax!$1:$1048576,MATCH(O$1,raw_data_pax!$1:$1,0),FALSE) | ... Q83: =VLOOKUP($F83,raw_data_pax!$1:$1048576,MATCH(Q$1,raw_data_pax!$1:$1,0),FALSE) | R83: =$G$83 | S83: =$G$83 | T83: =$G$83 | U83: =$G$83 | V83: =$G$83 | W83: =$G$83 | X83: =$G$83 | Y83: =$G$83 | ... BA83: =$G$83
C84: Passenger PHF / Movement PHF(ADPM) | D84: percent1 | F84: 여객PHF / 운항 PHF | G84: =SUMIF($H$169:$Q$169,"O",H84:Q84)/COUNTIFS($H$169:$Q$169,"O",H84:Q84,"<>0") | H84: =H81/H76 | I84: =I81/I76 | J84: =J81/J76 | K84: =K81/K76 | L84: =L81/L76 | M84: =M81/M76 | N84: =N81/N76 | O84: =O81/O76 | ... Q84: =Q81/Q76
C85: Peak Hour Passengers(ADPM) | D85: float0 | F85: ADPM/total_pax/all/첨두시 | H85: =VLOOKUP($F85,raw_data_pax!$1:$1048576,MATCH(H$1,raw_data_pax!$1:$1,0),FALSE) | I85: =VLOOKUP($F85,raw_data_pax!$1:$1048576,MATCH(I$1,raw_data_pax!$1:$1,0),FALSE) | J85: =VLOOKUP($F85,raw_data_pax!$1:$1048576,MATCH(J$1,raw_data_pax!$1:$1,0),FALSE) | K85: =VLOOKUP($F85,raw_data_pax!$1:$1048576,MATCH(K$1,raw_data_pax!$1:$1,0),FALSE) | L85: =VLOOKUP($F85,raw_data_pax!$1:$1048576,MATCH(L$1,raw_data_pax!$1:$1,0),FALSE) | M85: =VLOOKUP($F85,raw_data_pax!$1:$1048576,MATCH(M$1,raw_data_pax!$1:$1,0),FALSE) | N85: =VLOOKUP($F85,raw_data_pax!$1:$1048576,MATCH(N$1,raw_data_pax!$1:$1,0),FALSE) | O85: =VLOOKUP($F85,raw_data_pax!$1:$1048576,MATCH(O$1,raw_data_pax!$1:$1,0),FALSE) | ... Q85: =VLOOKUP($F85,raw_data_pax!$1:$1048576,MATCH(Q$1,raw_data_pax!$1:$1,0),FALSE) | R85: =R2*R81 | S85: =S2*S81 | T85: =T2*T81 | U85: =U2*U81 | V85: =V2*V81 | W85: =W2*W81 | X85: =X2*X81 | Y85: =Y2*Y81 | ... BA85: =BA2*BA81
C86: - Peak Hour departure Passengers(ADPM) | D86: float0 | F86: ADPM/total_pax/d/첨두시 | H86: =MIN(VLOOKUP($F86,raw_data_pax!$1:$1048576,MATCH(H$1,raw_data_pax!$1:$1,0),FALSE),H85) | I86: =MIN(VLOOKUP($F86,raw_data_pax!$1:$1048576,MATCH(I$1,raw_data_pax!$1:$1,0),FALSE),I85) | J86: =MIN(VLOOKUP($F86,raw_data_pax!$1:$1048576,MATCH(J$1,raw_data_pax!$1:$1,0),FALSE),J85) | K86: =MIN(VLOOKUP($F86,raw_data_pax!$1:$1048576,MATCH(K$1,raw_data_pax!$1:$1,0),FALSE),K85) | L86: =MIN(VLOOKUP($F86,raw_data_pax!$1:$1048576,MATCH(L$1,raw_data_pax!$1:$1,0),FALSE),L85) | M86: =MIN(VLOOKUP($F86,raw_data_pax!$1:$1048576,MATCH(M$1,raw_data_pax!$1:$1,0),FALSE),M85) | N86: =MIN(VLOOKUP($F86,raw_data_pax!$1:$1048576,MATCH(N$1,raw_data_pax!$1:$1,0),FALSE),N85) | O86: =MIN(VLOOKUP($F86,raw_data_pax!$1:$1048576,MATCH(O$1,raw_data_pax!$1:$1,0),FALSE),O85) | ... Q86: =MIN(VLOOKUP($F86,raw_data_pax!$1:$1048576,MATCH(Q$1,raw_data_pax!$1:$1,0),FALSE),Q85)
C87: - Peak Hour aival Passengers(ADPM) | D87: float0 | F87: ADPM/total_pax/a/첨두시 | H87: =MIN(VLOOKUP($F87,raw_data_pax!$1:$1048576,MATCH(H$1,raw_data_pax!$1:$1,0),FALSE),H85) | I87: =MIN(VLOOKUP($F87,raw_data_pax!$1:$1048576,MATCH(I$1,raw_data_pax!$1:$1,0),FALSE),I85) | J87: =MIN(VLOOKUP($F87,raw_data_pax!$1:$1048576,MATCH(J$1,raw_data_pax!$1:$1,0),FALSE),J85) | K87: =MIN(VLOOKUP($F87,raw_data_pax!$1:$1048576,MATCH(K$1,raw_data_pax!$1:$1,0),FALSE),K85) | L87: =MIN(VLOOKUP($F87,raw_data_pax!$1:$1048576,MATCH(L$1,raw_data_pax!$1:$1,0),FALSE),L85) | M87: =MIN(VLOOKUP($F87,raw_data_pax!$1:$1048576,MATCH(M$1,raw_data_pax!$1:$1,0),FALSE),M85) | N87: =MIN(VLOOKUP($F87,raw_data_pax!$1:$1048576,MATCH(N$1,raw_data_pax!$1:$1,0),FALSE),N85) | O87: =MIN(VLOOKUP($F87,raw_data_pax!$1:$1048576,MATCH(O$1,raw_data_pax!$1:$1,0),FALSE),O85) | ... Q87: =MIN(VLOOKUP($F87,raw_data_pax!$1:$1048576,MATCH(Q$1,raw_data_pax!$1:$1,0),FALSE),Q85)
C88: Peak Hour Seats(ADPM) | D88: float0 | F88: ADPM/total_seat_count/all/첨두시 | H88: =VLOOKUP($F88,raw_data_pax!$1:$1048576,MATCH(H$1,raw_data_pax!$1:$1,0),FALSE) | I88: =VLOOKUP($F88,raw_data_pax!$1:$1048576,MATCH(I$1,raw_data_pax!$1:$1,0),FALSE) | J88: =VLOOKUP($F88,raw_data_pax!$1:$1048576,MATCH(J$1,raw_data_pax!$1:$1,0),FALSE) | K88: =VLOOKUP($F88,raw_data_pax!$1:$1048576,MATCH(K$1,raw_data_pax!$1:$1,0),FALSE) | L88: =VLOOKUP($F88,raw_data_pax!$1:$1048576,MATCH(L$1,raw_data_pax!$1:$1,0),FALSE) | M88: =VLOOKUP($F88,raw_data_pax!$1:$1048576,MATCH(M$1,raw_data_pax!$1:$1,0),FALSE) | N88: =VLOOKUP($F88,raw_data_pax!$1:$1048576,MATCH(N$1,raw_data_pax!$1:$1,0),FALSE) | O88: =VLOOKUP($F88,raw_data_pax!$1:$1048576,MATCH(O$1,raw_data_pax!$1:$1,0),FALSE) | ... Q88: =VLOOKUP($F88,raw_data_pax!$1:$1048576,MATCH(Q$1,raw_data_pax!$1:$1,0),FALSE)
C89: Peak Hour Load Factor(%)(ADPM) | D89: percent1 | F89: 첨두여객(명) / 첨두공급좌석(수) | H89: =H85/H88 | I89: =I85/I88 | J89: =J85/J88 | K89: =K85/K88 | L89: =L85/L88 | M89: =M85/M88 | N89: =N85/N88 | O89: =O85/O88 | ... Q89: =Q85/Q88
B90: OD Passengers(ADPM) | C90: Peak Hour OD Passengers(ADPM) | D90: float0 | F90: ADPM/od_pax/all/첨두시 | H90: =VLOOKUP($F90,raw_data_pax!$1:$1048576,MATCH(H$1,raw_data_pax!$1:$1,0),FALSE) | I90: =VLOOKUP($F90,raw_data_pax!$1:$1048576,MATCH(I$1,raw_data_pax!$1:$1,0),FALSE) | J90: =VLOOKUP($F90,raw_data_pax!$1:$1048576,MATCH(J$1,raw_data_pax!$1:$1,0),FALSE) | K90: =VLOOKUP($F90,raw_data_pax!$1:$1048576,MATCH(K$1,raw_data_pax!$1:$1,0),FALSE) | L90: =VLOOKUP($F90,raw_data_pax!$1:$1048576,MATCH(L$1,raw_data_pax!$1:$1,0),FALSE) | M90: =VLOOKUP($F90,raw_data_pax!$1:$1048576,MATCH(M$1,raw_data_pax!$1:$1,0),FALSE) | N90: =VLOOKUP($F90,raw_data_pax!$1:$1048576,MATCH(N$1,raw_data_pax!$1:$1,0),FALSE) | O90: =VLOOKUP($F90,raw_data_pax!$1:$1048576,MATCH(O$1,raw_data_pax!$1:$1,0),FALSE) | ... Q90: =VLOOKUP($F90,raw_data_pax!$1:$1048576,MATCH(Q$1,raw_data_pax!$1:$1,0),FALSE) | R90: =R85*R105 | S90: =S85*S105 | T90: =T85*T105 | U90: =U85*U105 | V90: =V85*V105 | W90: =W85*W105 | X90: =X85*X105 | Y90: =Y85*Y105 | ... BA90: =BA85*BA105
C91: - Peak Hour OD departure Passengers(ADPM) | D91: float0 | F91: ADPM/od_pax/d/첨두시 | H91: =MIN(VLOOKUP($F91,raw_data_pax!$1:$1048576,MATCH(H$1,raw_data_pax!$1:$1,0),FALSE),H90) | I91: =MIN(VLOOKUP($F91,raw_data_pax!$1:$1048576,MATCH(I$1,raw_data_pax!$1:$1,0),FALSE),I90) | J91: =MIN(VLOOKUP($F91,raw_data_pax!$1:$1048576,MATCH(J$1,raw_data_pax!$1:$1,0),FALSE),J90) | K91: =MIN(VLOOKUP($F91,raw_data_pax!$1:$1048576,MATCH(K$1,raw_data_pax!$1:$1,0),FALSE),K90) | L91: =MIN(VLOOKUP($F91,raw_data_pax!$1:$1048576,MATCH(L$1,raw_data_pax!$1:$1,0),FALSE),L90) | M91: =MIN(VLOOKUP($F91,raw_data_pax!$1:$1048576,MATCH(M$1,raw_data_pax!$1:$1,0),FALSE),M90) | N91: =MIN(VLOOKUP($F91,raw_data_pax!$1:$1048576,MATCH(N$1,raw_data_pax!$1:$1,0),FALSE),N90) | O91: =MIN(VLOOKUP($F91,raw_data_pax!$1:$1048576,MATCH(O$1,raw_data_pax!$1:$1,0),FALSE),O90) | ... Q91: =MIN(VLOOKUP($F91,raw_data_pax!$1:$1048576,MATCH(Q$1,raw_data_pax!$1:$1,0),FALSE),Q90) | R91: =R90*R106 | S91: =S90*S106 | T91: =T90*T106 | U91: =U90*U106 | V91: =V90*V106 | W91: =W90*W106 | X91: =X90*X106 | Y91: =Y90*Y106 | ... BA91: =BA90*BA106
C92: - Peak Hour OD aival Passengers(ADPM) | D92: float0 | F92: ADPM/od_pax/a/첨두시 | H92: =MIN(VLOOKUP($F92,raw_data_pax!$1:$1048576,MATCH(H$1,raw_data_pax!$1:$1,0),FALSE),H90) | I92: =MIN(VLOOKUP($F92,raw_data_pax!$1:$1048576,MATCH(I$1,raw_data_pax!$1:$1,0),FALSE),I90) | J92: =MIN(VLOOKUP($F92,raw_data_pax!$1:$1048576,MATCH(J$1,raw_data_pax!$1:$1,0),FALSE),J90) | K92: =MIN(VLOOKUP($F92,raw_data_pax!$1:$1048576,MATCH(K$1,raw_data_pax!$1:$1,0),FALSE),K90) | L92: =MIN(VLOOKUP($F92,raw_data_pax!$1:$1048576,MATCH(L$1,raw_data_pax!$1:$1,0),FALSE),L90) | M92: =MIN(VLOOKUP($F92,raw_data_pax!$1:$1048576,MATCH(M$1,raw_data_pax!$1:$1,0),FALSE),M90) | N92: =MIN(VLOOKUP($F92,raw_data_pax!$1:$1048576,MATCH(N$1,raw_data_pax!$1:$1,0),FALSE),N90) | O92: =MIN(VLOOKUP($F92,raw_data_pax!$1:$1048576,MATCH(O$1,raw_data_pax!$1:$1,0),FALSE),O90) | ... Q92: =MIN(VLOOKUP($F92,raw_data_pax!$1:$1048576,MATCH(Q$1,raw_data_pax!$1:$1,0),FALSE),Q90) | R92: =R90*R107 | S92: =S90*S107 | T92: =T90*T107 | U92: =U90*U107 | V92: =V90*V107 | W92: =W90*W107 | X92: =X90*X107 | Y92: =Y90*Y107 | ... BA92: =BA90*BA107
B93: Transfer Passengers(ADPM) | C93: Peak Hour Transfer Passengers(ADPM) | D93: float0 | F93: ADPM/tr_pax/all/첨두시 | H93: =VLOOKUP($F93,raw_data_pax!$1:$1048576,MATCH(H$1,raw_data_pax!$1:$1,0),FALSE) | I93: =VLOOKUP($F93,raw_data_pax!$1:$1048576,MATCH(I$1,raw_data_pax!$1:$1,0),FALSE) | J93: =VLOOKUP($F93,raw_data_pax!$1:$1048576,MATCH(J$1,raw_data_pax!$1:$1,0),FALSE) | K93: =VLOOKUP($F93,raw_data_pax!$1:$1048576,MATCH(K$1,raw_data_pax!$1:$1,0),FALSE) | L93: =VLOOKUP($F93,raw_data_pax!$1:$1048576,MATCH(L$1,raw_data_pax!$1:$1,0),FALSE) | M93: =VLOOKUP($F93,raw_data_pax!$1:$1048576,MATCH(M$1,raw_data_pax!$1:$1,0),FALSE) | N93: =VLOOKUP($F93,raw_data_pax!$1:$1048576,MATCH(N$1,raw_data_pax!$1:$1,0),FALSE) | O93: =VLOOKUP($F93,raw_data_pax!$1:$1048576,MATCH(O$1,raw_data_pax!$1:$1,0),FALSE) | ... Q93: =VLOOKUP($F93,raw_data_pax!$1:$1048576,MATCH(Q$1,raw_data_pax!$1:$1,0),FALSE) | R93: =R85*R108 | S93: =S85*S108 | T93: =T85*T108 | U93: =U85*U108 | V93: =V85*V108 | W93: =W85*W108 | X93: =X85*X108 | Y93: =Y85*Y108 | ... BA93: =BA85*BA108
C94: - Peak Hour Transfer departure Passnegers(ADPM) | D94: float0 | F94: ADPM/tr_pax/d/첨두시 | H94: =MIN(VLOOKUP($F94,raw_data_pax!$1:$1048576,MATCH(H$1,raw_data_pax!$1:$1,0),FALSE),H93) | I94: =MIN(VLOOKUP($F94,raw_data_pax!$1:$1048576,MATCH(I$1,raw_data_pax!$1:$1,0),FALSE),I93) | J94: =MIN(VLOOKUP($F94,raw_data_pax!$1:$1048576,MATCH(J$1,raw_data_pax!$1:$1,0),FALSE),J93) | K94: =MIN(VLOOKUP($F94,raw_data_pax!$1:$1048576,MATCH(K$1,raw_data_pax!$1:$1,0),FALSE),K93) | L94: =MIN(VLOOKUP($F94,raw_data_pax!$1:$1048576,MATCH(L$1,raw_data_pax!$1:$1,0),FALSE),L93) | M94: =MIN(VLOOKUP($F94,raw_data_pax!$1:$1048576,MATCH(M$1,raw_data_pax!$1:$1,0),FALSE),M93) | N94: =MIN(VLOOKUP($F94,raw_data_pax!$1:$1048576,MATCH(N$1,raw_data_pax!$1:$1,0),FALSE),N93) | O94: =MIN(VLOOKUP($F94,raw_data_pax!$1:$1048576,MATCH(O$1,raw_data_pax!$1:$1,0),FALSE),O93) | ... Q94: =MIN(VLOOKUP($F94,raw_data_pax!$1:$1048576,MATCH(Q$1,raw_data_pax!$1:$1,0),FALSE),Q93) | R94: =R93*R109 | S94: =S93*S109 | T94: =T93*T109 | U94: =U93*U109 | V94: =V93*V109 | W94: =W93*W109 | X94: =X93*X109 | Y94: =Y93*Y109 | ... BA94: =BA93*BA109
C95: - Peak Hour Transfer aival Passengers(ADPM) | D95: float0 | F95: ADPM/tr_pax/a/첨두시 | H95: =MIN(VLOOKUP($F95,raw_data_pax!$1:$1048576,MATCH(H$1,raw_data_pax!$1:$1,0),FALSE),H93) | I95: =MIN(VLOOKUP($F95,raw_data_pax!$1:$1048576,MATCH(I$1,raw_data_pax!$1:$1,0),FALSE),I93) | J95: =MIN(VLOOKUP($F95,raw_data_pax!$1:$1048576,MATCH(J$1,raw_data_pax!$1:$1,0),FALSE),J93) | K95: =MIN(VLOOKUP($F95,raw_data_pax!$1:$1048576,MATCH(K$1,raw_data_pax!$1:$1,0),FALSE),K93) | L95: =MIN(VLOOKUP($F95,raw_data_pax!$1:$1048576,MATCH(L$1,raw_data_pax!$1:$1,0),FALSE),L93) | M95: =MIN(VLOOKUP($F95,raw_data_pax!$1:$1048576,MATCH(M$1,raw_data_pax!$1:$1,0),FALSE),M93) | N95: =MIN(VLOOKUP($F95,raw_data_pax!$1:$1048576,MATCH(N$1,raw_data_pax!$1:$1,0),FALSE),N93) | O95: =MIN(VLOOKUP($F95,raw_data_pax!$1:$1048576,MATCH(O$1,raw_data_pax!$1:$1,0),FALSE),O93) | ... Q95: =MIN(VLOOKUP($F95,raw_data_pax!$1:$1048576,MATCH(Q$1,raw_data_pax!$1:$1,0),FALSE),Q93) | R95: =R93*R110 | S95: =S93*S110 | T95: =T93*T110 | U95: =U93*U110 | V95: =V93*V110 | W95: =W93*W110 | X95: =X93*X110 | Y95: =Y93*Y110 | ... BA95: =BA93*BA110
B96: Crew(ADPM) | C96: Peak Hour Crew(ADPM) | D96: float0 | F96: 첨두여객(명) X 승무원비율(%) | H96: =H85*H19 | I96: =I85*I19 | J96: =J85*J19 | K96: =K85*K19 | L96: =L85*L19 | M96: =M85*M19 | N96: =N85*N19 | O96: =O85*O19 | ... Q96: =Q85*Q19
C97: - Peak Hour departure Crew(ADPM) | D97: float0 | F97: 첨두출발(명) X 승무원비율(%) | H97: =H86*H19 | I97: =I86*I19 | J97: =J86*J19 | K97: =K86*K19 | L97: =L86*L19 | M97: =M86*M19 | N97: =N86*N19 | O97: =O86*O19 | ... Q97: =Q86*Q19
C98: - Peak Hour aival Crew(ADPM) | D98: float0 | F98: 첨두도착(명) X 승무원비율(%) | H98: =H87*H19 | I98: =I87*I19 | J98: =J87*J19 | K98: =K87*K19 | L98: =L87*L19 | M98: =M87*M19 | N98: =N87*N19 | O98: =O87*O19 | ... Q98: =Q87*Q19
B99: Farewell/Greeter(ADPM) | C99: Fareweller Rate(ADPM) | D99: percent1 | F99: 실적조사, 경험수치 활용(여객 1인당 0.39명) | H99: 0.39 | I99: 0.39 | J99: 0.39 | K99: 0.39 | L99: 0.39 | M99: 0.39 | N99: 0.39 | O99: 0.39 | P99: 0.39 | Q99: 0.39
C100: Peak Hour Farewellers(ADPM) | D100: float0 | F100: 첨두OD출발 X 환송객원단위 | H100: =H91*H99 | I100: =I91*I99 | J100: =J91*J99 | K100: =K91*K99 | L100: =L91*L99 | M100: =M91*M99 | N100: =N91*N99 | O100: =O91*O99 | ... Q100: =Q91*Q99
C101: Greeter Rate(ADPM) | D101: percent1 | F101: 실적조사, 경험수치 활용(여객 1인당 0.45명) | H101: 0.45 | I101: 0.45 | J101: 0.45 | K101: 0.45 | L101: 0.45 | M101: 0.45 | N101: 0.45 | O101: 0.45 | P101: 0.45 | Q101: 0.45
C102: Peak Hour Greeters(ADPM) | D102: float0 | F102: 첨두OD도착 X 환영객원단위 | H102: =H92*H101 | I102: =I92*I101 | J102: =J92*J101 | K102: =K92*K101 | L102: =L92*L101 | M102: =M92*M101 | N102: =N92*N101 | O102: =O92*O101 | ... Q102: =Q92*Q101
A103: Directional Factor(ADPM) | B103: Movement Directional Factor(ADPM) | C103: departure Movement Directional Factor(%)(ADPM) | D103: percent1 | F103: ADPM/movement/d/중방향계수 | G103: =SUMIF($H$171:$Q$171,"O",H103:Q103)/COUNTIFS($H$171:$Q$171,"O",H103:Q103,"<>0") | H103: =H79/H78 | I103: =I79/I78 | J103: =J79/J78 | K103: =K79/K78 | L103: =L79/L78 | M103: =M79/M78 | N103: =N79/N78 | O103: =O79/O78 | ... Q103: =Q79/Q78 | R103: =$G103 | S103: =$G103 | T103: =$G103 | U103: =$G103 | V103: =$G103 | W103: =$G103 | X103: =$G103 | Y103: =$G103 | ... BA103: =$G103
...

Sheet Airside Demand
A1: top | B1: mid | C1: low | D1: decimal | E1: changeable | F1: 변수설명 | G1: Ref_Index | H1: =I1-1 | I1: =J1-1 | J1: =K1-1 | K1: =L1-1 | L1: =M1-1 | M1: =N1-1 | N1: =O1-1 | O1: =P1-1 | P1: =Q1-1 | Q1: =ref!B4 | R1: =Q1+1 | S1: =R1+1 | T1: =S1+1 | U1: =T1+1 | V1: =U1+1 | W1: =V1+1 | X1: =W1+1 | Y1: =X1+1 | ... BA1: =AZ1+1
A2: Airside Flight Index | C2: Annual Movements | D2: float0 | F2: 연간운항 | H2: =VLOOKUP($F2,raw_data_airside!$1:$1048576,MATCH(H$1,raw_data_airside!$1:$1,0),FALSE) | I2: =VLOOKUP($F2,raw_data_airside!$1:$1048576,MATCH(I$1,raw_data_airside!$1:$1,0),FALSE) | J2: =VLOOKUP($F2,raw_data_airside!$1:$1048576,MATCH(J$1,raw_data_airside!$1:$1,0),FALSE) | K2: =VLOOKUP($F2,raw_data_airside!$1:$1048576,MATCH(K$1,raw_data_airside!$1:$1,0),FALSE) | L2: =VLOOKUP($F2,raw_data_airside!$1:$1048576,MATCH(L$1,raw_data_airside!$1:$1,0),FALSE) | M2: =VLOOKUP($F2,raw_data_airside!$1:$1048576,MATCH(M$1,raw_data_airside!$1:$1,0),FALSE) | N2: =VLOOKUP($F2,raw_data_airside!$1:$1048576,MATCH(N$1,raw_data_airside!$1:$1,0),FALSE) | O2: =VLOOKUP($F2,raw_data_airside!$1:$1048576,MATCH(O$1,raw_data_airside!$1:$1,0),FALSE) | ... Q2: =VLOOKUP($F2,raw_data_airside!$1:$1048576,MATCH(Q$1,raw_data_airside!$1:$1,0),FALSE) | R2: ='Pax Demand'!R20+'Cargo Demand'!R3 | S2: ='Pax Demand'!S20+'Cargo Demand'!S3 | T2: ='Pax Demand'!T20+'Cargo Demand'!T3 | U2: ='Pax Demand'!U20+'Cargo Demand'!U3 | V2: ='Pax Demand'!V20+'Cargo Demand'!V3 | W2: ='Pax Demand'!W20+'Cargo Demand'!W3 | X2: ='Pax Demand'!X20+'Cargo Demand'!X3 | Y2: ='Pax Demand'!Y20+'Cargo Demand'!Y3 | ... BA2: ='Pax Demand'!BA20+'Cargo Demand'!BA3
C3: Average Taxiing Time Per Aircraft(min) | D3: float0 | F3: 대당택싱평균 | H3: =VLOOKUP($F3,raw_data_airside!$1:$1048576,MATCH(H$1,raw_data_airside!$1:$1,0),FALSE) | I3: =VLOOKUP($F3,raw_data_airside!$1:$1048576,MATCH(I$1,raw_data_airside!$1:$1,0),FALSE) | J3: =VLOOKUP($F3,raw_data_airside!$1:$1048576,MATCH(J$1,raw_data_airside!$1:$1,0),FALSE) | K3: =VLOOKUP($F3,raw_data_airside!$1:$1048576,MATCH(K$1,raw_data_airside!$1:$1,0),FALSE) | L3: =VLOOKUP($F3,raw_data_airside!$1:$1048576,MATCH(L$1,raw_data_airside!$1:$1,0),FALSE) | M3: =VLOOKUP($F3,raw_data_airside!$1:$1048576,MATCH(M$1,raw_data_airside!$1:$1,0),FALSE) | N3: =VLOOKUP($F3,raw_data_airside!$1:$1048576,MATCH(N$1,raw_data_airside!$1:$1,0),FALSE) | O3: =VLOOKUP($F3,raw_data_airside!$1:$1048576,MATCH(O$1,raw_data_airside!$1:$1,0),FALSE) | ... Q3: =VLOOKUP($F3,raw_data_airside!$1:$1048576,MATCH(Q$1,raw_data_airside!$1:$1,0),FALSE)
C4: Average PeakTime TurnAround Standing Time(min) | D4: float0 | F4: 피크시간 턴어라운드편 평균주기시간(분) | H4: =VLOOKUP($F4,raw_data_airside!$1:$1048576,MATCH(H$1,raw_data_airside!$1:$1,0),FALSE) | I4: =VLOOKUP($F4,raw_data_airside!$1:$1048576,MATCH(I$1,raw_data_airside!$1:$1,0),FALSE) | J4: =VLOOKUP($F4,raw_data_airside!$1:$1048576,MATCH(J$1,raw_data_airside!$1:$1,0),FALSE) | K4: =VLOOKUP($F4,raw_data_airside!$1:$1048576,MATCH(K$1,raw_data_airside!$1:$1,0),FALSE) | L4: =VLOOKUP($F4,raw_data_airside!$1:$1048576,MATCH(L$1,raw_data_airside!$1:$1,0),FALSE) | M4: =VLOOKUP($F4,raw_data_airside!$1:$1048576,MATCH(M$1,raw_data_airside!$1:$1,0),FALSE) | N4: =VLOOKUP($F4,raw_data_airside!$1:$1048576,MATCH(N$1,raw_data_airside!$1:$1,0),FALSE) | O4: =VLOOKUP($F4,raw_data_airside!$1:$1048576,MATCH(O$1,raw_data_airside!$1:$1,0),FALSE) | ... Q4: =VLOOKUP($F4,raw_data_airside!$1:$1048576,MATCH(Q$1,raw_data_airside!$1:$1,0),FALSE)
C5: Average PeakTIme TurnAround Ground Time(min) | D5: float0 | F5: 피크시간 턴어라운드편 평균그라운드시간(분) | H5: =VLOOKUP($F5,raw_data_airside!$1:$1048576,MATCH(H$1,raw_data_airside!$1:$1,0),FALSE) | I5: =VLOOKUP($F5,raw_data_airside!$1:$1048576,MATCH(I$1,raw_data_airside!$1:$1,0),FALSE) | J5: =VLOOKUP($F5,raw_data_airside!$1:$1048576,MATCH(J$1,raw_data_airside!$1:$1,0),FALSE) | K5: =VLOOKUP($F5,raw_data_airside!$1:$1048576,MATCH(K$1,raw_data_airside!$1:$1,0),FALSE) | L5: =VLOOKUP($F5,raw_data_airside!$1:$1048576,MATCH(L$1,raw_data_airside!$1:$1,0),FALSE) | M5: =VLOOKUP($F5,raw_data_airside!$1:$1048576,MATCH(M$1,raw_data_airside!$1:$1,0),FALSE) | N5: =VLOOKUP($F5,raw_data_airside!$1:$1048576,MATCH(N$1,raw_data_airside!$1:$1,0),FALSE) | O5: =VLOOKUP($F5,raw_data_airside!$1:$1048576,MATCH(O$1,raw_data_airside!$1:$1,0),FALSE) | ... Q5: =VLOOKUP($F5,raw_data_airside!$1:$1048576,MATCH(Q$1,raw_data_airside!$1:$1,0),FALSE)
C6: Average TurnAround Standing Time(min) | D6: float0 | F6: 턴어라운드편 평균주기시간(분) | H6: =VLOOKUP($F6,raw_data_airside!$1:$1048576,MATCH(H$1,raw_data_airside!$1:$1,0),FALSE) | I6: =VLOOKUP($F6,raw_data_airside!$1:$1048576,MATCH(I$1,raw_data_airside!$1:$1,0),FALSE) | J6: =VLOOKUP($F6,raw_data_airside!$1:$1048576,MATCH(J$1,raw_data_airside!$1:$1,0),FALSE) | K6: =VLOOKUP($F6,raw_data_airside!$1:$1048576,MATCH(K$1,raw_data_airside!$1:$1,0),FALSE) | L6: =VLOOKUP($F6,raw_data_airside!$1:$1048576,MATCH(L$1,raw_data_airside!$1:$1,0),FALSE) | M6: =VLOOKUP($F6,raw_data_airside!$1:$1048576,MATCH(M$1,raw_data_airside!$1:$1,0),FALSE) | N6: =VLOOKUP($F6,raw_data_airside!$1:$1048576,MATCH(N$1,raw_data_airside!$1:$1,0),FALSE) | O6: =VLOOKUP($F6,raw_data_airside!$1:$1048576,MATCH(O$1,raw_data_airside!$1:$1,0),FALSE) | ... Q6: =VLOOKUP($F6,raw_data_airside!$1:$1048576,MATCH(Q$1,raw_data_airside!$1:$1,0),FALSE)
C7: Average TurnAround Ground Time(min) | D7: float0 | F7: 턴어라운드편 평균그라운드시간(분) | H7: =VLOOKUP($F7,raw_data_airside!$1:$1048576,MATCH(H$1,raw_data_airside!$1:$1,0),FALSE) | I7: =VLOOKUP($F7,raw_data_airside!$1:$1048576,MATCH(I$1,raw_data_airside!$1:$1,0),FALSE) | J7: =VLOOKUP($F7,raw_data_airside!$1:$1048576,MATCH(J$1,raw_data_airside!$1:$1,0),FALSE) | K7: =VLOOKUP($F7,raw_data_airside!$1:$1048576,MATCH(K$1,raw_data_airside!$1:$1,0),FALSE) | L7: =VLOOKUP($F7,raw_data_airside!$1:$1048576,MATCH(L$1,raw_data_airside!$1:$1,0),FALSE) | M7: =VLOOKUP($F7,raw_data_airside!$1:$1048576,MATCH(M$1,raw_data_airside!$1:$1,0),FALSE) | N7: =VLOOKUP($F7,raw_data_airside!$1:$1048576,MATCH(N$1,raw_data_airside!$1:$1,0),FALSE) | O7: =VLOOKUP($F7,raw_data_airside!$1:$1048576,MATCH(O$1,raw_data_airside!$1:$1,0),FALSE) | ... Q7: =VLOOKUP($F7,raw_data_airside!$1:$1048576,MATCH(Q$1,raw_data_airside!$1:$1,0),FALSE)
C8: Average Total Standing Time(min) | D8: float0 | F8: (오버나잇, 소산 포함) 평균주기시간(분) | H8: =VLOOKUP($F8,raw_data_airside!$1:$1048576,MATCH(H$1,raw_data_airside!$1:$1,0),FALSE) | I8: =VLOOKUP($F8,raw_data_airside!$1:$1048576,MATCH(I$1,raw_data_airside!$1:$1,0),FALSE) | J8: =VLOOKUP($F8,raw_data_airside!$1:$1048576,MATCH(J$1,raw_data_airside!$1:$1,0),FALSE) | K8: =VLOOKUP($F8,raw_data_airside!$1:$1048576,MATCH(K$1,raw_data_airside!$1:$1,0),FALSE) | L8: =VLOOKUP($F8,raw_data_airside!$1:$1048576,MATCH(L$1,raw_data_airside!$1:$1,0),FALSE) | M8: =VLOOKUP($F8,raw_data_airside!$1:$1048576,MATCH(M$1,raw_data_airside!$1:$1,0),FALSE) | N8: =VLOOKUP($F8,raw_data_airside!$1:$1048576,MATCH(N$1,raw_data_airside!$1:$1,0),FALSE) | O8: =VLOOKUP($F8,raw_data_airside!$1:$1048576,MATCH(O$1,raw_data_airside!$1:$1,0),FALSE) | ... Q8: =VLOOKUP($F8,raw_data_airside!$1:$1048576,MATCH(Q$1,raw_data_airside!$1:$1,0),FALSE)
C9: Average Total Ground Time(min) | D9: float0 | F9: (오버나잇, 소산 포함) 평균그라운드시간(분) | H9: =VLOOKUP($F9,raw_data_airside!$1:$1048576,MATCH(H$1,raw_data_airside!$1:$1,0),FALSE) | I9: =VLOOKUP($F9,raw_data_airside!$1:$1048576,MATCH(I$1,raw_data_airside!$1:$1,0),FALSE) | J9: =VLOOKUP($F9,raw_data_airside!$1:$1048576,MATCH(J$1,raw_data_airside!$1:$1,0),FALSE) | K9: =VLOOKUP($F9,raw_data_airside!$1:$1048576,MATCH(K$1,raw_data_airside!$1:$1,0),FALSE) | L9: =VLOOKUP($F9,raw_data_airside!$1:$1048576,MATCH(L$1,raw_data_airside!$1:$1,0),FALSE) | M9: =VLOOKUP($F9,raw_data_airside!$1:$1048576,MATCH(M$1,raw_data_airside!$1:$1,0),FALSE) | N9: =VLOOKUP($F9,raw_data_airside!$1:$1048576,MATCH(N$1,raw_data_airside!$1:$1,0),FALSE) | O9: =VLOOKUP($F9,raw_data_airside!$1:$1048576,MATCH(O$1,raw_data_airside!$1:$1,0),FALSE) | ... Q9: =VLOOKUP($F9,raw_data_airside!$1:$1048576,MATCH(Q$1,raw_data_airside!$1:$1,0),FALSE)
C10: Maximum Takeoff Weight Per Aircraft(lb) | D10: float0 | F10: 대당최대이륙중량 | H10: =VLOOKUP($F10,raw_data_airside!$1:$1048576,MATCH(H$1,raw_data_airside!$1:$1,0),FALSE) | I10: =VLOOKUP($F10,raw_data_airside!$1:$1048576,MATCH(I$1,raw_data_airside!$1:$1,0),FALSE) | J10: =VLOOKUP($F10,raw_data_airside!$1:$1048576,MATCH(J$1,raw_data_airside!$1:$1,0),FALSE) | K10: =VLOOKUP($F10,raw_data_airside!$1:$1048576,MATCH(K$1,raw_data_airside!$1:$1,0),FALSE) | L10: =VLOOKUP($F10,raw_data_airside!$1:$1048576,MATCH(L$1,raw_data_airside!$1:$1,0),FALSE) | M10: =VLOOKUP($F10,raw_data_airside!$1:$1048576,MATCH(M$1,raw_data_airside!$1:$1,0),FALSE) | N10: =VLOOKUP($F10,raw_data_airside!$1:$1048576,MATCH(N$1,raw_data_airside!$1:$1,0),FALSE) | O10: =VLOOKUP($F10,raw_data_airside!$1:$1048576,MATCH(O$1,raw_data_airside!$1:$1,0),FALSE) | ... Q10: =VLOOKUP($F10,raw_data_airside!$1:$1048576,MATCH(Q$1,raw_data_airside!$1:$1,0),FALSE)
C11: Average Flight Distance(km) | D11: float0 | F11: 비행거리평균(km) | H11: =VLOOKUP($F11,raw_data_airside!$1:$1048576,MATCH(H$1,raw_data_airside!$1:$1,0),FALSE) | I11: =VLOOKUP($F11,raw_data_airside!$1:$1048576,MATCH(I$1,raw_data_airside!$1:$1,0),FALSE) | J11: =VLOOKUP($F11,raw_data_airside!$1:$1048576,MATCH(J$1,raw_data_airside!$1:$1,0),FALSE) | K11: =VLOOKUP($F11,raw_data_airside!$1:$1048576,MATCH(K$1,raw_data_airside!$1:$1,0),FALSE) | L11: =VLOOKUP($F11,raw_data_airside!$1:$1048576,MATCH(L$1,raw_data_airside!$1:$1,0),FALSE) | M11: =VLOOKUP($F11,raw_data_airside!$1:$1048576,MATCH(M$1,raw_data_airside!$1:$1,0),FALSE) | N11: =VLOOKUP($F11,raw_data_airside!$1:$1048576,MATCH(N$1,raw_data_airside!$1:$1,0),FALSE) | O11: =VLOOKUP($F11,raw_data_airside!$1:$1048576,MATCH(O$1,raw_data_airside!$1:$1,0),FALSE) | ... Q11: =VLOOKUP($F11,raw_data_airside!$1:$1048576,MATCH(Q$1,raw_data_airside!$1:$1,0),FALSE)
C12: Payload Per Aircraft | D12: float0 | F12: 대당유상탑재중량 | H12: =VLOOKUP($F12,raw_data_airside!$1:$1048576,MATCH(H$1,raw_data_airside!$1:$1,0),FALSE) | I12: =VLOOKUP($F12,raw_data_airside!$1:$1048576,MATCH(I$1,raw_data_airside!$1:$1,0),FALSE) | J12: =VLOOKUP($F12,raw_data_airside!$1:$1048576,MATCH(J$1,raw_data_airside!$1:$1,0),FALSE) | K12: =VLOOKUP($F12,raw_data_airside!$1:$1048576,MATCH(K$1,raw_data_airside!$1:$1,0),FALSE) | L12: =VLOOKUP($F12,raw_data_airside!$1:$1048576,MATCH(L$1,raw_data_airside!$1:$1,0),FALSE) | M12: =VLOOKUP($F12,raw_data_airside!$1:$1048576,MATCH(M$1,raw_data_airside!$1:$1,0),FALSE) | N12: =VLOOKUP($F12,raw_data_airside!$1:$1048576,MATCH(N$1,raw_data_airside!$1:$1,0),FALSE) | O12: =VLOOKUP($F12,raw_data_airside!$1:$1048576,MATCH(O$1,raw_data_airside!$1:$1,0),FALSE) | ... Q12: =VLOOKUP($F12,raw_data_airside!$1:$1048576,MATCH(Q$1,raw_data_airside!$1:$1,0),FALSE)
A13: Flight Class Index | B13: FleetMIx | C13: =C61&"FleetMix📝" | D13: percent1 | E13: O | F13: =C61&"혼합율" | G13: =IFERROR(SUMIF($H$72:$Q$72,"O",H13:Q13)/COUNTIFS($H$72:$Q$72,"O",H13:Q13,"<>0"),0) | H13: =VLOOKUP($F13,raw_data_airside!$1:$1048576,MATCH(H$1,raw_data_airside!$1:$1,0),FALSE) | I13: =VLOOKUP($F13,raw_data_airside!$1:$1048576,MATCH(I$1,raw_data_airside!$1:$1,0),FALSE) | J13: =VLOOKUP($F13,raw_data_airside!$1:$1048576,MATCH(J$1,raw_data_airside!$1:$1,0),FALSE) | K13: =VLOOKUP($F13,raw_data_airside!$1:$1048576,MATCH(K$1,raw_data_airside!$1:$1,0),FALSE) | L13: =VLOOKUP($F13,raw_data_airside!$1:$1048576,MATCH(L$1,raw_data_airside!$1:$1,0),FALSE) | M13: =VLOOKUP($F13,raw_data_airside!$1:$1048576,MATCH(M$1,raw_data_airside!$1:$1,0),FALSE) | N13: =VLOOKUP($F13,raw_data_airside!$1:$1048576,MATCH(N$1,raw_data_airside!$1:$1,0),FALSE) | O13: =VLOOKUP($F13,raw_data_airside!$1:$1048576,MATCH(O$1,raw_data_airside!$1:$1,0),FALSE) | ... Q13: =VLOOKUP($F13,raw_data_airside!$1:$1048576,MATCH(Q$1,raw_data_airside!$1:$1,0),FALSE) | R13: =G13 | S13: =R13 | T13: =S13 | U13: =T13 | V13: =U13 | W13: =V13 | X13: =W13 | Y13: =X13 | Z13: =Y13 | ... BA13: =AZ13
C14: =C62&"FleetMix📝" | D14: percent1 | E14: O | F14: =C62&"혼합율" | G14: =IFERROR(SUMIF($H$72:$Q$72,"O",H14:Q14)/COUNTIFS($H$72:$Q$72,"O",H14:Q14,"<>0"),0) | H14: =VLOOKUP($F14,raw_data_airside!$1:$1048576,MATCH(H$1,raw_data_airside!$1:$1,0),FALSE) | I14: =VLOOKUP($F14,raw_data_airside!$1:$1048576,MATCH(I$1,raw_data_airside!$1:$1,0),FALSE) | J14: =VLOOKUP($F14,raw_data_airside!$1:$1048576,MATCH(J$1,raw_data_airside!$1:$1,0),FALSE) | K14: =VLOOKUP($F14,raw_data_airside!$1:$1048576,MATCH(K$1,raw_data_airside!$1:$1,0),FALSE) | L14: =VLOOKUP($F14,raw_data_airside!$1:$1048576,MATCH(L$1,raw_data_airside!$1:$1,0),FALSE) | M14: =VLOOKUP($F14,raw_data_airside!$1:$1048576,MATCH(M$1,raw_data_airside!$1:$1,0),FALSE) | N14: =VLOOKUP($F14,raw_data_airside!$1:$1048576,MATCH(N$1,raw_data_airside!$1:$1,0),FALSE) | O14: =VLOOKUP($F14,raw_data_airside!$1:$1048576,MATCH(O$1,raw_data_airside!$1:$1,0),FALSE) | ... Q14: =VLOOKUP($F14,raw_data_airside!$1:$1048576,MATCH(Q$1,raw_data_airside!$1:$1,0),FALSE) | R14: =G14 | S14: =R14 | T14: =S14 | U14: =T14 | V14: =U14 | W14: =V14 | X14: =W14 | Y14: =X14 | Z14: =Y14 | ... BA14: =AZ14
C15: =C63&"FleetMix📝" | D15: percent1 | E15: O | F15: =C63&"혼합율" | G15: =IFERROR(SUMIF($H$72:$Q$72,"O",H15:Q15)/COUNTIFS($H$72:$Q$72,"O",H15:Q15,"<>0"),0) | H15: =VLOOKUP($F15,raw_data_airside!$1:$1048576,MATCH(H$1,raw_data_airside!$1:$1,0),FALSE) | I15: =VLOOKUP($F15,raw_data_airside!$1:$1048576,MATCH(I$1,raw_data_airside!$1:$1,0),FALSE) | J15: =VLOOKUP($F15,raw_data_airside!$1:$1048576,MATCH(J$1,raw_data_airside!$1:$1,0),FALSE) | K15: =VLOOKUP($F15,raw_data_airside!$1:$1048576,MATCH(K$1,raw_data_airside!$1:$1,0),FALSE) | L15: =VLOOKUP($F15,raw_data_airside!$1:$1048576,MATCH(L$1,raw_data_airside!$1:$1,0),FALSE) | M15: =VLOOKUP($F15,raw_data_airside!$1:$1048576,MATCH(M$1,raw_data_airside!$1:$1,0),FALSE) | N15: =VLOOKUP($F15,raw_data_airside!$1:$1048576,MATCH(N$1,raw_data_airside!$1:$1,0),FALSE) | O15: =VLOOKUP($F15,raw_data_airside!$1:$1048576,MATCH(O$1,raw_data_airside!$1:$1,0),FALSE) | ... Q15: =VLOOKUP($F15,raw_data_airside!$1:$1048576,MATCH(Q$1,raw_data_airside!$1:$1,0),FALSE) | R15: =G15 | S15: =R15 | T15: =S15 | U15: =T15 | V15: =U15 | W15: =V15 | X15: =W15 | Y15: =X15 | Z15: =Y15 | ... BA15: =AZ15
C16: =C64&"FleetMix📝" | D16: percent1 | E16: O | F16: =C64&"혼합율" | G16: =IFERROR(SUMIF($H$72:$Q$72,"O",H16:Q16)/COUNTIFS($H$72:$Q$72,"O",H16:Q16,"<>0"),0) | H16: =VLOOKUP($F16,raw_data_airside!$1:$1048576,MATCH(H$1,raw_data_airside!$1:$1,0),FALSE) | I16: =VLOOKUP($F16,raw_data_airside!$1:$1048576,MATCH(I$1,raw_data_airside!$1:$1,0),FALSE) | J16: =VLOOKUP($F16,raw_data_airside!$1:$1048576,MATCH(J$1,raw_data_airside!$1:$1,0),FALSE) | K16: =VLOOKUP($F16,raw_data_airside!$1:$1048576,MATCH(K$1,raw_data_airside!$1:$1,0),FALSE) | L16: =VLOOKUP($F16,raw_data_airside!$1:$1048576,MATCH(L$1,raw_data_airside!$1:$1,0),FALSE) | M16: =VLOOKUP($F16,raw_data_airside!$1:$1048576,MATCH(M$1,raw_data_airside!$1:$1,0),FALSE) | N16: =VLOOKUP($F16,raw_data_airside!$1:$1048576,MATCH(N$1,raw_data_airside!$1:$1,0),FALSE) | O16: =VLOOKUP($F16,raw_data_airside!$1:$1048576,MATCH(O$1,raw_data_airside!$1:$1,0),FALSE) | ... Q16: =VLOOKUP($F16,raw_data_airside!$1:$1048576,MATCH(Q$1,raw_data_airside!$1:$1,0),FALSE) | R16: =G16 | S16: =R16 | T16: =S16 | U16: =T16 | V16: =U16 | W16: =V16 | X16: =W16 | Y16: =X16 | Z16: =Y16 | ... BA16: =AZ16
B17: Movements by Class | C17: =C61&"Movements" | D17: float0 | F17: =C61&"운항횟수" | H17: =VLOOKUP($F17,raw_data_airside!$1:$1048576,MATCH(H$1,raw_data_airside!$1:$1,0),FALSE) | I17: =VLOOKUP($F17,raw_data_airside!$1:$1048576,MATCH(I$1,raw_data_airside!$1:$1,0),FALSE) | J17: =VLOOKUP($F17,raw_data_airside!$1:$1048576,MATCH(J$1,raw_data_airside!$1:$1,0),FALSE) | K17: =VLOOKUP($F17,raw_data_airside!$1:$1048576,MATCH(K$1,raw_data_airside!$1:$1,0),FALSE) | L17: =VLOOKUP($F17,raw_data_airside!$1:$1048576,MATCH(L$1,raw_data_airside!$1:$1,0),FALSE) | M17: =VLOOKUP($F17,raw_data_airside!$1:$1048576,MATCH(M$1,raw_data_airside!$1:$1,0),FALSE) | N17: =VLOOKUP($F17,raw_data_airside!$1:$1048576,MATCH(N$1,raw_data_airside!$1:$1,0),FALSE) | O17: =VLOOKUP($F17,raw_data_airside!$1:$1048576,MATCH(O$1,raw_data_airside!$1:$1,0),FALSE) | ... Q17: =VLOOKUP($F17,raw_data_airside!$1:$1048576,MATCH(Q$1,raw_data_airside!$1:$1,0),FALSE) | R17: =R2*R13 | S17: =S2*S13 | T17: =T2*T13 | U17: =U2*U13 | V17: =V2*V13 | W17: =W2*W13 | X17: =X2*X13 | Y17: =Y2*Y13 | ... BA17: =BA2*BA13
C18: =C62&"Movements" | D18: float0 | F18: =C62&"운항횟수" | H18: =VLOOKUP($F18,raw_data_airside!$1:$1048576,MATCH(H$1,raw_data_airside!$1:$1,0),FALSE) | I18: =VLOOKUP($F18,raw_data_airside!$1:$1048576,MATCH(I$1,raw_data_airside!$1:$1,0),FALSE) | J18: =VLOOKUP($F18,raw_data_airside!$1:$1048576,MATCH(J$1,raw_data_airside!$1:$1,0),FALSE) | K18: =VLOOKUP($F18,raw_data_airside!$1:$1048576,MATCH(K$1,raw_data_airside!$1:$1,0),FALSE) | L18: =VLOOKUP($F18,raw_data_airside!$1:$1048576,MATCH(L$1,raw_data_airside!$1:$1,0),FALSE) | M18: =VLOOKUP($F18,raw_data_airside!$1:$1048576,MATCH(M$1,raw_data_airside!$1:$1,0),FALSE) | N18: =VLOOKUP($F18,raw_data_airside!$1:$1048576,MATCH(N$1,raw_data_airside!$1:$1,0),FALSE) | O18: =VLOOKUP($F18,raw_data_airside!$1:$1048576,MATCH(O$1,raw_data_airside!$1:$1,0),FALSE) | ... Q18: =VLOOKUP($F18,raw_data_airside!$1:$1048576,MATCH(Q$1,raw_data_airside!$1:$1,0),FALSE) | R18: =R2*R14 | S18: =S2*S14 | T18: =T2*T14 | U18: =U2*U14 | V18: =V2*V14 | W18: =W2*W14 | X18: =X2*X14 | Y18: =Y2*Y14 | ... BA18: =BA2*BA14
C19: =C63&"Movements" | D19: float0 | F19: =C63&"운항횟수" | H19: =VLOOKUP($F19,raw_data_airside!$1:$1048576,MATCH(H$1,raw_data_airside!$1:$1,0),FALSE) | I19: =VLOOKUP($F19,raw_data_airside!$1:$1048576,MATCH(I$1,raw_data_airside!$1:$1,0),FALSE) | J19: =VLOOKUP($F19,raw_data_airside!$1:$1048576,MATCH(J$1,raw_data_airside!$1:$1,0),FALSE) | K19: =VLOOKUP($F19,raw_data_airside!$1:$1048576,MATCH(K$1,raw_data_airside!$1:$1,0),FALSE) | L19: =VLOOKUP($F19,raw_data_airside!$1:$1048576,MATCH(L$1,raw_data_airside!$1:$1,0),FALSE) | M19: =VLOOKUP($F19,raw_data_airside!$1:$1048576,MATCH(M$1,raw_data_airside!$1:$1,0),FALSE) | N19: =VLOOKUP($F19,raw_data_airside!$1:$1048576,MATCH(N$1,raw_data_airside!$1:$1,0),FALSE) | O19: =VLOOKUP($F19,raw_data_airside!$1:$1048576,MATCH(O$1,raw_data_airside!$1:$1,0),FALSE) | ... Q19: =VLOOKUP($F19,raw_data_airside!$1:$1048576,MATCH(Q$1,raw_data_airside!$1:$1,0),FALSE) | R19: =R2*R15 | S19: =S2*S15 | T19: =T2*T15 | U19: =U2*U15 | V19: =V2*V15 | W19: =W2*W15 | X19: =X2*X15 | Y19: =Y2*Y15 | ... BA19: =BA2*BA15
C20: =C64&"Movements" | D20: float0 | F20: =C64&"운항횟수" | H20: =VLOOKUP($F20,raw_data_airside!$1:$1048576,MATCH(H$1,raw_data_airside!$1:$1,0),FALSE) | I20: =VLOOKUP($F20,raw_data_airside!$1:$1048576,MATCH(I$1,raw_data_airside!$1:$1,0),FALSE) | J20: =VLOOKUP($F20,raw_data_airside!$1:$1048576,MATCH(J$1,raw_data_airside!$1:$1,0),FALSE) | K20: =VLOOKUP($F20,raw_data_airside!$1:$1048576,MATCH(K$1,raw_data_airside!$1:$1,0),FALSE) | L20: =VLOOKUP($F20,raw_data_airside!$1:$1048576,MATCH(L$1,raw_data_airside!$1:$1,0),FALSE) | M20: =VLOOKUP($F20,raw_data_airside!$1:$1048576,MATCH(M$1,raw_data_airside!$1:$1,0),FALSE) | N20: =VLOOKUP($F20,raw_data_airside!$1:$1048576,MATCH(N$1,raw_data_airside!$1:$1,0),FALSE) | O20: =VLOOKUP($F20,raw_data_airside!$1:$1048576,MATCH(O$1,raw_data_airside!$1:$1,0),FALSE) | ... Q20: =VLOOKUP($F20,raw_data_airside!$1:$1048576,MATCH(Q$1,raw_data_airside!$1:$1,0),FALSE) | R20: =R2*R16 | S20: =S2*S16 | T20: =T2*T16 | U20: =U2*U16 | V20: =V2*V16 | W20: =W2*W16 | X20: =X2*X16 | Y20: =Y2*Y16 | ... BA20: =BA2*BA16
B21: MTOW by Class | C21: =C61&"MTOW" | D21: float0 | F21: =C61&"대당최대이륙중량" | G21: =IFERROR(SUMIF($H$82:$Q$82,"O",H21:Q21)/COUNTIFS($H$82:$Q$82,"O",H21:Q21,"<>0"),0) | H21: =VLOOKUP($F21,raw_data_airside!$1:$1048576,MATCH(H$1,raw_data_airside!$1:$1,0),FALSE) | I21: =VLOOKUP($F21,raw_data_airside!$1:$1048576,MATCH(I$1,raw_data_airside!$1:$1,0),FALSE) | J21: =VLOOKUP($F21,raw_data_airside!$1:$1048576,MATCH(J$1,raw_data_airside!$1:$1,0),FALSE) | K21: =VLOOKUP($F21,raw_data_airside!$1:$1048576,MATCH(K$1,raw_data_airside!$1:$1,0),FALSE) | L21: =VLOOKUP($F21,raw_data_airside!$1:$1048576,MATCH(L$1,raw_data_airside!$1:$1,0),FALSE) | M21: =VLOOKUP($F21,raw_data_airside!$1:$1048576,MATCH(M$1,raw_data_airside!$1:$1,0),FALSE) | N21: =VLOOKUP($F21,raw_data_airside!$1:$1048576,MATCH(N$1,raw_data_airside!$1:$1,0),FALSE) | O21: =VLOOKUP($F21,raw_data_airside!$1:$1048576,MATCH(O$1,raw_data_airside!$1:$1,0),FALSE) | ... Q21: =VLOOKUP($F21,raw_data_airside!$1:$1048576,MATCH(Q$1,raw_data_airside!$1:$1,0),FALSE) | R21: =G21 | S21: =R21 | T21: =S21 | U21: =T21 | V21: =U21 | W21: =V21 | X21: =W21 | Y21: =X21 | Z21: =Y21 | ... BA21: =AZ21
C22: =C62&"MTOW" | D22: float0 | F22: =C62&"대당최대이륙중량" | G22: =IFERROR(SUMIF($H$82:$Q$82,"O",H22:Q22)/COUNTIFS($H$82:$Q$82,"O",H22:Q22,"<>0"),0) | H22: =VLOOKUP($F22,raw_data_airside!$1:$1048576,MATCH(H$1,raw_data_airside!$1:$1,0),FALSE) | I22: =VLOOKUP($F22,raw_data_airside!$1:$1048576,MATCH(I$1,raw_data_airside!$1:$1,0),FALSE) | J22: =VLOOKUP($F22,raw_data_airside!$1:$1048576,MATCH(J$1,raw_data_airside!$1:$1,0),FALSE) | K22: =VLOOKUP($F22,raw_data_airside!$1:$1048576,MATCH(K$1,raw_data_airside!$1:$1,0),FALSE) | L22: =VLOOKUP($F22,raw_data_airside!$1:$1048576,MATCH(L$1,raw_data_airside!$1:$1,0),FALSE) | M22: =VLOOKUP($F22,raw_data_airside!$1:$1048576,MATCH(M$1,raw_data_airside!$1:$1,0),FALSE) | N22: =VLOOKUP($F22,raw_data_airside!$1:$1048576,MATCH(N$1,raw_data_airside!$1:$1,0),FALSE) | O22: =VLOOKUP($F22,raw_data_airside!$1:$1048576,MATCH(O$1,raw_data_airside!$1:$1,0),FALSE) | ... Q22: =VLOOKUP($F22,raw_data_airside!$1:$1048576,MATCH(Q$1,raw_data_airside!$1:$1,0),FALSE) | R22: =G22 | S22: =R22 | T22: =S22 | U22: =T22 | V22: =U22 | W22: =V22 | X22: =W22 | Y22: =X22 | Z22: =Y22 | ... BA22: =AZ22
C23: =C63&"MTOW" | D23: float0 | F23: =C63&"대당최대이륙중량" | G23: =IFERROR(SUMIF($H$82:$Q$82,"O",H23:Q23)/COUNTIFS($H$82:$Q$82,"O",H23:Q23,"<>0"),0) | H23: =VLOOKUP($F23,raw_data_airside!$1:$1048576,MATCH(H$1,raw_data_airside!$1:$1,0),FALSE) | I23: =VLOOKUP($F23,raw_data_airside!$1:$1048576,MATCH(I$1,raw_data_airside!$1:$1,0),FALSE) | J23: =VLOOKUP($F23,raw_data_airside!$1:$1048576,MATCH(J$1,raw_data_airside!$1:$1,0),FALSE) | K23: =VLOOKUP($F23,raw_data_airside!$1:$1048576,MATCH(K$1,raw_data_airside!$1:$1,0),FALSE) | L23: =VLOOKUP($F23,raw_data_airside!$1:$1048576,MATCH(L$1,raw_data_airside!$1:$1,0),FALSE) | M23: =VLOOKUP($F23,raw_data_airside!$1:$1048576,MATCH(M$1,raw_data_airside!$1:$1,0),FALSE) | N23: =VLOOKUP($F23,raw_data_airside!$1:$1048576,MATCH(N$1,raw_data_airside!$1:$1,0),FALSE) | O23: =VLOOKUP($F23,raw_data_airside!$1:$1048576,MATCH(O$1,raw_data_airside!$1:$1,0),FALSE) | ... Q23: =VLOOKUP($F23,raw_data_airside!$1:$1048576,MATCH(Q$1,raw_data_airside!$1:$1,0),FALSE) | R23: =G23 | S23: =R23 | T23: =S23 | U23: =T23 | V23: =U23 | W23: =V23 | X23: =W23 | Y23: =X23 | Z23: =Y23 | ... BA23: =AZ23
C24: =C64&"MTOW" | D24: float0 | F24: =C64&"대당최대이륙중량" | G24: =IFERROR(SUMIF($H$82:$Q$82,"O",H24:Q24)/COUNTIFS($H$82:$Q$82,"O",H24:Q24,"<>0"),0) | H24: =VLOOKUP($F24,raw_data_airside!$1:$1048576,MATCH(H$1,raw_data_airside!$1:$1,0),FALSE) | I24: =VLOOKUP($F24,raw_data_airside!$1:$1048576,MATCH(I$1,raw_data_airside!$1:$1,0),FALSE) | J24: =VLOOKUP($F24,raw_data_airside!$1:$1048576,MATCH(J$1,raw_data_airside!$1:$1,0),FALSE) | K24: =VLOOKUP($F24,raw_data_airside!$1:$1048576,MATCH(K$1,raw_data_airside!$1:$1,0),FALSE) | L24: =VLOOKUP($F24,raw_data_airside!$1:$1048576,MATCH(L$1,raw_data_airside!$1:$1,0),FALSE) | M24: =VLOOKUP($F24,raw_data_airside!$1:$1048576,MATCH(M$1,raw_data_airside!$1:$1,0),FALSE) | N24: =VLOOKUP($F24,raw_data_airside!$1:$1048576,MATCH(N$1,raw_data_airside!$1:$1,0),FALSE) | O24: =VLOOKUP($F24,raw_data_airside!$1:$1048576,MATCH(O$1,raw_data_airside!$1:$1,0),FALSE) | ... Q24: =VLOOKUP($F24,raw_data_airside!$1:$1048576,MATCH(Q$1,raw_data_airside!$1:$1,0),FALSE) | R24: =G24 | S24: =R24 | T24: =S24 | U24: =T24 | V24: =U24 | W24: =V24 | X24: =W24 | Y24: =X24 | Z24: =Y24 | ... BA24: =AZ24
B25: Standing Time by Class | C25: =C61&"Average PeakTime TurnAround Standing Time📝" | D25: float0 | E25: O | F25: =C61&"피크시간 턴어라운드편 평균주기시간(분)" | G25: =IFERROR(SUMIF($H$83:$Q$83,"O",H25:Q25)/COUNTIFS($H$83:$Q$83,"O",H25:Q25,"<>0"),0) | H25: =VLOOKUP($F25,raw_data_airside!$1:$1048576,MATCH(H$1,raw_data_airside!$1:$1,0),FALSE) | I25: =VLOOKUP($F25,raw_data_airside!$1:$1048576,MATCH(I$1,raw_data_airside!$1:$1,0),FALSE) | J25: =VLOOKUP($F25,raw_data_airside!$1:$1048576,MATCH(J$1,raw_data_airside!$1:$1,0),FALSE) | K25: =VLOOKUP($F25,raw_data_airside!$1:$1048576,MATCH(K$1,raw_data_airside!$1:$1,0),FALSE) | L25: =VLOOKUP($F25,raw_data_airside!$1:$1048576,MATCH(L$1,raw_data_airside!$1:$1,0),FALSE) | M25: =VLOOKUP($F25,raw_data_airside!$1:$1048576,MATCH(M$1,raw_data_airside!$1:$1,0),FALSE) | N25: =VLOOKUP($F25,raw_data_airside!$1:$1048576,MATCH(N$1,raw_data_airside!$1:$1,0),FALSE) | O25: =VLOOKUP($F25,raw_data_airside!$1:$1048576,MATCH(O$1,raw_data_airside!$1:$1,0),FALSE) | ... Q25: =VLOOKUP($F25,raw_data_airside!$1:$1048576,MATCH(Q$1,raw_data_airside!$1:$1,0),FALSE) | R25: =G25 | S25: =R25 | T25: =S25 | U25: =T25 | V25: =U25 | W25: =V25 | X25: =W25 | Y25: =X25 | Z25: =Y25 | ... BA25: =AZ25
C26: =C62&"Average PeakTime TurnAround Standing Time📝" | D26: float0 | E26: O | F26: =C62&"피크시간 턴어라운드편 평균주기시간(분)" | G26: =IFERROR(SUMIF($H$83:$Q$83,"O",H26:Q26)/COUNTIFS($H$83:$Q$83,"O",H26:Q26,"<>0"),0) | H26: =VLOOKUP($F26,raw_data_airside!$1:$1048576,MATCH(H$1,raw_data_airside!$1:$1,0),FALSE) | I26: =VLOOKUP($F26,raw_data_airside!$1:$1048576,MATCH(I$1,raw_data_airside!$1:$1,0),FALSE) | J26: =VLOOKUP($F26,raw_data_airside!$1:$1048576,MATCH(J$1,raw_data_airside!$1:$1,0),FALSE) | K26: =VLOOKUP($F26,raw_data_airside!$1:$1048576,MATCH(K$1,raw_data_airside!$1:$1,0),FALSE) | L26: =VLOOKUP($F26,raw_data_airside!$1:$1048576,MATCH(L$1,raw_data_airside!$1:$1,0),FALSE) | M26: =VLOOKUP($F26,raw_data_airside!$1:$1048576,MATCH(M$1,raw_data_airside!$1:$1,0),FALSE) | N26: =VLOOKUP($F26,raw_data_airside!$1:$1048576,MATCH(N$1,raw_data_airside!$1:$1,0),FALSE) | O26: =VLOOKUP($F26,raw_data_airside!$1:$1048576,MATCH(O$1,raw_data_airside!$1:$1,0),FALSE) | ... Q26: =VLOOKUP($F26,raw_data_airside!$1:$1048576,MATCH(Q$1,raw_data_airside!$1:$1,0),FALSE) | R26: =G26 | S26: =R26 | T26: =S26 | U26: =T26 | V26: =U26 | W26: =V26 | X26: =W26 | Y26: =X26 | Z26: =Y26 | ... BA26: =AZ26
C27: =C63&"Average PeakTime TurnAround Standing Time📝" | D27: float0 | E27: O | F27: =C63&"피크시간 턴어라운드편 평균주기시간(분)" | G27: =IFERROR(SUMIF($H$83:$Q$83,"O",H27:Q27)/COUNTIFS($H$83:$Q$83,"O",H27:Q27,"<>0"),0) | H27: =VLOOKUP($F27,raw_data_airside!$1:$1048576,MATCH(H$1,raw_data_airside!$1:$1,0),FALSE) | I27: =VLOOKUP($F27,raw_data_airside!$1:$1048576,MATCH(I$1,raw_data_airside!$1:$1,0),FALSE) | J27: =VLOOKUP($F27,raw_data_airside!$1:$1048576,MATCH(J$1,raw_data_airside!$1:$1,0),FALSE) | K27: =VLOOKUP($F27,raw_data_airside!$1:$1048576,MATCH(K$1,raw_data_airside!$1:$1,0),FALSE) | L27: =VLOOKUP($F27,raw_data_airside!$1:$1048576,MATCH(L$1,raw_data_airside!$1:$1,0),FALSE) | M27: =VLOOKUP($F27,raw_data_airside!$1:$1048576,MATCH(M$1,raw_data_airside!$1:$1,0),FALSE) | N27: =VLOOKUP($F27,raw_data_airside!$1:$1048576,MATCH(N$1,raw_data_airside!$1:$1,0),FALSE) | O27: =VLOOKUP($F27,raw_data_airside!$1:$1048576,MATCH(O$1,raw_data_airside!$1:$1,0),FALSE) | ... Q27: =VLOOKUP($F27,raw_data_airside!$1:$1048576,MATCH(Q$1,raw_data_airside!$1:$1,0),FALSE) | R27: =G27 | S27: =R27 | T27: =S27 | U27: =T27 | V27: =U27 | W27: =V27 | X27: =W27 | Y27: =X27 | Z27: =Y27 | ... BA27: =AZ27
C28: =C64&"Average PeakTime TurnAround Standing Time📝" | D28: float0 | E28: O | F28: =C64&"피크시간 턴어라운드편 평균주기시간(분)" | G28: =IFERROR(SUMIF($H$83:$Q$83,"O",H28:Q28)/COUNTIFS($H$83:$Q$83,"O",H28:Q28,"<>0"),0) | H28: =VLOOKUP($F28,raw_data_airside!$1:$1048576,MATCH(H$1,raw_data_airside!$1:$1,0),FALSE) | I28: =VLOOKUP($F28,raw_data_airside!$1:$1048576,MATCH(I$1,raw_data_airside!$1:$1,0),FALSE) | J28: =VLOOKUP($F28,raw_data_airside!$1:$1048576,MATCH(J$1,raw_data_airside!$1:$1,0),FALSE) | K28: =VLOOKUP($F28,raw_data_airside!$1:$1048576,MATCH(K$1,raw_data_airside!$1:$1,0),FALSE) | L28: =VLOOKUP($F28,raw_data_airside!$1:$1048576,MATCH(L$1,raw_data_airside!$1:$1,0),FALSE) | M28: =VLOOKUP($F28,raw_data_airside!$1:$1048576,MATCH(M$1,raw_data_airside!$1:$1,0),FALSE) | N28: =VLOOKUP($F28,raw_data_airside!$1:$1048576,MATCH(N$1,raw_data_airside!$1:$1,0),FALSE) | O28: =VLOOKUP($F28,raw_data_airside!$1:$1048576,MATCH(O$1,raw_data_airside!$1:$1,0),FALSE) | ... Q28: =VLOOKUP($F28,raw_data_airside!$1:$1048576,MATCH(Q$1,raw_data_airside!$1:$1,0),FALSE) | R28: =G28 | S28: =R28 | T28: =S28 | U28: =T28 | V28: =U28 | W28: =V28 | X28: =W28 | Y28: =X28 | Z28: =Y28 | ... BA28: =AZ28
B29: Standing(Total) Time by Class | C29: =C61&"Average Peak Standing Time📝" | D29: float0 | E29: O | F29: =C61&"(오버나잇, 소산 포함) 피크시간 평균주기시간(분)" | G29: =IFERROR(SUMIF($H$83:$Q$83,"O",H29:Q29)/COUNTIFS($H$83:$Q$83,"O",H29:Q29,"<>0"),0) | H29: =VLOOKUP($F29,raw_data_airside!$1:$1048576,MATCH(H$1,raw_data_airside!$1:$1,0),FALSE) | I29: =VLOOKUP($F29,raw_data_airside!$1:$1048576,MATCH(I$1,raw_data_airside!$1:$1,0),FALSE) | J29: =VLOOKUP($F29,raw_data_airside!$1:$1048576,MATCH(J$1,raw_data_airside!$1:$1,0),FALSE) | K29: =VLOOKUP($F29,raw_data_airside!$1:$1048576,MATCH(K$1,raw_data_airside!$1:$1,0),FALSE) | L29: =VLOOKUP($F29,raw_data_airside!$1:$1048576,MATCH(L$1,raw_data_airside!$1:$1,0),FALSE) | M29: =VLOOKUP($F29,raw_data_airside!$1:$1048576,MATCH(M$1,raw_data_airside!$1:$1,0),FALSE) | N29: =VLOOKUP($F29,raw_data_airside!$1:$1048576,MATCH(N$1,raw_data_airside!$1:$1,0),FALSE) | O29: =VLOOKUP($F29,raw_data_airside!$1:$1048576,MATCH(O$1,raw_data_airside!$1:$1,0),FALSE) | ... Q29: =VLOOKUP($F29,raw_data_airside!$1:$1048576,MATCH(Q$1,raw_data_airside!$1:$1,0),FALSE) | R29: =G29 | S29: =R29 | T29: =S29 | U29: =T29 | V29: =U29 | W29: =V29 | X29: =W29 | Y29: =X29 | Z29: =Y29 | ... BA29: =AZ29
C30: =C62&"Average Peak Standing Time📝" | D30: float0 | E30: O | F30: =C62&"(오버나잇, 소산 포함) 피크시간 평균주기시간(분)" | G30: =IFERROR(SUMIF($H$83:$Q$83,"O",H30:Q30)/COUNTIFS($H$83:$Q$83,"O",H30:Q30,"<>0"),0) | H30: =VLOOKUP($F30,raw_data_airside!$1:$1048576,MATCH(H$1,raw_data_airside!$1:$1,0),FALSE) | I30: =VLOOKUP($F30,raw_data_airside!$1:$1048576,MATCH(I$1,raw_data_airside!$1:$1,0),FALSE) | J30: =VLOOKUP($F30,raw_data_airside!$1:$1048576,MATCH(J$1,raw_data_airside!$1:$1,0),FALSE) | K30: =VLOOKUP($F30,raw_data_airside!$1:$1048576,MATCH(K$1,raw_data_airside!$1:$1,0),FALSE) | L30: =VLOOKUP($F30,raw_data_airside!$1:$1048576,MATCH(L$1,raw_data_airside!$1:$1,0),FALSE) | M30: =VLOOKUP($F30,raw_data_airside!$1:$1048576,MATCH(M$1,raw_data_airside!$1:$1,0),FALSE) | N30: =VLOOKUP($F30,raw_data_airside!$1:$1048576,MATCH(N$1,raw_data_airside!$1:$1,0),FALSE) | O30: =VLOOKUP($F30,raw_data_airside!$1:$1048576,MATCH(O$1,raw_data_airside!$1:$1,0),FALSE) | ... Q30: =VLOOKUP($F30,raw_data_airside!$1:$1048576,MATCH(Q$1,raw_data_airside!$1:$1,0),FALSE) | R30: =G30 | S30: =R30 | T30: =S30 | U30: =T30 | V30: =U30 | W30: =V30 | X30: =W30 | Y30: =X30 | Z30: =Y30 | ... BA30: =AZ30
C31: =C63&"Average Peak Standing Time📝" | D31: float0 | E31: O | F31: =C63&"(오버나잇, 소산 포함) 피크시간 평균주기시간(분)" | G31: =IFERROR(SUMIF($H$83:$Q$83,"O",H31:Q31)/COUNTIFS($H$83:$Q$83,"O",H31:Q31,"<>0"),0) | H31: =VLOOKUP($F31,raw_data_airside!$1:$1048576,MATCH(H$1,raw_data_airside!$1:$1,0),FALSE) | I31: =VLOOKUP($F31,raw_data_airside!$1:$1048576,MATCH(I$1,raw_data_airside!$1:$1,0),FALSE) | J31: =VLOOKUP($F31,raw_data_airside!$1:$1048576,MATCH(J$1,raw_data_airside!$1:$1,0),FALSE) | K31: =VLOOKUP($F31,raw_data_airside!$1:$1048576,MATCH(K$1,raw_data_airside!$1:$1,0),FALSE) | L31: =VLOOKUP($F31,raw_data_airside!$1:$1048576,MATCH(L$1,raw_data_airside!$1:$1,0),FALSE) | M31: =VLOOKUP($F31,raw_data_airside!$1:$1048576,MATCH(M$1,raw_data_airside!$1:$1,0),FALSE) | N31: =VLOOKUP($F31,raw_data_airside!$1:$1048576,MATCH(N$1,raw_data_airside!$1:$1,0),FALSE) | O31: =VLOOKUP($F31,raw_data_airside!$1:$1048576,MATCH(O$1,raw_data_airside!$1:$1,0),FALSE) | ... Q31: =VLOOKUP($F31,raw_data_airside!$1:$1048576,MATCH(Q$1,raw_data_airside!$1:$1,0),FALSE) | R31: =G31 | S31: =R31 | T31: =S31 | U31: =T31 | V31: =U31 | W31: =V31 | X31: =W31 | Y31: =X31 | Z31: =Y31 | ... BA31: =AZ31
C32: =C64&"Average Peak Standing Time📝" | D32: float0 | E32: O | F32: =C64&"(오버나잇, 소산 포함) 피크시간 평균주기시간(분)" | G32: =IFERROR(SUMIF($H$83:$Q$83,"O",H32:Q32)/COUNTIFS($H$83:$Q$83,"O",H32:Q32,"<>0"),0) | H32: =VLOOKUP($F32,raw_data_airside!$1:$1048576,MATCH(H$1,raw_data_airside!$1:$1,0),FALSE) | I32: =VLOOKUP($F32,raw_data_airside!$1:$1048576,MATCH(I$1,raw_data_airside!$1:$1,0),FALSE) | J32: =VLOOKUP($F32,raw_data_airside!$1:$1048576,MATCH(J$1,raw_data_airside!$1:$1,0),FALSE) | K32: =VLOOKUP($F32,raw_data_airside!$1:$1048576,MATCH(K$1,raw_data_airside!$1:$1,0),FALSE) | L32: =VLOOKUP($F32,raw_data_airside!$1:$1048576,MATCH(L$1,raw_data_airside!$1:$1,0),FALSE) | M32: =VLOOKUP($F32,raw_data_airside!$1:$1048576,MATCH(M$1,raw_data_airside!$1:$1,0),FALSE) | N32: =VLOOKUP($F32,raw_data_airside!$1:$1048576,MATCH(N$1,raw_data_airside!$1:$1,0),FALSE) | O32: =VLOOKUP($F32,raw_data_airside!$1:$1048576,MATCH(O$1,raw_data_airside!$1:$1,0),FALSE) | ... Q32: =VLOOKUP($F32,raw_data_airside!$1:$1048576,MATCH(Q$1,raw_data_airside!$1:$1,0),FALSE) | R32: =G32 | S32: =R32 | T32: =S32 | U32: =T32 | V32: =U32 | W32: =V32 | X32: =W32 | Y32: =X32 | Z32: =Y32 | ... BA32: =AZ32
A36: top | B36: mid | C36: low | D36: decimal | E36: changeable | F36: 변수설명 | G36: Ref_Index | H36: =I36-1 | I36: =J36-1 | J36: =K36-1 | K36: =L36-1 | L36: =M36-1 | M36: =N36-1 | N36: =O36-1 | O36: =P36-1 | P36: =Q36-1 | Q36: =ref!B4 | R36: =Q36+1 | S36: =R36+1 | T36: =S36+1 | U36: =T36+1 | V36: =U36+1 | W36: =V36+1 | X36: =W36+1 | Y36: =X36+1 | ... BA36: =AZ36+1
A37: Airside(ADPM) | B37: Airside Flight Movements(ADPM) | C37: Movement PHF(%)(ADPM) | D37: percent4 | F37: ADPM/movement/all/PHF | H37: =VLOOKUP($F37,raw_data_airside!$1:$1048576,MATCH(H$1,raw_data_airside!$1:$1,0),FALSE) | I37: =VLOOKUP($F37,raw_data_airside!$1:$1048576,MATCH(I$1,raw_data_airside!$1:$1,0),FALSE) | J37: =VLOOKUP($F37,raw_data_airside!$1:$1048576,MATCH(J$1,raw_data_airside!$1:$1,0),FALSE) | K37: =VLOOKUP($F37,raw_data_airside!$1:$1048576,MATCH(K$1,raw_data_airside!$1:$1,0),FALSE) | L37: =VLOOKUP($F37,raw_data_airside!$1:$1048576,MATCH(L$1,raw_data_airside!$1:$1,0),FALSE) | M37: =VLOOKUP($F37,raw_data_airside!$1:$1048576,MATCH(M$1,raw_data_airside!$1:$1,0),FALSE) | N37: =VLOOKUP($F37,raw_data_airside!$1:$1048576,MATCH(N$1,raw_data_airside!$1:$1,0),FALSE) | O37: =VLOOKUP($F37,raw_data_airside!$1:$1048576,MATCH(O$1,raw_data_airside!$1:$1,0),FALSE) | ... Q37: =VLOOKUP($F37,raw_data_airside!$1:$1048576,MATCH(Q$1,raw_data_airside!$1:$1,0),FALSE) | R37: =0.0021*R2^(-0.183)*$G$41 | S37: =0.0021*S2^(-0.183)*$G$41 | T37: =0.0021*T2^(-0.183)*$G$41 | U37: =0.0021*U2^(-0.183)*$G$41 | V37: =0.0021*V2^(-0.183)*$G$41 | W37: =0.0021*W2^(-0.183)*$G$41 | X37: =0.0021*X2^(-0.183)*$G$41 | Y37: =0.0021*Y2^(-0.183)*$G$41 | ... BA37: =0.0021*BA2^(-0.183)*$G$41
C38: - Movement H Factor(ADPM) | D38: float1 | F38: ADPM/movement/all/H팩터 | H38: =VLOOKUP($F38,raw_data_airside!$1:$1048576,MATCH(H$1,raw_data_airside!$1:$1,0),FALSE) | I38: =VLOOKUP($F38,raw_data_airside!$1:$1048576,MATCH(I$1,raw_data_airside!$1:$1,0),FALSE) | J38: =VLOOKUP($F38,raw_data_airside!$1:$1048576,MATCH(J$1,raw_data_airside!$1:$1,0),FALSE) | K38: =VLOOKUP($F38,raw_data_airside!$1:$1048576,MATCH(K$1,raw_data_airside!$1:$1,0),FALSE) | L38: =VLOOKUP($F38,raw_data_airside!$1:$1048576,MATCH(L$1,raw_data_airside!$1:$1,0),FALSE) | M38: =VLOOKUP($F38,raw_data_airside!$1:$1048576,MATCH(M$1,raw_data_airside!$1:$1,0),FALSE) | N38: =VLOOKUP($F38,raw_data_airside!$1:$1048576,MATCH(N$1,raw_data_airside!$1:$1,0),FALSE) | O38: =VLOOKUP($F38,raw_data_airside!$1:$1048576,MATCH(O$1,raw_data_airside!$1:$1,0),FALSE) | ... Q38: =VLOOKUP($F38,raw_data_airside!$1:$1048576,MATCH(Q$1,raw_data_airside!$1:$1,0),FALSE) | R38: =1/R37/R39 | S38: =1/S37/S39 | T38: =1/T37/T39 | U38: =1/U37/U39 | V38: =1/V37/V39 | W38: =1/W37/W39 | X38: =1/X37/X39 | Y38: =1/Y37/Y39 | ... BA38: =1/BA37/BA39
C39: - Movement D Factor(ADPM) | D39: float1 | F39: ADPM/movement/all/D팩터 | G39: =SUMIF($H$78:$Q$78,"O",H39:Q39)/COUNTIFS($H$78:$Q$78,"O",H39:Q39,"<>0") | H39: =VLOOKUP($F39,raw_data_airside!$1:$1048576,MATCH(H$1,raw_data_airside!$1:$1,0),FALSE) | I39: =VLOOKUP($F39,raw_data_airside!$1:$1048576,MATCH(I$1,raw_data_airside!$1:$1,0),FALSE) | J39: =VLOOKUP($F39,raw_data_airside!$1:$1048576,MATCH(J$1,raw_data_airside!$1:$1,0),FALSE) | K39: =VLOOKUP($F39,raw_data_airside!$1:$1048576,MATCH(K$1,raw_data_airside!$1:$1,0),FALSE) | L39: =VLOOKUP($F39,raw_data_airside!$1:$1048576,MATCH(L$1,raw_data_airside!$1:$1,0),FALSE) | M39: =VLOOKUP($F39,raw_data_airside!$1:$1048576,MATCH(M$1,raw_data_airside!$1:$1,0),FALSE) | N39: =VLOOKUP($F39,raw_data_airside!$1:$1048576,MATCH(N$1,raw_data_airside!$1:$1,0),FALSE) | O39: =VLOOKUP($F39,raw_data_airside!$1:$1048576,MATCH(O$1,raw_data_airside!$1:$1,0),FALSE) | ... Q39: =VLOOKUP($F39,raw_data_airside!$1:$1048576,MATCH(Q$1,raw_data_airside!$1:$1,0),FALSE) | R39: =$G$39 | S39: =$G$39 | T39: =$G$39 | U39: =$G$39 | V39: =$G$39 | W39: =$G$39 | X39: =$G$39 | Y39: =$G$39 | ... BA39: =$G$39
C40: Movement PHF(%) Model(ADPM) | D40: percent4 | F40: 모형 | H40: =0.0021*H2^(-0.183) | I40: =0.0021*I2^(-0.183) | J40: =0.0021*J2^(-0.183) | K40: =0.0021*K2^(-0.183) | L40: =0.0021*L2^(-0.183) | M40: =0.0021*M2^(-0.183) | N40: =0.0021*N2^(-0.183) | O40: =0.0021*O2^(-0.183) | ... Q40: =0.0021*Q2^(-0.183)
C41: Movement Model PHF / Movement PHF(ADPM) | D41: percent1 | F41: 모형PHF / 실제 PHF | G41: =SUMIF($H$77:$Q$77,"O",H41:Q41)/COUNTIFS($H$77:$Q$77,"O",H41:Q41,"<>0") | H41: =H37/H40 | I41: =I37/I40 | J41: =J37/J40 | K41: =K37/K40 | L41: =L37/L40 | M41: =M37/M40 | N41: =N37/N40 | O41: =O37/O40 | ... Q41: =Q37/Q40
C42: Peak Hour Movements(ADPM) | D42: float0 | F42: ADPM/movement/all/첨두시 | H42: =VLOOKUP($F42,raw_data_airside!$1:$1048576,MATCH(H$1,raw_data_airside!$1:$1,0),FALSE) | I42: =VLOOKUP($F42,raw_data_airside!$1:$1048576,MATCH(I$1,raw_data_airside!$1:$1,0),FALSE) | J42: =VLOOKUP($F42,raw_data_airside!$1:$1048576,MATCH(J$1,raw_data_airside!$1:$1,0),FALSE) | K42: =VLOOKUP($F42,raw_data_airside!$1:$1048576,MATCH(K$1,raw_data_airside!$1:$1,0),FALSE) | L42: =VLOOKUP($F42,raw_data_airside!$1:$1048576,MATCH(L$1,raw_data_airside!$1:$1,0),FALSE) | M42: =VLOOKUP($F42,raw_data_airside!$1:$1048576,MATCH(M$1,raw_data_airside!$1:$1,0),FALSE) | N42: =VLOOKUP($F42,raw_data_airside!$1:$1048576,MATCH(N$1,raw_data_airside!$1:$1,0),FALSE) | O42: =VLOOKUP($F42,raw_data_airside!$1:$1048576,MATCH(O$1,raw_data_airside!$1:$1,0),FALSE) | ... Q42: =VLOOKUP($F42,raw_data_airside!$1:$1048576,MATCH(Q$1,raw_data_airside!$1:$1,0),FALSE) | R42: =R2*R37 | S42: =S2*S37 | T42: =T2*T37 | U42: =U2*U37 | V42: =V2*V37 | W42: =W2*W37 | X42: =X2*X37 | Y42: =Y2*Y37 | ... BA42: =BA2*BA37
C43: - Peak Hour departure Movement(ADPM) | D43: float0 | F43: ADPM/movement/d/첨두시 | H43: =MIN(VLOOKUP($F43,raw_data_airside!$1:$1048576,MATCH(H$1,raw_data_airside!$1:$1,0),FALSE),H42) | I43: =MIN(VLOOKUP($F43,raw_data_airside!$1:$1048576,MATCH(I$1,raw_data_airside!$1:$1,0),FALSE),I42) | J43: =MIN(VLOOKUP($F43,raw_data_airside!$1:$1048576,MATCH(J$1,raw_data_airside!$1:$1,0),FALSE),J42) | K43: =MIN(VLOOKUP($F43,raw_data_airside!$1:$1048576,MATCH(K$1,raw_data_airside!$1:$1,0),FALSE),K42) | L43: =MIN(VLOOKUP($F43,raw_data_airside!$1:$1048576,MATCH(L$1,raw_data_airside!$1:$1,0),FALSE),L42) | M43: =MIN(VLOOKUP($F43,raw_data_airside!$1:$1048576,MATCH(M$1,raw_data_airside!$1:$1,0),FALSE),M42) | N43: =MIN(VLOOKUP($F43,raw_data_airside!$1:$1048576,MATCH(N$1,raw_data_airside!$1:$1,0),FALSE),N42) | O43: =MIN(VLOOKUP($F43,raw_data_airside!$1:$1048576,MATCH(O$1,raw_data_airside!$1:$1,0),FALSE),O42) | ... Q43: =MIN(VLOOKUP($F43,raw_data_airside!$1:$1048576,MATCH(Q$1,raw_data_airside!$1:$1,0),FALSE),Q42) | R43: =R42*R45 | S43: =S42*S45 | T43: =T42*T45 | U43: =U42*U45 | V43: =V42*V45 | W43: =W42*W45 | X43: =X42*X45 | Y43: =Y42*Y45 | ... BA43: =BA42*BA45
C44: - Peak Hour aival Movement(ADPM) | D44: float0 | F44: ADPM/movement/a/첨두시 | H44: =MIN(VLOOKUP($F44,raw_data_airside!$1:$1048576,MATCH(H$1,raw_data_airside!$1:$1,0),FALSE),H42) | I44: =MIN(VLOOKUP($F44,raw_data_airside!$1:$1048576,MATCH(I$1,raw_data_airside!$1:$1,0),FALSE),I42) | J44: =MIN(VLOOKUP($F44,raw_data_airside!$1:$1048576,MATCH(J$1,raw_data_airside!$1:$1,0),FALSE),J42) | K44: =MIN(VLOOKUP($F44,raw_data_airside!$1:$1048576,MATCH(K$1,raw_data_airside!$1:$1,0),FALSE),K42) | L44: =MIN(VLOOKUP($F44,raw_data_airside!$1:$1048576,MATCH(L$1,raw_data_airside!$1:$1,0),FALSE),L42) | M44: =MIN(VLOOKUP($F44,raw_data_airside!$1:$1048576,MATCH(M$1,raw_data_airside!$1:$1,0),FALSE),M42) | N44: =MIN(VLOOKUP($F44,raw_data_airside!$1:$1048576,MATCH(N$1,raw_data_airside!$1:$1,0),FALSE),N42) | O44: =MIN(VLOOKUP($F44,raw_data_airside!$1:$1048576,MATCH(O$1,raw_data_airside!$1:$1,0),FALSE),O42) | ... Q44: =MIN(VLOOKUP($F44,raw_data_airside!$1:$1048576,MATCH(Q$1,raw_data_airside!$1:$1,0),FALSE),Q42) | R44: =R42*R46 | S44: =S42*S46 | T44: =T42*T46 | U44: =U42*U46 | V44: =V42*V46 | W44: =W42*W46 | X44: =X42*X46 | Y44: =Y42*Y46 | ... BA44: =BA42*BA46
A45: Directional Factor(ADPM) | B45: Movement Directional Factor(ADPM) | C45: departure Movement Directional Factor(%)(ADPM) | D45: percent1 | F45: ADPM/movement/d/중방향계수 | G45: =SUMIF($H$81:$Q$81,"O",H45:Q45)/COUNTIFS($H$81:$Q$81,"O",H45:Q45,"<>0") | H45: =H43/H42 | I45: =I43/I42 | J45: =J43/J42 | K45: =K43/K42 | L45: =L43/L42 | M45: =M43/M42 | N45: =N43/N42 | O45: =O43/O42 | ... Q45: =Q43/Q42 | R45: =$G45 | S45: =$G45 | T45: =$G45 | U45: =$G45 | V45: =$G45 | W45: =$G45 | X45: =$G45 | Y45: =$G45 | ... BA45: =$G45
C46: aival Movement Directional Factor(%)(ADPM) | D46: percent1 | F46: ADPM/movement/a/중방향계수 | G46: =SUMIF($H$81:$Q$81,"O",H46:Q46)/COUNTIFS($H$81:$Q$81,"O",H46:Q46,"<>0") | H46: =H44/H42 | I46: =I44/I42 | J46: =J44/J42 | K46: =K44/K42 | L46: =L44/L42 | M46: =M44/M42 | N46: =N44/N42 | O46: =O44/O42 | ... Q46: =Q44/Q42 | R46: =$G46 | S46: =$G46 | T46: =$G46 | U46: =$G46 | V46: =$G46 | W46: =$G46 | X46: =$G46 | Y46: =$G46 | ... BA46: =$G46
A50: top | B50: mid | C50: low | D50: decimal | E50: changeable | F50: 변수설명 | G50: Ref_Index | H50: =I50-1 | I50: =J50-1 | J50: =K50-1 | K50: =L50-1 | L50: =M50-1 | M50: =N50-1 | N50: =O50-1 | O50: =P50-1 | P50: =Q50-1 | Q50: =ref!B4 | R50: =Q50+1 | S50: =R50+1 | T50: =S50+1 | U50: =T50+1 | V50: =U50+1 | W50: =V50+1 | X50: =W50+1 | Y50: =X50+1 | ... BA50: =AZ50+1
A51: Airside(SBR) | B51: Passenger Flight Movements(SBR) | C51: Movement PHF(%)(SBR) | D51: percent4 | F51: SBR/movement/all/PHF | H51: =VLOOKUP($F51,raw_data_airside!$1:$1048576,MATCH(H$1,raw_data_airside!$1:$1,0),FALSE) | I51: =VLOOKUP($F51,raw_data_airside!$1:$1048576,MATCH(I$1,raw_data_airside!$1:$1,0),FALSE) | J51: =VLOOKUP($F51,raw_data_airside!$1:$1048576,MATCH(J$1,raw_data_airside!$1:$1,0),FALSE) | K51: =VLOOKUP($F51,raw_data_airside!$1:$1048576,MATCH(K$1,raw_data_airside!$1:$1,0),FALSE) | L51: =VLOOKUP($F51,raw_data_airside!$1:$1048576,MATCH(L$1,raw_data_airside!$1:$1,0),FALSE) | M51: =VLOOKUP($F51,raw_data_airside!$1:$1048576,MATCH(M$1,raw_data_airside!$1:$1,0),FALSE) | N51: =VLOOKUP($F51,raw_data_airside!$1:$1048576,MATCH(N$1,raw_data_airside!$1:$1,0),FALSE) | O51: =VLOOKUP($F51,raw_data_airside!$1:$1048576,MATCH(O$1,raw_data_airside!$1:$1,0),FALSE) | ... Q51: =VLOOKUP($F51,raw_data_airside!$1:$1048576,MATCH(Q$1,raw_data_airside!$1:$1,0),FALSE) | R51: =0.0021*R2^(-0.183)*$G$53 | S51: =0.0021*S2^(-0.183)*$G$53 | T51: =0.0021*T2^(-0.183)*$G$53 | U51: =0.0021*U2^(-0.183)*$G$53 | V51: =0.0021*V2^(-0.183)*$G$53 | W51: =0.0021*W2^(-0.183)*$G$53 | X51: =0.0021*X2^(-0.183)*$G$53 | Y51: =0.0021*Y2^(-0.183)*$G$53 | ... BA51: =0.0021*BA2^(-0.183)*$G$53
C52: Movement PHF(%) Model(SBR) | D52: percent4 | F52: 모형 | H52: =0.0021*H2^(-0.183) | I52: =0.0021*I2^(-0.183) | J52: =0.0021*J2^(-0.183) | K52: =0.0021*K2^(-0.183) | L52: =0.0021*L2^(-0.183) | M52: =0.0021*M2^(-0.183) | N52: =0.0021*N2^(-0.183) | O52: =0.0021*O2^(-0.183) | ... Q52: =0.0021*Q2^(-0.183)
C53: Movement Model PHF / Movement PHF(SBR) | D53: percent1 | F53: 모형PHF / 실제 PHF | G53: =SUMIF($H$77:$Q$77,"O",H53:Q53)/COUNTIFS($H$77:$Q$77,"O",H53:Q53,"<>0") | H53: =H51/H52 | I53: =I51/I52 | J53: =J51/J52 | K53: =K51/K52 | L53: =L51/L52 | M53: =M51/M52 | N53: =N51/N52 | O53: =O51/O52 | ... Q53: =Q51/Q52
C54: Peak Hour Movements(SBR) | D54: float0 | F54: SBR/movement/all/첨두시 | H54: =VLOOKUP($F54,raw_data_airside!$1:$1048576,MATCH(H$1,raw_data_airside!$1:$1,0),FALSE) | I54: =VLOOKUP($F54,raw_data_airside!$1:$1048576,MATCH(I$1,raw_data_airside!$1:$1,0),FALSE) | J54: =VLOOKUP($F54,raw_data_airside!$1:$1048576,MATCH(J$1,raw_data_airside!$1:$1,0),FALSE) | K54: =VLOOKUP($F54,raw_data_airside!$1:$1048576,MATCH(K$1,raw_data_airside!$1:$1,0),FALSE) | L54: =VLOOKUP($F54,raw_data_airside!$1:$1048576,MATCH(L$1,raw_data_airside!$1:$1,0),FALSE) | M54: =VLOOKUP($F54,raw_data_airside!$1:$1048576,MATCH(M$1,raw_data_airside!$1:$1,0),FALSE) | N54: =VLOOKUP($F54,raw_data_airside!$1:$1048576,MATCH(N$1,raw_data_airside!$1:$1,0),FALSE) | O54: =VLOOKUP($F54,raw_data_airside!$1:$1048576,MATCH(O$1,raw_data_airside!$1:$1,0),FALSE) | ... Q54: =VLOOKUP($F54,raw_data_airside!$1:$1048576,MATCH(Q$1,raw_data_airside!$1:$1,0),FALSE) | R54: =R2*R51 | S54: =S2*S51 | T54: =T2*T51 | U54: =U2*U51 | V54: =V2*V51 | W54: =W2*W51 | X54: =X2*X51 | Y54: =Y2*Y51 | ... BA54: =BA2*BA51
C55: - Peak Hour departure Movement(SBR) | D55: float0 | F55: SBR/movement/d/첨두시 | H55: =VLOOKUP($F55,raw_data_airside!$1:$1048576,MATCH(H$1,raw_data_airside!$1:$1,0),FALSE) | I55: =VLOOKUP($F55,raw_data_airside!$1:$1048576,MATCH(I$1,raw_data_airside!$1:$1,0),FALSE) | J55: =VLOOKUP($F55,raw_data_airside!$1:$1048576,MATCH(J$1,raw_data_airside!$1:$1,0),FALSE) | K55: =VLOOKUP($F55,raw_data_airside!$1:$1048576,MATCH(K$1,raw_data_airside!$1:$1,0),FALSE) | L55: =VLOOKUP($F55,raw_data_airside!$1:$1048576,MATCH(L$1,raw_data_airside!$1:$1,0),FALSE) | M55: =VLOOKUP($F55,raw_data_airside!$1:$1048576,MATCH(M$1,raw_data_airside!$1:$1,0),FALSE) | N55: =VLOOKUP($F55,raw_data_airside!$1:$1048576,MATCH(N$1,raw_data_airside!$1:$1,0),FALSE) | O55: =VLOOKUP($F55,raw_data_airside!$1:$1048576,MATCH(O$1,raw_data_airside!$1:$1,0),FALSE) | ... Q55: =VLOOKUP($F55,raw_data_airside!$1:$1048576,MATCH(Q$1,raw_data_airside!$1:$1,0),FALSE) | R55: =R54*R57 | S55: =S54*S57 | T55: =T54*T57 | U55: =U54*U57 | V55: =V54*V57 | W55: =W54*W57 | X55: =X54*X57 | Y55: =Y54*Y57 | ... BA55: =BA54*BA57
C56: - Peak Hour aival Movement(SBR) | D56: float0 | F56: SBR/movement/a/첨두시 | H56: =VLOOKUP($F56,raw_data_airside!$1:$1048576,MATCH(H$1,raw_data_airside!$1:$1,0),FALSE) | I56: =VLOOKUP($F56,raw_data_airside!$1:$1048576,MATCH(I$1,raw_data_airside!$1:$1,0),FALSE) | J56: =VLOOKUP($F56,raw_data_airside!$1:$1048576,MATCH(J$1,raw_data_airside!$1:$1,0),FALSE) | K56: =VLOOKUP($F56,raw_data_airside!$1:$1048576,MATCH(K$1,raw_data_airside!$1:$1,0),FALSE) | L56: =VLOOKUP($F56,raw_data_airside!$1:$1048576,MATCH(L$1,raw_data_airside!$1:$1,0),FALSE) | M56: =VLOOKUP($F56,raw_data_airside!$1:$1048576,MATCH(M$1,raw_data_airside!$1:$1,0),FALSE) | N56: =VLOOKUP($F56,raw_data_airside!$1:$1048576,MATCH(N$1,raw_data_airside!$1:$1,0),FALSE) | O56: =VLOOKUP($F56,raw_data_airside!$1:$1048576,MATCH(O$1,raw_data_airside!$1:$1,0),FALSE) | ... Q56: =VLOOKUP($F56,raw_data_airside!$1:$1048576,MATCH(Q$1,raw_data_airside!$1:$1,0),FALSE) | R56: =R54*R58 | S56: =S54*S58 | T56: =T54*T58 | U56: =U54*U58 | V56: =V54*V58 | W56: =W54*W58 | X56: =X54*X58 | Y56: =Y54*Y58 | ... BA56: =BA54*BA58
A57: Directional Factor(SBR) | B57: Movement Directional Factor(SBR) | C57: departure Movement Directional Factor(%)(SBR) | D57: percent1 | F57: ADPM/movement/d/중방향계수 | G57: =SUMIF($H$81:$Q$81,"O",H57:Q57)/COUNTIFS($H$81:$Q$81,"O",H57:Q57,"<>0") | H57: =H55/H54 | I57: =I55/I54 | J57: =J55/J54 | K57: =K55/K54 | L57: =L55/L54 | M57: =M55/M54 | N57: =N55/N54 | O57: =O55/O54 | ... Q57: =Q55/Q54 | R57: =$G57 | S57: =$G57 | T57: =$G57 | U57: =$G57 | V57: =$G57 | W57: =$G57 | X57: =$G57 | Y57: =$G57 | ... BA57: =$G57
C58: aival Movement Directional Factor(%)(SBR) | D58: percent1 | F58: ADPM/movement/a/중방향계수 | G58: =SUMIF($H$81:$Q$81,"O",H58:Q58)/COUNTIFS($H$81:$Q$81,"O",H58:Q58,"<>0") | H58: =H56/H54 | I58: =I56/I54 | J58: =J56/J54 | K58: =K56/K54 | L58: =L56/L54 | M58: =M56/M54 | N58: =N56/N54 | O58: =O56/O54 | ... Q58: =Q56/Q54 | R58: =$G58 | S58: =$G58 | T58: =$G58 | U58: =$G58 | V58: =$G58 | W58: =$G58 | X58: =$G58 | Y58: =$G58 | ... BA58: =$G58
C60: Aircraft_category
C61: (Widebody Jets)
C62: (Narrowbody Jets)
C63: (Regional Jets)
C64: (Business Jets)
G68: 참조지표 제작 | H68: =I68-1 | I68: =J68-1 | J68: =K68-1 | K68: =L68-1 | L68: =M68-1 | M68: =N68-1 | N68: =O68-1 | O68: =P68-1 | P68: =Q68-1 | Q68: =ref!B4
G69: Demand | H69: =IF(VLOOKUP($G69,ref!$A$12:$AT$35,MATCH(H$1,ref!$12:$12,0),FALSE),"O","") | I69: =IF(VLOOKUP($G69,ref!$A$12:$AT$35,MATCH(I$1,ref!$12:$12,0),FALSE),"O","") | J69: =IF(VLOOKUP($G69,ref!$A$12:$AT$35,MATCH(J$1,ref!$12:$12,0),FALSE),"O","") | K69: =IF(VLOOKUP($G69,ref!$A$12:$AT$35,MATCH(K$1,ref!$12:$12,0),FALSE),"O","") | L69: =IF(VLOOKUP($G69,ref!$A$12:$AT$35,MATCH(L$1,ref!$12:$12,0),FALSE),"O","") | M69: =IF(VLOOKUP($G69,ref!$A$12:$AT$35,MATCH(M$1,ref!$12:$12,0),FALSE),"O","") | N69: =IF(VLOOKUP($G69,ref!$A$12:$AT$35,MATCH(N$1,ref!$12:$12,0),FALSE),"O","") | O69: =IF(VLOOKUP($G69,ref!$A$12:$AT$35,MATCH(O$1,ref!$12:$12,0),FALSE),"O","") | ... Q69: =IF(VLOOKUP($G69,ref!$A$12:$AT$35,MATCH(Q$1,ref!$12:$12,0),FALSE),"O","")
G70: Load_Factor | H70: =IF(VLOOKUP($G70,ref!$A$12:$AT$35,MATCH(H$1,ref!$12:$12,0),FALSE),"O","") | I70: =IF(VLOOKUP($G70,ref!$A$12:$AT$35,MATCH(I$1,ref!$12:$12,0),FALSE),"O","") | J70: =IF(VLOOKUP($G70,ref!$A$12:$AT$35,MATCH(J$1,ref!$12:$12,0),FALSE),"O","") | K70: =IF(VLOOKUP($G70,ref!$A$12:$AT$35,MATCH(K$1,ref!$12:$12,0),FALSE),"O","") | L70: =IF(VLOOKUP($G70,ref!$A$12:$AT$35,MATCH(L$1,ref!$12:$12,0),FALSE),"O","") | M70: =IF(VLOOKUP($G70,ref!$A$12:$AT$35,MATCH(M$1,ref!$12:$12,0),FALSE),"O","") | N70: =IF(VLOOKUP($G70,ref!$A$12:$AT$35,MATCH(N$1,ref!$12:$12,0),FALSE),"O","") | O70: =IF(VLOOKUP($G70,ref!$A$12:$AT$35,MATCH(O$1,ref!$12:$12,0),FALSE),"O","") | ... Q70: =IF(VLOOKUP($G70,ref!$A$12:$AT$35,MATCH(Q$1,ref!$12:$12,0),FALSE),"O","")
G71: Transfer_Rate | H71: =IF(VLOOKUP($G71,ref!$A$12:$AT$35,MATCH(H$1,ref!$12:$12,0),FALSE),"O","") | I71: =IF(VLOOKUP($G71,ref!$A$12:$AT$35,MATCH(I$1,ref!$12:$12,0),FALSE),"O","") | J71: =IF(VLOOKUP($G71,ref!$A$12:$AT$35,MATCH(J$1,ref!$12:$12,0),FALSE),"O","") | K71: =IF(VLOOKUP($G71,ref!$A$12:$AT$35,MATCH(K$1,ref!$12:$12,0),FALSE),"O","") | L71: =IF(VLOOKUP($G71,ref!$A$12:$AT$35,MATCH(L$1,ref!$12:$12,0),FALSE),"O","") | M71: =IF(VLOOKUP($G71,ref!$A$12:$AT$35,MATCH(M$1,ref!$12:$12,0),FALSE),"O","") | N71: =IF(VLOOKUP($G71,ref!$A$12:$AT$35,MATCH(N$1,ref!$12:$12,0),FALSE),"O","") | O71: =IF(VLOOKUP($G71,ref!$A$12:$AT$35,MATCH(O$1,ref!$12:$12,0),FALSE),"O","") | ... Q71: =IF(VLOOKUP($G71,ref!$A$12:$AT$35,MATCH(Q$1,ref!$12:$12,0),FALSE),"O","")
G72: FleetMix_Rate | H72: =IF(VLOOKUP($G72,ref!$A$12:$AT$35,MATCH(H$1,ref!$12:$12,0),FALSE),"O","") | I72: =IF(VLOOKUP($G72,ref!$A$12:$AT$35,MATCH(I$1,ref!$12:$12,0),FALSE),"O","") | J72: =IF(VLOOKUP($G72,ref!$A$12:$AT$35,MATCH(J$1,ref!$12:$12,0),FALSE),"O","") | K72: =IF(VLOOKUP($G72,ref!$A$12:$AT$35,MATCH(K$1,ref!$12:$12,0),FALSE),"O","") | L72: =IF(VLOOKUP($G72,ref!$A$12:$AT$35,MATCH(L$1,ref!$12:$12,0),FALSE),"O","") | M72: =IF(VLOOKUP($G72,ref!$A$12:$AT$35,MATCH(M$1,ref!$12:$12,0),FALSE),"O","") | N72: =IF(VLOOKUP($G72,ref!$A$12:$AT$35,MATCH(N$1,ref!$12:$12,0),FALSE),"O","") | O72: =IF(VLOOKUP($G72,ref!$A$12:$AT$35,MATCH(O$1,ref!$12:$12,0),FALSE),"O","") | ... Q72: =IF(VLOOKUP($G72,ref!$A$12:$AT$35,MATCH(Q$1,ref!$12:$12,0),FALSE),"O","")
G73: Seats_Per_Aircraft | H73: =IF(VLOOKUP($G73,ref!$A$12:$AT$35,MATCH(H$1,ref!$12:$12,0),FALSE),"O","") | I73: =IF(VLOOKUP($G73,ref!$A$12:$AT$35,MATCH(I$1,ref!$12:$12,0),FALSE),"O","") | J73: =IF(VLOOKUP($G73,ref!$A$12:$AT$35,MATCH(J$1,ref!$12:$12,0),FALSE),"O","") | K73: =IF(VLOOKUP($G73,ref!$A$12:$AT$35,MATCH(K$1,ref!$12:$12,0),FALSE),"O","") | L73: =IF(VLOOKUP($G73,ref!$A$12:$AT$35,MATCH(L$1,ref!$12:$12,0),FALSE),"O","") | M73: =IF(VLOOKUP($G73,ref!$A$12:$AT$35,MATCH(M$1,ref!$12:$12,0),FALSE),"O","") | N73: =IF(VLOOKUP($G73,ref!$A$12:$AT$35,MATCH(N$1,ref!$12:$12,0),FALSE),"O","") | O73: =IF(VLOOKUP($G73,ref!$A$12:$AT$35,MATCH(O$1,ref!$12:$12,0),FALSE),"O","") | ... Q73: =IF(VLOOKUP($G73,ref!$A$12:$AT$35,MATCH(Q$1,ref!$12:$12,0),FALSE),"O","")
G74: Load_Factor_By_Class | H74: =IF(VLOOKUP($G74,ref!$A$12:$AT$35,MATCH(H$1,ref!$12:$12,0),FALSE),"O","") | I74: =IF(VLOOKUP($G74,ref!$A$12:$AT$35,MATCH(I$1,ref!$12:$12,0),FALSE),"O","") | J74: =IF(VLOOKUP($G74,ref!$A$12:$AT$35,MATCH(J$1,ref!$12:$12,0),FALSE),"O","") | K74: =IF(VLOOKUP($G74,ref!$A$12:$AT$35,MATCH(K$1,ref!$12:$12,0),FALSE),"O","") | L74: =IF(VLOOKUP($G74,ref!$A$12:$AT$35,MATCH(L$1,ref!$12:$12,0),FALSE),"O","") | M74: =IF(VLOOKUP($G74,ref!$A$12:$AT$35,MATCH(M$1,ref!$12:$12,0),FALSE),"O","") | N74: =IF(VLOOKUP($G74,ref!$A$12:$AT$35,MATCH(N$1,ref!$12:$12,0),FALSE),"O","") | O74: =IF(VLOOKUP($G74,ref!$A$12:$AT$35,MATCH(O$1,ref!$12:$12,0),FALSE),"O","") | ... Q74: =IF(VLOOKUP($G74,ref!$A$12:$AT$35,MATCH(Q$1,ref!$12:$12,0),FALSE),"O","")
G75: Transfer_Rate_By_Class | H75: =IF(VLOOKUP($G75,ref!$A$12:$AT$35,MATCH(H$1,ref!$12:$12,0),FALSE),"O","") | I75: =IF(VLOOKUP($G75,ref!$A$12:$AT$35,MATCH(I$1,ref!$12:$12,0),FALSE),"O","") | J75: =IF(VLOOKUP($G75,ref!$A$12:$AT$35,MATCH(J$1,ref!$12:$12,0),FALSE),"O","") | K75: =IF(VLOOKUP($G75,ref!$A$12:$AT$35,MATCH(K$1,ref!$12:$12,0),FALSE),"O","") | L75: =IF(VLOOKUP($G75,ref!$A$12:$AT$35,MATCH(L$1,ref!$12:$12,0),FALSE),"O","") | M75: =IF(VLOOKUP($G75,ref!$A$12:$AT$35,MATCH(M$1,ref!$12:$12,0),FALSE),"O","") | N75: =IF(VLOOKUP($G75,ref!$A$12:$AT$35,MATCH(N$1,ref!$12:$12,0),FALSE),"O","") | O75: =IF(VLOOKUP($G75,ref!$A$12:$AT$35,MATCH(O$1,ref!$12:$12,0),FALSE),"O","") | ... Q75: =IF(VLOOKUP($G75,ref!$A$12:$AT$35,MATCH(Q$1,ref!$12:$12,0),FALSE),"O","")
G76: Crew_Per_Aircraft | H76: =IF(VLOOKUP($G76,ref!$A$12:$AT$35,MATCH(H$1,ref!$12:$12,0),FALSE),"O","") | I76: =IF(VLOOKUP($G76,ref!$A$12:$AT$35,MATCH(I$1,ref!$12:$12,0),FALSE),"O","") | J76: =IF(VLOOKUP($G76,ref!$A$12:$AT$35,MATCH(J$1,ref!$12:$12,0),FALSE),"O","") | K76: =IF(VLOOKUP($G76,ref!$A$12:$AT$35,MATCH(K$1,ref!$12:$12,0),FALSE),"O","") | L76: =IF(VLOOKUP($G76,ref!$A$12:$AT$35,MATCH(L$1,ref!$12:$12,0),FALSE),"O","") | M76: =IF(VLOOKUP($G76,ref!$A$12:$AT$35,MATCH(M$1,ref!$12:$12,0),FALSE),"O","") | N76: =IF(VLOOKUP($G76,ref!$A$12:$AT$35,MATCH(N$1,ref!$12:$12,0),FALSE),"O","") | O76: =IF(VLOOKUP($G76,ref!$A$12:$AT$35,MATCH(O$1,ref!$12:$12,0),FALSE),"O","") | ... Q76: =IF(VLOOKUP($G76,ref!$A$12:$AT$35,MATCH(Q$1,ref!$12:$12,0),FALSE),"O","")
G77: Movement_PHF_Adjustment | H77: =IF(VLOOKUP($G77,ref!$A$12:$AT$35,MATCH(H$1,ref!$12:$12,0),FALSE),"O","") | I77: =IF(VLOOKUP($G77,ref!$A$12:$AT$35,MATCH(I$1,ref!$12:$12,0),FALSE),"O","") | J77: =IF(VLOOKUP($G77,ref!$A$12:$AT$35,MATCH(J$1,ref!$12:$12,0),FALSE),"O","") | K77: =IF(VLOOKUP($G77,ref!$A$12:$AT$35,MATCH(K$1,ref!$12:$12,0),FALSE),"O","") | L77: =IF(VLOOKUP($G77,ref!$A$12:$AT$35,MATCH(L$1,ref!$12:$12,0),FALSE),"O","") | M77: =IF(VLOOKUP($G77,ref!$A$12:$AT$35,MATCH(M$1,ref!$12:$12,0),FALSE),"O","") | N77: =IF(VLOOKUP($G77,ref!$A$12:$AT$35,MATCH(N$1,ref!$12:$12,0),FALSE),"O","") | O77: =IF(VLOOKUP($G77,ref!$A$12:$AT$35,MATCH(O$1,ref!$12:$12,0),FALSE),"O","") | ... Q77: =IF(VLOOKUP($G77,ref!$A$12:$AT$35,MATCH(Q$1,ref!$12:$12,0),FALSE),"O","")
G78: Movement_D_Factor | H78: =IF(VLOOKUP($G78,ref!$A$12:$AT$35,MATCH(H$1,ref!$12:$12,0),FALSE),"O","") | I78: =IF(VLOOKUP($G78,ref!$A$12:$AT$35,MATCH(I$1,ref!$12:$12,0),FALSE),"O","") | J78: =IF(VLOOKUP($G78,ref!$A$12:$AT$35,MATCH(J$1,ref!$12:$12,0),FALSE),"O","") | K78: =IF(VLOOKUP($G78,ref!$A$12:$AT$35,MATCH(K$1,ref!$12:$12,0),FALSE),"O","") | L78: =IF(VLOOKUP($G78,ref!$A$12:$AT$35,MATCH(L$1,ref!$12:$12,0),FALSE),"O","") | M78: =IF(VLOOKUP($G78,ref!$A$12:$AT$35,MATCH(M$1,ref!$12:$12,0),FALSE),"O","") | N78: =IF(VLOOKUP($G78,ref!$A$12:$AT$35,MATCH(N$1,ref!$12:$12,0),FALSE),"O","") | O78: =IF(VLOOKUP($G78,ref!$A$12:$AT$35,MATCH(O$1,ref!$12:$12,0),FALSE),"O","") | ... Q78: =IF(VLOOKUP($G78,ref!$A$12:$AT$35,MATCH(Q$1,ref!$12:$12,0),FALSE),"O","")
G79: Passenger_PHF_Adjustment | H79: =IF(VLOOKUP($G79,ref!$A$12:$AT$35,MATCH(H$1,ref!$12:$12,0),FALSE),"O","") | I79: =IF(VLOOKUP($G79,ref!$A$12:$AT$35,MATCH(I$1,ref!$12:$12,0),FALSE),"O","") | J79: =IF(VLOOKUP($G79,ref!$A$12:$AT$35,MATCH(J$1,ref!$12:$12,0),FALSE),"O","") | K79: =IF(VLOOKUP($G79,ref!$A$12:$AT$35,MATCH(K$1,ref!$12:$12,0),FALSE),"O","") | L79: =IF(VLOOKUP($G79,ref!$A$12:$AT$35,MATCH(L$1,ref!$12:$12,0),FALSE),"O","") | M79: =IF(VLOOKUP($G79,ref!$A$12:$AT$35,MATCH(M$1,ref!$12:$12,0),FALSE),"O","") | N79: =IF(VLOOKUP($G79,ref!$A$12:$AT$35,MATCH(N$1,ref!$12:$12,0),FALSE),"O","") | O79: =IF(VLOOKUP($G79,ref!$A$12:$AT$35,MATCH(O$1,ref!$12:$12,0),FALSE),"O","") | ... Q79: =IF(VLOOKUP($G79,ref!$A$12:$AT$35,MATCH(Q$1,ref!$12:$12,0),FALSE),"O","")
G80: Passenger_D_Factor | H80: =IF(VLOOKUP($G80,ref!$A$12:$AT$35,MATCH(H$1,ref!$12:$12,0),FALSE),"O","") | I80: =IF(VLOOKUP($G80,ref!$A$12:$AT$35,MATCH(I$1,ref!$12:$12,0),FALSE),"O","") | J80: =IF(VLOOKUP($G80,ref!$A$12:$AT$35,MATCH(J$1,ref!$12:$12,0),FALSE),"O","") | K80: =IF(VLOOKUP($G80,ref!$A$12:$AT$35,MATCH(K$1,ref!$12:$12,0),FALSE),"O","") | L80: =IF(VLOOKUP($G80,ref!$A$12:$AT$35,MATCH(L$1,ref!$12:$12,0),FALSE),"O","") | M80: =IF(VLOOKUP($G80,ref!$A$12:$AT$35,MATCH(M$1,ref!$12:$12,0),FALSE),"O","") | N80: =IF(VLOOKUP($G80,ref!$A$12:$AT$35,MATCH(N$1,ref!$12:$12,0),FALSE),"O","") | O80: =IF(VLOOKUP($G80,ref!$A$12:$AT$35,MATCH(O$1,ref!$12:$12,0),FALSE),"O","") | ... Q80: =IF(VLOOKUP($G80,ref!$A$12:$AT$35,MATCH(Q$1,ref!$12:$12,0),FALSE),"O","")
... G83: PeakTime Standing | H83: =IF(VLOOKUP($G83,ref!$A$12:$AT$35,MATCH(H$1,ref!$12:$12,0),FALSE),"O","") | I83: =IF(VLOOKUP($G83,ref!$A$12:$AT$35,MATCH(I$1,ref!$12:$12,0),FALSE),"O","") | J83: =IF(VLOOKUP($G83,ref!$A$12:$AT$35,MATCH(J$1,ref!$12:$12,0),FALSE),"O","") | K83: =IF(VLOOKUP($G83,ref!$A$12:$AT$35,MATCH(K$1,ref!$12:$12,0),FALSE),"O","") | L83: =IF(VLOOKUP($G83,ref!$A$12:$AT$35,MATCH(L$1,ref!$12:$12,0),FALSE),"O","") | M83: =IF(VLOOKUP($G83,ref!$A$12:$AT$35,MATCH(M$1,ref!$12:$12,0),FALSE),"O","") | N83: =IF(VLOOKUP($G83,ref!$A$12:$AT$35,MATCH(N$1,ref!$12:$12,0),FALSE),"O","") | O83: =IF(VLOOKUP($G83,ref!$A$12:$AT$35,MATCH(O$1,ref!$12:$12,0),FALSE),"O","") | ... Q83: =IF(VLOOKUP($G83,ref!$A$12:$AT$35,MATCH(Q$1,ref!$12:$12,0),FALSE),"O","")

Sheet Cargo Demand
A1: top | B1: mid | C1: low | D1: decimal | E1: changeable | F1: 변수설명 | G1: Ref_Index | H1: =I1-1 | I1: =J1-1 | J1: =K1-1 | K1: =L1-1 | L1: =M1-1 | M1: =N1-1 | N1: =O1-1 | O1: =P1-1 | P1: =Q1-1 | Q1: =ref!B4 | R1: =Q1+1 | S1: =R1+1 | T1: =S1+1 | U1: =T1+1 | V1: =U1+1 | W1: =V1+1 | X1: =W1+1 | Y1: =X1+1 | ... BA1: =AZ1+1
C2: Cargo/Passenger ratio | F2: 화물/여객 비율 | G2: =IFERROR(SUMIF($H$73:$Q$73,"O",H2:Q2)/COUNTIFS($H$73:$Q$73,"O",H14:Q14,"<>0"),0) | H2: =H3/'Pax Demand'!H20 | I2: =I3/'Pax Demand'!I20 | J2: =J3/'Pax Demand'!J20 | K2: =K3/'Pax Demand'!K20 | L2: =L3/'Pax Demand'!L20 | M2: =M3/'Pax Demand'!M20 | N2: =N3/'Pax Demand'!N20 | O2: =O3/'Pax Demand'!O20 | ... Q2: =Q3/'Pax Demand'!Q20 | R2: =G2 | S2: =R2 | T2: =S2 | U2: =T2 | V2: =U2 | W2: =V2 | X2: =W2 | Y2: =X2 | Z2: =Y2 | ... BA2: =AZ2
A3: Cargo Flight Index | C3: Annual Movements | D3: float0 | F3: 연간운항 | H3: =VLOOKUP($F3,raw_data_cargo!$1:$1048576,MATCH(H$1,raw_data_cargo!$1:$1,0),FALSE) | I3: =VLOOKUP($F3,raw_data_cargo!$1:$1048576,MATCH(I$1,raw_data_cargo!$1:$1,0),FALSE) | J3: =VLOOKUP($F3,raw_data_cargo!$1:$1048576,MATCH(J$1,raw_data_cargo!$1:$1,0),FALSE) | K3: =VLOOKUP($F3,raw_data_cargo!$1:$1048576,MATCH(K$1,raw_data_cargo!$1:$1,0),FALSE) | L3: =VLOOKUP($F3,raw_data_cargo!$1:$1048576,MATCH(L$1,raw_data_cargo!$1:$1,0),FALSE) | M3: =VLOOKUP($F3,raw_data_cargo!$1:$1048576,MATCH(M$1,raw_data_cargo!$1:$1,0),FALSE) | N3: =VLOOKUP($F3,raw_data_cargo!$1:$1048576,MATCH(N$1,raw_data_cargo!$1:$1,0),FALSE) | O3: =VLOOKUP($F3,raw_data_cargo!$1:$1048576,MATCH(O$1,raw_data_cargo!$1:$1,0),FALSE) | ... Q3: =VLOOKUP($F3,raw_data_cargo!$1:$1048576,MATCH(Q$1,raw_data_cargo!$1:$1,0),FALSE) | R3: =R2*'Pax Demand'!R20 | S3: =S2*'Pax Demand'!S20 | T3: =T2*'Pax Demand'!T20 | U3: =U2*'Pax Demand'!U20 | V3: =V2*'Pax Demand'!V20 | W3: =W2*'Pax Demand'!W20 | X3: =X2*'Pax Demand'!X20 | Y3: =Y2*'Pax Demand'!Y20 | ... BA3: =BA2*'Pax Demand'!BA20
C4: Average Taxiing Time Per Aircraft(min) | D4: float0 | F4: 대당택싱평균 | H4: =VLOOKUP($F4,raw_data_cargo!$1:$1048576,MATCH(H$1,raw_data_cargo!$1:$1,0),FALSE) | I4: =VLOOKUP($F4,raw_data_cargo!$1:$1048576,MATCH(I$1,raw_data_cargo!$1:$1,0),FALSE) | J4: =VLOOKUP($F4,raw_data_cargo!$1:$1048576,MATCH(J$1,raw_data_cargo!$1:$1,0),FALSE) | K4: =VLOOKUP($F4,raw_data_cargo!$1:$1048576,MATCH(K$1,raw_data_cargo!$1:$1,0),FALSE) | L4: =VLOOKUP($F4,raw_data_cargo!$1:$1048576,MATCH(L$1,raw_data_cargo!$1:$1,0),FALSE) | M4: =VLOOKUP($F4,raw_data_cargo!$1:$1048576,MATCH(M$1,raw_data_cargo!$1:$1,0),FALSE) | N4: =VLOOKUP($F4,raw_data_cargo!$1:$1048576,MATCH(N$1,raw_data_cargo!$1:$1,0),FALSE) | O4: =VLOOKUP($F4,raw_data_cargo!$1:$1048576,MATCH(O$1,raw_data_cargo!$1:$1,0),FALSE) | ... Q4: =VLOOKUP($F4,raw_data_cargo!$1:$1048576,MATCH(Q$1,raw_data_cargo!$1:$1,0),FALSE)
C5: Average PeakTime TurnAround Standing Time(min) | D5: float0 | F5: 피크시간 턴어라운드편 평균주기시간(분) | H5: =VLOOKUP($F5,raw_data_cargo!$1:$1048576,MATCH(H$1,raw_data_cargo!$1:$1,0),FALSE) | I5: =VLOOKUP($F5,raw_data_cargo!$1:$1048576,MATCH(I$1,raw_data_cargo!$1:$1,0),FALSE) | J5: =VLOOKUP($F5,raw_data_cargo!$1:$1048576,MATCH(J$1,raw_data_cargo!$1:$1,0),FALSE) | K5: =VLOOKUP($F5,raw_data_cargo!$1:$1048576,MATCH(K$1,raw_data_cargo!$1:$1,0),FALSE) | L5: =VLOOKUP($F5,raw_data_cargo!$1:$1048576,MATCH(L$1,raw_data_cargo!$1:$1,0),FALSE) | M5: =VLOOKUP($F5,raw_data_cargo!$1:$1048576,MATCH(M$1,raw_data_cargo!$1:$1,0),FALSE) | N5: =VLOOKUP($F5,raw_data_cargo!$1:$1048576,MATCH(N$1,raw_data_cargo!$1:$1,0),FALSE) | O5: =VLOOKUP($F5,raw_data_cargo!$1:$1048576,MATCH(O$1,raw_data_cargo!$1:$1,0),FALSE) | ... Q5: =VLOOKUP($F5,raw_data_cargo!$1:$1048576,MATCH(Q$1,raw_data_cargo!$1:$1,0),FALSE)
C6: Average PeakTIme TurnAround Ground Time(min) | D6: float0 | F6: 피크시간 턴어라운드편 평균그라운드시간(분) | H6: =VLOOKUP($F6,raw_data_cargo!$1:$1048576,MATCH(H$1,raw_data_cargo!$1:$1,0),FALSE) | I6: =VLOOKUP($F6,raw_data_cargo!$1:$1048576,MATCH(I$1,raw_data_cargo!$1:$1,0),FALSE) | J6: =VLOOKUP($F6,raw_data_cargo!$1:$1048576,MATCH(J$1,raw_data_cargo!$1:$1,0),FALSE) | K6: =VLOOKUP($F6,raw_data_cargo!$1:$1048576,MATCH(K$1,raw_data_cargo!$1:$1,0),FALSE) | L6: =VLOOKUP($F6,raw_data_cargo!$1:$1048576,MATCH(L$1,raw_data_cargo!$1:$1,0),FALSE) | M6: =VLOOKUP($F6,raw_data_cargo!$1:$1048576,MATCH(M$1,raw_data_cargo!$1:$1,0),FALSE) | N6: =VLOOKUP($F6,raw_data_cargo!$1:$1048576,MATCH(N$1,raw_data_cargo!$1:$1,0),FALSE) | O6: =VLOOKUP($F6,raw_data_cargo!$1:$1048576,MATCH(O$1,raw_data_cargo!$1:$1,0),FALSE) | ... Q6: =VLOOKUP($F6,raw_data_cargo!$1:$1048576,MATCH(Q$1,raw_data_cargo!$1:$1,0),FALSE)
C7: Average TurnAround Standing Time(min) | D7: float0 | F7: 턴어라운드편 평균주기시간(분) | H7: =VLOOKUP($F7,raw_data_cargo!$1:$1048576,MATCH(H$1,raw_data_cargo!$1:$1,0),FALSE) | I7: =VLOOKUP($F7,raw_data_cargo!$1:$1048576,MATCH(I$1,raw_data_cargo!$1:$1,0),FALSE) | J7: =VLOOKUP($F7,raw_data_cargo!$1:$1048576,MATCH(J$1,raw_data_cargo!$1:$1,0),FALSE) | K7: =VLOOKUP($F7,raw_data_cargo!$1:$1048576,MATCH(K$1,raw_data_cargo!$1:$1,0),FALSE) | L7: =VLOOKUP($F7,raw_data_cargo!$1:$1048576,MATCH(L$1,raw_data_cargo!$1:$1,0),FALSE) | M7: =VLOOKUP($F7,raw_data_cargo!$1:$1048576,MATCH(M$1,raw_data_cargo!$1:$1,0),FALSE) | N7: =VLOOKUP($F7,raw_data_cargo!$1:$1048576,MATCH(N$1,raw_data_cargo!$1:$1,0),FALSE) | O7: =VLOOKUP($F7,raw_data_cargo!$1:$1048576,MATCH(O$1,raw_data_cargo!$1:$1,0),FALSE) | ... Q7: =VLOOKUP($F7,raw_data_cargo!$1:$1048576,MATCH(Q$1,raw_data_cargo!$1:$1,0),FALSE)
C8: Average TurnAround Ground Time(min) | D8: float0 | F8: 턴어라운드편 평균그라운드시간(분) | H8: =VLOOKUP($F8,raw_data_cargo!$1:$1048576,MATCH(H$1,raw_data_cargo!$1:$1,0),FALSE) | I8: =VLOOKUP($F8,raw_data_cargo!$1:$1048576,MATCH(I$1,raw_data_cargo!$1:$1,0),FALSE) | J8: =VLOOKUP($F8,raw_data_cargo!$1:$1048576,MATCH(J$1,raw_data_cargo!$1:$1,0),FALSE) | K8: =VLOOKUP($F8,raw_data_cargo!$1:$1048576,MATCH(K$1,raw_data_cargo!$1:$1,0),FALSE) | L8: =VLOOKUP($F8,raw_data_cargo!$1:$1048576,MATCH(L$1,raw_data_cargo!$1:$1,0),FALSE) | M8: =VLOOKUP($F8,raw_data_cargo!$1:$1048576,MATCH(M$1,raw_data_cargo!$1:$1,0),FALSE) | N8: =VLOOKUP($F8,raw_data_cargo!$1:$1048576,MATCH(N$1,raw_data_cargo!$1:$1,0),FALSE) | O8: =VLOOKUP($F8,raw_data_cargo!$1:$1048576,MATCH(O$1,raw_data_cargo!$1:$1,0),FALSE) | ... Q8: =VLOOKUP($F8,raw_data_cargo!$1:$1048576,MATCH(Q$1,raw_data_cargo!$1:$1,0),FALSE)
C9: Average Total Standing Time(min) | D9: float0 | F9: (오버나잇, 소산 포함) 평균주기시간(분) | H9: =VLOOKUP($F9,raw_data_cargo!$1:$1048576,MATCH(H$1,raw_data_cargo!$1:$1,0),FALSE) | I9: =VLOOKUP($F9,raw_data_cargo!$1:$1048576,MATCH(I$1,raw_data_cargo!$1:$1,0),FALSE) | J9: =VLOOKUP($F9,raw_data_cargo!$1:$1048576,MATCH(J$1,raw_data_cargo!$1:$1,0),FALSE) | K9: =VLOOKUP($F9,raw_data_cargo!$1:$1048576,MATCH(K$1,raw_data_cargo!$1:$1,0),FALSE) | L9: =VLOOKUP($F9,raw_data_cargo!$1:$1048576,MATCH(L$1,raw_data_cargo!$1:$1,0),FALSE) | M9: =VLOOKUP($F9,raw_data_cargo!$1:$1048576,MATCH(M$1,raw_data_cargo!$1:$1,0),FALSE) | N9: =VLOOKUP($F9,raw_data_cargo!$1:$1048576,MATCH(N$1,raw_data_cargo!$1:$1,0),FALSE) | O9: =VLOOKUP($F9,raw_data_cargo!$1:$1048576,MATCH(O$1,raw_data_cargo!$1:$1,0),FALSE) | ... Q9: =VLOOKUP($F9,raw_data_cargo!$1:$1048576,MATCH(Q$1,raw_data_cargo!$1:$1,0),FALSE)
C10: Average Total Ground Time(min) | D10: float0 | F10: (오버나잇, 소산 포함) 평균그라운드시간(분) | H10: =VLOOKUP($F10,raw_data_cargo!$1:$1048576,MATCH(H$1,raw_data_cargo!$1:$1,0),FALSE) | I10: =VLOOKUP($F10,raw_data_cargo!$1:$1048576,MATCH(I$1,raw_data_cargo!$1:$1,0),FALSE) | J10: =VLOOKUP($F10,raw_data_cargo!$1:$1048576,MATCH(J$1,raw_data_cargo!$1:$1,0),FALSE) | K10: =VLOOKUP($F10,raw_data_cargo!$1:$1048576,MATCH(K$1,raw_data_cargo!$1:$1,0),FALSE) | L10: =VLOOKUP($F10,raw_data_cargo!$1:$1048576,MATCH(L$1,raw_data_cargo!$1:$1,0),FALSE) | M10: =VLOOKUP($F10,raw_data_cargo!$1:$1048576,MATCH(M$1,raw_data_cargo!$1:$1,0),FALSE) | N10: =VLOOKUP($F10,raw_data_cargo!$1:$1048576,MATCH(N$1,raw_data_cargo!$1:$1,0),FALSE) | O10: =VLOOKUP($F10,raw_data_cargo!$1:$1048576,MATCH(O$1,raw_data_cargo!$1:$1,0),FALSE) | ... Q10: =VLOOKUP($F10,raw_data_cargo!$1:$1048576,MATCH(Q$1,raw_data_cargo!$1:$1,0),FALSE)
C11: Maximum Takeoff Weight Per Aircraft(lb) | D11: float0 | F11: 대당최대이륙중량 | H11: =VLOOKUP($F11,raw_data_cargo!$1:$1048576,MATCH(H$1,raw_data_cargo!$1:$1,0),FALSE) | I11: =VLOOKUP($F11,raw_data_cargo!$1:$1048576,MATCH(I$1,raw_data_cargo!$1:$1,0),FALSE) | J11: =VLOOKUP($F11,raw_data_cargo!$1:$1048576,MATCH(J$1,raw_data_cargo!$1:$1,0),FALSE) | K11: =VLOOKUP($F11,raw_data_cargo!$1:$1048576,MATCH(K$1,raw_data_cargo!$1:$1,0),FALSE) | L11: =VLOOKUP($F11,raw_data_cargo!$1:$1048576,MATCH(L$1,raw_data_cargo!$1:$1,0),FALSE) | M11: =VLOOKUP($F11,raw_data_cargo!$1:$1048576,MATCH(M$1,raw_data_cargo!$1:$1,0),FALSE) | N11: =VLOOKUP($F11,raw_data_cargo!$1:$1048576,MATCH(N$1,raw_data_cargo!$1:$1,0),FALSE) | O11: =VLOOKUP($F11,raw_data_cargo!$1:$1048576,MATCH(O$1,raw_data_cargo!$1:$1,0),FALSE) | ... Q11: =VLOOKUP($F11,raw_data_cargo!$1:$1048576,MATCH(Q$1,raw_data_cargo!$1:$1,0),FALSE)
C12: Average Flight Distance(km) | D12: float0 | F12: 비행거리평균(km) | H12: =VLOOKUP($F12,raw_data_cargo!$1:$1048576,MATCH(H$1,raw_data_cargo!$1:$1,0),FALSE) | I12: =VLOOKUP($F12,raw_data_cargo!$1:$1048576,MATCH(I$1,raw_data_cargo!$1:$1,0),FALSE) | J12: =VLOOKUP($F12,raw_data_cargo!$1:$1048576,MATCH(J$1,raw_data_cargo!$1:$1,0),FALSE) | K12: =VLOOKUP($F12,raw_data_cargo!$1:$1048576,MATCH(K$1,raw_data_cargo!$1:$1,0),FALSE) | L12: =VLOOKUP($F12,raw_data_cargo!$1:$1048576,MATCH(L$1,raw_data_cargo!$1:$1,0),FALSE) | M12: =VLOOKUP($F12,raw_data_cargo!$1:$1048576,MATCH(M$1,raw_data_cargo!$1:$1,0),FALSE) | N12: =VLOOKUP($F12,raw_data_cargo!$1:$1048576,MATCH(N$1,raw_data_cargo!$1:$1,0),FALSE) | O12: =VLOOKUP($F12,raw_data_cargo!$1:$1048576,MATCH(O$1,raw_data_cargo!$1:$1,0),FALSE) | ... Q12: =VLOOKUP($F12,raw_data_cargo!$1:$1048576,MATCH(Q$1,raw_data_cargo!$1:$1,0),FALSE)
C13: Payload Per Aircraft | D13: float0 | F13: 대당유상탑재중량 | H13: =VLOOKUP($F13,raw_data_cargo!$1:$1048576,MATCH(H$1,raw_data_cargo!$1:$1,0),FALSE) | I13: =VLOOKUP($F13,raw_data_cargo!$1:$1048576,MATCH(I$1,raw_data_cargo!$1:$1,0),FALSE) | J13: =VLOOKUP($F13,raw_data_cargo!$1:$1048576,MATCH(J$1,raw_data_cargo!$1:$1,0),FALSE) | K13: =VLOOKUP($F13,raw_data_cargo!$1:$1048576,MATCH(K$1,raw_data_cargo!$1:$1,0),FALSE) | L13: =VLOOKUP($F13,raw_data_cargo!$1:$1048576,MATCH(L$1,raw_data_cargo!$1:$1,0),FALSE) | M13: =VLOOKUP($F13,raw_data_cargo!$1:$1048576,MATCH(M$1,raw_data_cargo!$1:$1,0),FALSE) | N13: =VLOOKUP($F13,raw_data_cargo!$1:$1048576,MATCH(N$1,raw_data_cargo!$1:$1,0),FALSE) | O13: =VLOOKUP($F13,raw_data_cargo!$1:$1048576,MATCH(O$1,raw_data_cargo!$1:$1,0),FALSE) | ... Q13: =VLOOKUP($F13,raw_data_cargo!$1:$1048576,MATCH(Q$1,raw_data_cargo!$1:$1,0),FALSE)
A14: Flight Class Index | B14: FleetMIx | C14: =C62&"FleetMix📝" | D14: percent1 | E14: O | F14: =C62&"혼합율" | G14: =IFERROR(SUMIF($H$73:$Q$73,"O",H14:Q14)/COUNTIFS($H$73:$Q$73,"O",H14:Q14,"<>0"),0) | H14: =VLOOKUP($F14,raw_data_cargo!$1:$1048576,MATCH(H$1,raw_data_cargo!$1:$1,0),FALSE) | I14: =VLOOKUP($F14,raw_data_cargo!$1:$1048576,MATCH(I$1,raw_data_cargo!$1:$1,0),FALSE) | J14: =VLOOKUP($F14,raw_data_cargo!$1:$1048576,MATCH(J$1,raw_data_cargo!$1:$1,0),FALSE) | K14: =VLOOKUP($F14,raw_data_cargo!$1:$1048576,MATCH(K$1,raw_data_cargo!$1:$1,0),FALSE) | L14: =VLOOKUP($F14,raw_data_cargo!$1:$1048576,MATCH(L$1,raw_data_cargo!$1:$1,0),FALSE) | M14: =VLOOKUP($F14,raw_data_cargo!$1:$1048576,MATCH(M$1,raw_data_cargo!$1:$1,0),FALSE) | N14: =VLOOKUP($F14,raw_data_cargo!$1:$1048576,MATCH(N$1,raw_data_cargo!$1:$1,0),FALSE) | O14: =VLOOKUP($F14,raw_data_cargo!$1:$1048576,MATCH(O$1,raw_data_cargo!$1:$1,0),FALSE) | ... Q14: =VLOOKUP($F14,raw_data_cargo!$1:$1048576,MATCH(Q$1,raw_data_cargo!$1:$1,0),FALSE) | R14: =G14 | S14: =R14 | T14: =S14 | U14: =T14 | V14: =U14 | W14: =V14 | X14: =W14 | Y14: =X14 | Z14: =Y14 | ... BA14: =AZ14
C15: =C63&"FleetMix📝" | D15: percent1 | E15: O | F15: =C63&"혼합율" | G15: =IFERROR(SUMIF($H$73:$Q$73,"O",H15:Q15)/COUNTIFS($H$73:$Q$73,"O",H15:Q15,"<>0"),0) | H15: =VLOOKUP($F15,raw_data_cargo!$1:$1048576,MATCH(H$1,raw_data_cargo!$1:$1,0),FALSE) | I15: =VLOOKUP($F15,raw_data_cargo!$1:$1048576,MATCH(I$1,raw_data_cargo!$1:$1,0),FALSE) | J15: =VLOOKUP($F15,raw_data_cargo!$1:$1048576,MATCH(J$1,raw_data_cargo!$1:$1,0),FALSE) | K15: =VLOOKUP($F15,raw_data_cargo!$1:$1048576,MATCH(K$1,raw_data_cargo!$1:$1,0),FALSE) | L15: =VLOOKUP($F15,raw_data_cargo!$1:$1048576,MATCH(L$1,raw_data_cargo!$1:$1,0),FALSE) | M15: =VLOOKUP($F15,raw_data_cargo!$1:$1048576,MATCH(M$1,raw_data_cargo!$1:$1,0),FALSE) | N15: =VLOOKUP($F15,raw_data_cargo!$1:$1048576,MATCH(N$1,raw_data_cargo!$1:$1,0),FALSE) | O15: =VLOOKUP($F15,raw_data_cargo!$1:$1048576,MATCH(O$1,raw_data_cargo!$1:$1,0),FALSE) | ... Q15: =VLOOKUP($F15,raw_data_cargo!$1:$1048576,MATCH(Q$1,raw_data_cargo!$1:$1,0),FALSE) | R15: =G15 | S15: =R15 | T15: =S15 | U15: =T15 | V15: =U15 | W15: =V15 | X15: =W15 | Y15: =X15 | Z15: =Y15 | ... BA15: =AZ15
C16: =C64&"FleetMix📝" | D16: percent1 | E16: O | F16: =C64&"혼합율" | G16: =IFERROR(SUMIF($H$73:$Q$73,"O",H16:Q16)/COUNTIFS($H$73:$Q$73,"O",H16:Q16,"<>0"),0) | H16: =VLOOKUP($F16,raw_data_cargo!$1:$1048576,MATCH(H$1,raw_data_cargo!$1:$1,0),FALSE) | I16: =VLOOKUP($F16,raw_data_cargo!$1:$1048576,MATCH(I$1,raw_data_cargo!$1:$1,0),FALSE) | J16: =VLOOKUP($F16,raw_data_cargo!$1:$1048576,MATCH(J$1,raw_data_cargo!$1:$1,0),FALSE) | K16: =VLOOKUP($F16,raw_data_cargo!$1:$1048576,MATCH(K$1,raw_data_cargo!$1:$1,0),FALSE) | L16: =VLOOKUP($F16,raw_data_cargo!$1:$1048576,MATCH(L$1,raw_data_cargo!$1:$1,0),FALSE) | M16: =VLOOKUP($F16,raw_data_cargo!$1:$1048576,MATCH(M$1,raw_data_cargo!$1:$1,0),FALSE) | N16: =VLOOKUP($F16,raw_data_cargo!$1:$1048576,MATCH(N$1,raw_data_cargo!$1:$1,0),FALSE) | O16: =VLOOKUP($F16,raw_data_cargo!$1:$1048576,MATCH(O$1,raw_data_cargo!$1:$1,0),FALSE) | ... Q16: =VLOOKUP($F16,raw_data_cargo!$1:$1048576,MATCH(Q$1,raw_data_cargo!$1:$1,0),FALSE) | R16: =G16 | S16: =R16 | T16: =S16 | U16: =T16 | V16: =U16 | W16: =V16 | X16: =W16 | Y16: =X16 | Z16: =Y16 | ... BA16: =AZ16
C17: =C65&"FleetMix📝" | D17: percent1 | E17: O | F17: =C65&"혼합율" | G17: =IFERROR(SUMIF($H$73:$Q$73,"O",H17:Q17)/COUNTIFS($H$73:$Q$73,"O",H17:Q17,"<>0"),0) | H17: =VLOOKUP($F17,raw_data_cargo!$1:$1048576,MATCH(H$1,raw_data_cargo!$1:$1,0),FALSE) | I17: =VLOOKUP($F17,raw_data_cargo!$1:$1048576,MATCH(I$1,raw_data_cargo!$1:$1,0),FALSE) | J17: =VLOOKUP($F17,raw_data_cargo!$1:$1048576,MATCH(J$1,raw_data_cargo!$1:$1,0),FALSE) | K17: =VLOOKUP($F17,raw_data_cargo!$1:$1048576,MATCH(K$1,raw_data_cargo!$1:$1,0),FALSE) | L17: =VLOOKUP($F17,raw_data_cargo!$1:$1048576,MATCH(L$1,raw_data_cargo!$1:$1,0),FALSE) | M17: =VLOOKUP($F17,raw_data_cargo!$1:$1048576,MATCH(M$1,raw_data_cargo!$1:$1,0),FALSE) | N17: =VLOOKUP($F17,raw_data_cargo!$1:$1048576,MATCH(N$1,raw_data_cargo!$1:$1,0),FALSE) | O17: =VLOOKUP($F17,raw_data_cargo!$1:$1048576,MATCH(O$1,raw_data_cargo!$1:$1,0),FALSE) | ... Q17: =VLOOKUP($F17,raw_data_cargo!$1:$1048576,MATCH(Q$1,raw_data_cargo!$1:$1,0),FALSE) | R17: =G17 | S17: =R17 | T17: =S17 | U17: =T17 | V17: =U17 | W17: =V17 | X17: =W17 | Y17: =X17 | Z17: =Y17 | ... BA17: =AZ17
B18: Movements by Class | C18: =C62&"Movements" | D18: float0 | F18: =C62&"운항횟수" | H18: =VLOOKUP($F18,raw_data_cargo!$1:$1048576,MATCH(H$1,raw_data_cargo!$1:$1,0),FALSE) | I18: =VLOOKUP($F18,raw_data_cargo!$1:$1048576,MATCH(I$1,raw_data_cargo!$1:$1,0),FALSE) | J18: =VLOOKUP($F18,raw_data_cargo!$1:$1048576,MATCH(J$1,raw_data_cargo!$1:$1,0),FALSE) | K18: =VLOOKUP($F18,raw_data_cargo!$1:$1048576,MATCH(K$1,raw_data_cargo!$1:$1,0),FALSE) | L18: =VLOOKUP($F18,raw_data_cargo!$1:$1048576,MATCH(L$1,raw_data_cargo!$1:$1,0),FALSE) | M18: =VLOOKUP($F18,raw_data_cargo!$1:$1048576,MATCH(M$1,raw_data_cargo!$1:$1,0),FALSE) | N18: =VLOOKUP($F18,raw_data_cargo!$1:$1048576,MATCH(N$1,raw_data_cargo!$1:$1,0),FALSE) | O18: =VLOOKUP($F18,raw_data_cargo!$1:$1048576,MATCH(O$1,raw_data_cargo!$1:$1,0),FALSE) | ... Q18: =VLOOKUP($F18,raw_data_cargo!$1:$1048576,MATCH(Q$1,raw_data_cargo!$1:$1,0),FALSE) | R18: =R3*R14 | S18: =S3*S14 | T18: =T3*T14 | U18: =U3*U14 | V18: =V3*V14 | W18: =W3*W14 | X18: =X3*X14 | Y18: =Y3*Y14 | ... BA18: =BA3*BA14
C19: =C63&"Movements" | D19: float0 | F19: =C63&"운항횟수" | H19: =VLOOKUP($F19,raw_data_cargo!$1:$1048576,MATCH(H$1,raw_data_cargo!$1:$1,0),FALSE) | I19: =VLOOKUP($F19,raw_data_cargo!$1:$1048576,MATCH(I$1,raw_data_cargo!$1:$1,0),FALSE) | J19: =VLOOKUP($F19,raw_data_cargo!$1:$1048576,MATCH(J$1,raw_data_cargo!$1:$1,0),FALSE) | K19: =VLOOKUP($F19,raw_data_cargo!$1:$1048576,MATCH(K$1,raw_data_cargo!$1:$1,0),FALSE) | L19: =VLOOKUP($F19,raw_data_cargo!$1:$1048576,MATCH(L$1,raw_data_cargo!$1:$1,0),FALSE) | M19: =VLOOKUP($F19,raw_data_cargo!$1:$1048576,MATCH(M$1,raw_data_cargo!$1:$1,0),FALSE) | N19: =VLOOKUP($F19,raw_data_cargo!$1:$1048576,MATCH(N$1,raw_data_cargo!$1:$1,0),FALSE) | O19: =VLOOKUP($F19,raw_data_cargo!$1:$1048576,MATCH(O$1,raw_data_cargo!$1:$1,0),FALSE) | ... Q19: =VLOOKUP($F19,raw_data_cargo!$1:$1048576,MATCH(Q$1,raw_data_cargo!$1:$1,0),FALSE) | R19: =R3*R15 | S19: =S3*S15 | T19: =T3*T15 | U19: =U3*U15 | V19: =V3*V15 | W19: =W3*W15 | X19: =X3*X15 | Y19: =Y3*Y15 | ... BA19: =BA3*BA15
C20: =C64&"Movements" | D20: float0 | F20: =C64&"운항횟수" | H20: =VLOOKUP($F20,raw_data_cargo!$1:$1048576,MATCH(H$1,raw_data_cargo!$1:$1,0),FALSE) | I20: =VLOOKUP($F20,raw_data_cargo!$1:$1048576,MATCH(I$1,raw_data_cargo!$1:$1,0),FALSE) | J20: =VLOOKUP($F20,raw_data_cargo!$1:$1048576,MATCH(J$1,raw_data_cargo!$1:$1,0),FALSE) | K20: =VLOOKUP($F20,raw_data_cargo!$1:$1048576,MATCH(K$1,raw_data_cargo!$1:$1,0),FALSE) | L20: =VLOOKUP($F20,raw_data_cargo!$1:$1048576,MATCH(L$1,raw_data_cargo!$1:$1,0),FALSE) | M20: =VLOOKUP($F20,raw_data_cargo!$1:$1048576,MATCH(M$1,raw_data_cargo!$1:$1,0),FALSE) | N20: =VLOOKUP($F20,raw_data_cargo!$1:$1048576,MATCH(N$1,raw_data_cargo!$1:$1,0),FALSE) | O20: =VLOOKUP($F20,raw_data_cargo!$1:$1048576,MATCH(O$1,raw_data_cargo!$1:$1,0),FALSE) | ... Q20: =VLOOKUP($F20,raw_data_cargo!$1:$1048576,MATCH(Q$1,raw_data_cargo!$1:$1,0),FALSE) | R20: =R3*R16 | S20: =S3*S16 | T20: =T3*T16 | U20: =U3*U16 | V20: =V3*V16 | W20: =W3*W16 | X20: =X3*X16 | Y20: =Y3*Y16 | ... BA20: =BA3*BA16
C21: =C65&"Movements" | D21: float0 | F21: =C65&"운항횟수" | H21: =VLOOKUP($F21,raw_data_cargo!$1:$1048576,MATCH(H$1,raw_data_cargo!$1:$1,0),FALSE) | I21: =VLOOKUP($F21,raw_data_cargo!$1:$1048576,MATCH(I$1,raw_data_cargo!$1:$1,0),FALSE) | J21: =VLOOKUP($F21,raw_data_cargo!$1:$1048576,MATCH(J$1,raw_data_cargo!$1:$1,0),FALSE) | K21: =VLOOKUP($F21,raw_data_cargo!$1:$1048576,MATCH(K$1,raw_data_cargo!$1:$1,0),FALSE) | L21: =VLOOKUP($F21,raw_data_cargo!$1:$1048576,MATCH(L$1,raw_data_cargo!$1:$1,0),FALSE) | M21: =VLOOKUP($F21,raw_data_cargo!$1:$1048576,MATCH(M$1,raw_data_cargo!$1:$1,0),FALSE) | N21: =VLOOKUP($F21,raw_data_cargo!$1:$1048576,MATCH(N$1,raw_data_cargo!$1:$1,0),FALSE) | O21: =VLOOKUP($F21,raw_data_cargo!$1:$1048576,MATCH(O$1,raw_data_cargo!$1:$1,0),FALSE) | ... Q21: =VLOOKUP($F21,raw_data_cargo!$1:$1048576,MATCH(Q$1,raw_data_cargo!$1:$1,0),FALSE) | R21: =R3*R17 | S21: =S3*S17 | T21: =T3*T17 | U21: =U3*U17 | V21: =V3*V17 | W21: =W3*W17 | X21: =X3*X17 | Y21: =Y3*Y17 | ... BA21: =BA3*BA17
B22: MTOW by Class | C22: =C62&"MTOW" | D22: float0 | F22: =C62&"대당최대이륙중량" | G22: =IFERROR(SUMIF($H$83:$Q$83,"O",H22:Q22)/COUNTIFS($H$83:$Q$83,"O",H22:Q22,"<>0"),0) | H22: =VLOOKUP($F22,raw_data_cargo!$1:$1048576,MATCH(H$1,raw_data_cargo!$1:$1,0),FALSE) | I22: =VLOOKUP($F22,raw_data_cargo!$1:$1048576,MATCH(I$1,raw_data_cargo!$1:$1,0),FALSE) | J22: =VLOOKUP($F22,raw_data_cargo!$1:$1048576,MATCH(J$1,raw_data_cargo!$1:$1,0),FALSE) | K22: =VLOOKUP($F22,raw_data_cargo!$1:$1048576,MATCH(K$1,raw_data_cargo!$1:$1,0),FALSE) | L22: =VLOOKUP($F22,raw_data_cargo!$1:$1048576,MATCH(L$1,raw_data_cargo!$1:$1,0),FALSE) | M22: =VLOOKUP($F22,raw_data_cargo!$1:$1048576,MATCH(M$1,raw_data_cargo!$1:$1,0),FALSE) | N22: =VLOOKUP($F22,raw_data_cargo!$1:$1048576,MATCH(N$1,raw_data_cargo!$1:$1,0),FALSE) | O22: =VLOOKUP($F22,raw_data_cargo!$1:$1048576,MATCH(O$1,raw_data_cargo!$1:$1,0),FALSE) | ... Q22: =VLOOKUP($F22,raw_data_cargo!$1:$1048576,MATCH(Q$1,raw_data_cargo!$1:$1,0),FALSE) | R22: =G22 | S22: =R22 | T22: =S22 | U22: =T22 | V22: =U22 | W22: =V22 | X22: =W22 | Y22: =X22 | Z22: =Y22 | ... BA22: =AZ22
C23: =C63&"MTOW" | D23: float0 | F23: =C63&"대당최대이륙중량" | G23: =IFERROR(SUMIF($H$83:$Q$83,"O",H23:Q23)/COUNTIFS($H$83:$Q$83,"O",H23:Q23,"<>0"),0) | H23: =VLOOKUP($F23,raw_data_cargo!$1:$1048576,MATCH(H$1,raw_data_cargo!$1:$1,0),FALSE) | I23: =VLOOKUP($F23,raw_data_cargo!$1:$1048576,MATCH(I$1,raw_data_cargo!$1:$1,0),FALSE) | J23: =VLOOKUP($F23,raw_data_cargo!$1:$1048576,MATCH(J$1,raw_data_cargo!$1:$1,0),FALSE) | K23: =VLOOKUP($F23,raw_data_cargo!$1:$1048576,MATCH(K$1,raw_data_cargo!$1:$1,0),FALSE) | L23: =VLOOKUP($F23,raw_data_cargo!$1:$1048576,MATCH(L$1,raw_data_cargo!$1:$1,0),FALSE) | M23: =VLOOKUP($F23,raw_data_cargo!$1:$1048576,MATCH(M$1,raw_data_cargo!$1:$1,0),FALSE) | N23: =VLOOKUP($F23,raw_data_cargo!$1:$1048576,MATCH(N$1,raw_data_cargo!$1:$1,0),FALSE) | O23: =VLOOKUP($F23,raw_data_cargo!$1:$1048576,MATCH(O$1,raw_data_cargo!$1:$1,0),FALSE) | ... Q23: =VLOOKUP($F23,raw_data_cargo!$1:$1048576,MATCH(Q$1,raw_data_cargo!$1:$1,0),FALSE) | R23: =G23 | S23: =R23 | T23: =S23 | U23: =T23 | V23: =U23 | W23: =V23 | X23: =W23 | Y23: =X23 | Z23: =Y23 | ... BA23: =AZ23
C24: =C64&"MTOW" | D24: float0 | F24: =C64&"대당최대이륙중량" | G24: =IFERROR(SUMIF($H$83:$Q$83,"O",H24:Q24)/COUNTIFS($H$83:$Q$83,"O",H24:Q24,"<>0"),0) | H24: =VLOOKUP($F24,raw_data_cargo!$1:$1048576,MATCH(H$1,raw_data_cargo!$1:$1,0),FALSE) | I24: =VLOOKUP($F24,raw_data_cargo!$1:$1048576,MATCH(I$1,raw_data_cargo!$1:$1,0),FALSE) | J24: =VLOOKUP($F24,raw_data_cargo!$1:$1048576,MATCH(J$1,raw_data_cargo!$1:$1,0),FALSE) | K24: =VLOOKUP($F24,raw_data_cargo!$1:$1048576,MATCH(K$1,raw_data_cargo!$1:$1,0),FALSE) | L24: =VLOOKUP($F24,raw_data_cargo!$1:$1048576,MATCH(L$1,raw_data_cargo!$1:$1,0),FALSE) | M24: =VLOOKUP($F24,raw_data_cargo!$1:$1048576,MATCH(M$1,raw_data_cargo!$1:$1,0),FALSE) | N24: =VLOOKUP($F24,raw_data_cargo!$1:$1048576,MATCH(N$1,raw_data_cargo!$1:$1,0),FALSE) | O24: =VLOOKUP($F24,raw_data_cargo!$1:$1048576,MATCH(O$1,raw_data_cargo!$1:$1,0),FALSE) | ... Q24: =VLOOKUP($F24,raw_data_cargo!$1:$1048576,MATCH(Q$1,raw_data_cargo!$1:$1,0),FALSE) | R24: =G24 | S24: =R24 | T24: =S24 | U24: =T24 | V24: =U24 | W24: =V24 | X24: =W24 | Y24: =X24 | Z24: =Y24 | ... BA24: =AZ24
C25: =C65&"MTOW" | D25: float0 | F25: =C65&"대당최대이륙중량" | G25: =IFERROR(SUMIF($H$83:$Q$83,"O",H25:Q25)/COUNTIFS($H$83:$Q$83,"O",H25:Q25,"<>0"),0) | H25: =VLOOKUP($F25,raw_data_cargo!$1:$1048576,MATCH(H$1,raw_data_cargo!$1:$1,0),FALSE) | I25: =VLOOKUP($F25,raw_data_cargo!$1:$1048576,MATCH(I$1,raw_data_cargo!$1:$1,0),FALSE) | J25: =VLOOKUP($F25,raw_data_cargo!$1:$1048576,MATCH(J$1,raw_data_cargo!$1:$1,0),FALSE) | K25: =VLOOKUP($F25,raw_data_cargo!$1:$1048576,MATCH(K$1,raw_data_cargo!$1:$1,0),FALSE) | L25: =VLOOKUP($F25,raw_data_cargo!$1:$1048576,MATCH(L$1,raw_data_cargo!$1:$1,0),FALSE) | M25: =VLOOKUP($F25,raw_data_cargo!$1:$1048576,MATCH(M$1,raw_data_cargo!$1:$1,0),FALSE) | N25: =VLOOKUP($F25,raw_data_cargo!$1:$1048576,MATCH(N$1,raw_data_cargo!$1:$1,0),FALSE) | O25: =VLOOKUP($F25,raw_data_cargo!$1:$1048576,MATCH(O$1,raw_data_cargo!$1:$1,0),FALSE) | ... Q25: =VLOOKUP($F25,raw_data_cargo!$1:$1048576,MATCH(Q$1,raw_data_cargo!$1:$1,0),FALSE) | R25: =G25 | S25: =R25 | T25: =S25 | U25: =T25 | V25: =U25 | W25: =V25 | X25: =W25 | Y25: =X25 | Z25: =Y25 | ... BA25: =AZ25
B26: Standing Time by Class | C26: =C62&"Average PeakTime TurnAround Standing Time📝" | D26: float0 | E26: O | F26: =C62&"피크시간 턴어라운드편 평균주기시간(분)" | G26: =IFERROR(SUMIF($H$84:$Q$84,"O",H26:Q26)/COUNTIFS($H$84:$Q$84,"O",H26:Q26,"<>0"),0) | H26: =VLOOKUP($F26,raw_data_cargo!$1:$1048576,MATCH(H$1,raw_data_cargo!$1:$1,0),FALSE) | I26: =VLOOKUP($F26,raw_data_cargo!$1:$1048576,MATCH(I$1,raw_data_cargo!$1:$1,0),FALSE) | J26: =VLOOKUP($F26,raw_data_cargo!$1:$1048576,MATCH(J$1,raw_data_cargo!$1:$1,0),FALSE) | K26: =VLOOKUP($F26,raw_data_cargo!$1:$1048576,MATCH(K$1,raw_data_cargo!$1:$1,0),FALSE) | L26: =VLOOKUP($F26,raw_data_cargo!$1:$1048576,MATCH(L$1,raw_data_cargo!$1:$1,0),FALSE) | M26: =VLOOKUP($F26,raw_data_cargo!$1:$1048576,MATCH(M$1,raw_data_cargo!$1:$1,0),FALSE) | N26: =VLOOKUP($F26,raw_data_cargo!$1:$1048576,MATCH(N$1,raw_data_cargo!$1:$1,0),FALSE) | O26: =VLOOKUP($F26,raw_data_cargo!$1:$1048576,MATCH(O$1,raw_data_cargo!$1:$1,0),FALSE) | ... Q26: =VLOOKUP($F26,raw_data_cargo!$1:$1048576,MATCH(Q$1,raw_data_cargo!$1:$1,0),FALSE) | R26: =G26 | S26: =R26 | T26: =S26 | U26: =T26 | V26: =U26 | W26: =V26 | X26: =W26 | Y26: =X26 | Z26: =Y26 | ... BA26: =AZ26
C27: =C63&"Average PeakTime TurnAround Standing Time📝" | D27: float0 | E27: O | F27: =C63&"피크시간 턴어라운드편 평균주기시간(분)" | G27: =IFERROR(SUMIF($H$84:$Q$84,"O",H27:Q27)/COUNTIFS($H$84:$Q$84,"O",H27:Q27,"<>0"),0) | H27: =VLOOKUP($F27,raw_data_cargo!$1:$1048576,MATCH(H$1,raw_data_cargo!$1:$1,0),FALSE) | I27: =VLOOKUP($F27,raw_data_cargo!$1:$1048576,MATCH(I$1,raw_data_cargo!$1:$1,0),FALSE) | J27: =VLOOKUP($F27,raw_data_cargo!$1:$1048576,MATCH(J$1,raw_data_cargo!$1:$1,0),FALSE) | K27: =VLOOKUP($F27,raw_data_cargo!$1:$1048576,MATCH(K$1,raw_data_cargo!$1:$1,0),FALSE) | L27: =VLOOKUP($F27,raw_data_cargo!$1:$1048576,MATCH(L$1,raw_data_cargo!$1:$1,0),FALSE) | M27: =VLOOKUP($F27,raw_data_cargo!$1:$1048576,MATCH(M$1,raw_data_cargo!$1:$1,0),FALSE) | N27: =VLOOKUP($F27,raw_data_cargo!$1:$1048576,MATCH(N$1,raw_data_cargo!$1:$1,0),FALSE) | O27: =VLOOKUP($F27,raw_data_cargo!$1:$1048576,MATCH(O$1,raw_data_cargo!$1:$1,0),FALSE) | ... Q27: =VLOOKUP($F27,raw_data_cargo!$1:$1048576,MATCH(Q$1,raw_data_cargo!$1:$1,0),FALSE) | R27: =G27 | S27: =R27 | T27: =S27 | U27: =T27 | V27: =U27 | W27: =V27 | X27: =W27 | Y27: =X27 | Z27: =Y27 | ... BA27: =AZ27
C28: =C64&"Average PeakTime TurnAround Standing Time📝" | D28: float0 | E28: O | F28: =C64&"피크시간 턴어라운드편 평균주기시간(분)" | G28: =IFERROR(SUMIF($H$84:$Q$84,"O",H28:Q28)/COUNTIFS($H$84:$Q$84,"O",H28:Q28,"<>0"),0) | H28: =VLOOKUP($F28,raw_data_cargo!$1:$1048576,MATCH(H$1,raw_data_cargo!$1:$1,0),FALSE) | I28: =VLOOKUP($F28,raw_data_cargo!$1:$1048576,MATCH(I$1,raw_data_cargo!$1:$1,0),FALSE) | J28: =VLOOKUP($F28,raw_data_cargo!$1:$1048576,MATCH(J$1,raw_data_cargo!$1:$1,0),FALSE) | K28: =VLOOKUP($F28,raw_data_cargo!$1:$1048576,MATCH(K$1,raw_data_cargo!$1:$1,0),FALSE) | L28: =VLOOKUP($F28,raw_data_cargo!$1:$1048576,MATCH(L$1,raw_data_cargo!$1:$1,0),FALSE) | M28: =VLOOKUP($F28,raw_data_cargo!$1:$1048576,MATCH(M$1,raw_data_cargo!$1:$1,0),FALSE) | N28: =VLOOKUP($F28,raw_data_cargo!$1:$1048576,MATCH(N$1,raw_data_cargo!$1:$1,0),FALSE) | O28: =VLOOKUP($F28,raw_data_cargo!$1:$1048576,MATCH(O$1,raw_data_cargo!$1:$1,0),FALSE) | ... Q28: =VLOOKUP($F28,raw_data_cargo!$1:$1048576,MATCH(Q$1,raw_data_cargo!$1:$1,0),FALSE) | R28: =G28 | S28: =R28 | T28: =S28 | U28: =T28 | V28: =U28 | W28: =V28 | X28: =W28 | Y28: =X28 | Z28: =Y28 | ... BA28: =AZ28
C29: =C65&"Average PeakTime TurnAround Standing Time📝" | D29: float0 | E29: O | F29: =C65&"피크시간 턴어라운드편 평균주기시간(분)" | G29: =IFERROR(SUMIF($H$84:$Q$84,"O",H29:Q29)/COUNTIFS($H$84:$Q$84,"O",H29:Q29,"<>0"),0) | H29: =VLOOKUP($F29,raw_data_cargo!$1:$1048576,MATCH(H$1,raw_data_cargo!$1:$1,0),FALSE) | I29: =VLOOKUP($F29,raw_data_cargo!$1:$1048576,MATCH(I$1,raw_data_cargo!$1:$1,0),FALSE) | J29: =VLOOKUP($F29,raw_data_cargo!$1:$1048576,MATCH(J$1,raw_data_cargo!$1:$1,0),FALSE) | K29: =VLOOKUP($F29,raw_data_cargo!$1:$1048576,MATCH(K$1,raw_data_cargo!$1:$1,0),FALSE) | L29: =VLOOKUP($F29,raw_data_cargo!$1:$1048576,MATCH(L$1,raw_data_cargo!$1:$1,0),FALSE) | M29: =VLOOKUP($F29,raw_data_cargo!$1:$1048576,MATCH(M$1,raw_data_cargo!$1:$1,0),FALSE) | N29: =VLOOKUP($F29,raw_data_cargo!$1:$1048576,MATCH(N$1,raw_data_cargo!$1:$1,0),FALSE) | O29: =VLOOKUP($F29,raw_data_cargo!$1:$1048576,MATCH(O$1,raw_data_cargo!$1:$1,0),FALSE) | ... Q29: =VLOOKUP($F29,raw_data_cargo!$1:$1048576,MATCH(Q$1,raw_data_cargo!$1:$1,0),FALSE) | R29: =G29 | S29: =R29 | T29: =S29 | U29: =T29 | V29: =U29 | W29: =V29 | X29: =W29 | Y29: =X29 | Z29: =Y29 | ... BA29: =AZ29
B30: Standing(Total) Time by Class | C30: =C62&"Average Peak Standing Time📝" | D30: float0 | E30: O | F30: =C62&"(오버나잇, 소산 포함) 피크시간 평균주기시간(분)" | G30: =IFERROR(SUMIF($H$84:$Q$84,"O",H30:Q30)/COUNTIFS($H$84:$Q$84,"O",H30:Q30,"<>0"),0) | H30: =VLOOKUP($F30,raw_data_cargo!$1:$1048576,MATCH(H$1,raw_data_cargo!$1:$1,0),FALSE) | I30: =VLOOKUP($F30,raw_data_cargo!$1:$1048576,MATCH(I$1,raw_data_cargo!$1:$1,0),FALSE) | J30: =VLOOKUP($F30,raw_data_cargo!$1:$1048576,MATCH(J$1,raw_data_cargo!$1:$1,0),FALSE) | K30: =VLOOKUP($F30,raw_data_cargo!$1:$1048576,MATCH(K$1,raw_data_cargo!$1:$1,0),FALSE) | L30: =VLOOKUP($F30,raw_data_cargo!$1:$1048576,MATCH(L$1,raw_data_cargo!$1:$1,0),FALSE) | M30: =VLOOKUP($F30,raw_data_cargo!$1:$1048576,MATCH(M$1,raw_data_cargo!$1:$1,0),FALSE) | N30: =VLOOKUP($F30,raw_data_cargo!$1:$1048576,MATCH(N$1,raw_data_cargo!$1:$1,0),FALSE) | O30: =VLOOKUP($F30,raw_data_cargo!$1:$1048576,MATCH(O$1,raw_data_cargo!$1:$1,0),FALSE) | ... Q30: =VLOOKUP($F30,raw_data_cargo!$1:$1048576,MATCH(Q$1,raw_data_cargo!$1:$1,0),FALSE) | R30: =G30 | S30: =R30 | T30: =S30 | U30: =T30 | V30: =U30 | W30: =V30 | X30: =W30 | Y30: =X30 | Z30: =Y30 | ... BA30: =AZ30
C31: =C63&"Average Peak Standing Time📝" | D31: float0 | E31: O | F31: =C63&"(오버나잇, 소산 포함) 피크시간 평균주기시간(분)" | G31: =IFERROR(SUMIF($H$84:$Q$84,"O",H31:Q31)/COUNTIFS($H$84:$Q$84,"O",H31:Q31,"<>0"),0) | H31: =VLOOKUP($F31,raw_data_cargo!$1:$1048576,MATCH(H$1,raw_data_cargo!$1:$1,0),FALSE) | I31: =VLOOKUP($F31,raw_data_cargo!$1:$1048576,MATCH(I$1,raw_data_cargo!$1:$1,0),FALSE) | J31: =VLOOKUP($F31,raw_data_cargo!$1:$1048576,MATCH(J$1,raw_data_cargo!$1:$1,0),FALSE) | K31: =VLOOKUP($F31,raw_data_cargo!$1:$1048576,MATCH(K$1,raw_data_cargo!$1:$1,0),FALSE) | L31: =VLOOKUP($F31,raw_data_cargo!$1:$1048576,MATCH(L$1,raw_data_cargo!$1:$1,0),FALSE) | M31: =VLOOKUP($F31,raw_data_cargo!$1:$1048576,MATCH(M$1,raw_data_cargo!$1:$1,0),FALSE) | N31: =VLOOKUP($F31,raw_data_cargo!$1:$1048576,MATCH(N$1,raw_data_cargo!$1:$1,0),FALSE) | O31: =VLOOKUP($F31,raw_data_cargo!$1:$1048576,MATCH(O$1,raw_data_cargo!$1:$1,0),FALSE) | ... Q31: =VLOOKUP($F31,raw_data_cargo!$1:$1048576,MATCH(Q$1,raw_data_cargo!$1:$1,0),FALSE) | R31: =G31 | S31: =R31 | T31: =S31 | U31: =T31 | V31: =U31 | W31: =V31 | X31: =W31 | Y31: =X31 | Z31: =Y31 | ... BA31: =AZ31
C32: =C64&"Average Peak Standing Time📝" | D32: float0 | E32: O | F32: =C64&"(오버나잇, 소산 포함) 피크시간 평균주기시간(분)" | G32: =IFERROR(SUMIF($H$84:$Q$84,"O",H32:Q32)/COUNTIFS($H$84:$Q$84,"O",H32:Q32,"<>0"),0) | H32: =VLOOKUP($F32,raw_data_cargo!$1:$1048576,MATCH(H$1,raw_data_cargo!$1:$1,0),FALSE) | I32: =VLOOKUP($F32,raw_data_cargo!$1:$1048576,MATCH(I$1,raw_data_cargo!$1:$1,0),FALSE) | J32: =VLOOKUP($F32,raw_data_cargo!$1:$1048576,MATCH(J$1,raw_data_cargo!$1:$1,0),FALSE) | K32: =VLOOKUP($F32,raw_data_cargo!$1:$1048576,MATCH(K$1,raw_data_cargo!$1:$1,0),FALSE) | L32: =VLOOKUP($F32,raw_data_cargo!$1:$1048576,MATCH(L$1,raw_data_cargo!$1:$1,0),FALSE) | M32: =VLOOKUP($F32,raw_data_cargo!$1:$1048576,MATCH(M$1,raw_data_cargo!$1:$1,0),FALSE) | N32: =VLOOKUP($F32,raw_data_cargo!$1:$1048576,MATCH(N$1,raw_data_cargo!$1:$1,0),FALSE) | O32: =VLOOKUP($F32,raw_data_cargo!$1:$1048576,MATCH(O$1,raw_data_cargo!$1:$1,0),FALSE) | ... Q32: =VLOOKUP($F32,raw_data_cargo!$1:$1048576,MATCH(Q$1,raw_data_cargo!$1:$1,0),FALSE) | R32: =G32 | S32: =R32 | T32: =S32 | U32: =T32 | V32: =U32 | W32: =V32 | X32: =W32 | Y32: =X32 | Z32: =Y32 | ... BA32: =AZ32
C33: =C65&"Average Peak Standing Time📝" | D33: float0 | E33: O | F33: =C65&"(오버나잇, 소산 포함) 피크시간 평균주기시간(분)" | G33: =IFERROR(SUMIF($H$84:$Q$84,"O",H33:Q33)/COUNTIFS($H$84:$Q$84,"O",H33:Q33,"<>0"),0) | H33: =VLOOKUP($F33,raw_data_cargo!$1:$1048576,MATCH(H$1,raw_data_cargo!$1:$1,0),FALSE) | I33: =VLOOKUP($F33,raw_data_cargo!$1:$1048576,MATCH(I$1,raw_data_cargo!$1:$1,0),FALSE) | J33: =VLOOKUP($F33,raw_data_cargo!$1:$1048576,MATCH(J$1,raw_data_cargo!$1:$1,0),FALSE) | K33: =VLOOKUP($F33,raw_data_cargo!$1:$1048576,MATCH(K$1,raw_data_cargo!$1:$1,0),FALSE) | L33: =VLOOKUP($F33,raw_data_cargo!$1:$1048576,MATCH(L$1,raw_data_cargo!$1:$1,0),FALSE) | M33: =VLOOKUP($F33,raw_data_cargo!$1:$1048576,MATCH(M$1,raw_data_cargo!$1:$1,0),FALSE) | N33: =VLOOKUP($F33,raw_data_cargo!$1:$1048576,MATCH(N$1,raw_data_cargo!$1:$1,0),FALSE) | O33: =VLOOKUP($F33,raw_data_cargo!$1:$1048576,MATCH(O$1,raw_data_cargo!$1:$1,0),FALSE) | ... Q33: =VLOOKUP($F33,raw_data_cargo!$1:$1048576,MATCH(Q$1,raw_data_cargo!$1:$1,0),FALSE) | R33: =G33 | S33: =R33 | T33: =S33 | U33: =T33 | V33: =U33 | W33: =V33 | X33: =W33 | Y33: =X33 | Z33: =Y33 | ... BA33: =AZ33
A37: top | B37: mid | C37: low | D37: decimal | E37: changeable | F37: 변수설명 | G37: Ref_Index | H37: =I37-1 | I37: =J37-1 | J37: =K37-1 | K37: =L37-1 | L37: =M37-1 | M37: =N37-1 | N37: =O37-1 | O37: =P37-1 | P37: =Q37-1 | Q37: =ref!B4 | R37: =Q37+1 | S37: =R37+1 | T37: =S37+1 | U37: =T37+1 | V37: =U37+1 | W37: =V37+1 | X37: =W37+1 | Y37: =X37+1 | ... BA37: =AZ37+1
A38: Airside(ADPM) | B38: Cargo Flight Movements(ADPM) | C38: Movement PHF(%)(ADPM) | D38: percent4 | F38: ADPM/movement/all/PHF | H38: =VLOOKUP($F38,raw_data_cargo!$1:$1048576,MATCH(H$1,raw_data_cargo!$1:$1,0),FALSE) | I38: =VLOOKUP($F38,raw_data_cargo!$1:$1048576,MATCH(I$1,raw_data_cargo!$1:$1,0),FALSE) | J38: =VLOOKUP($F38,raw_data_cargo!$1:$1048576,MATCH(J$1,raw_data_cargo!$1:$1,0),FALSE) | K38: =VLOOKUP($F38,raw_data_cargo!$1:$1048576,MATCH(K$1,raw_data_cargo!$1:$1,0),FALSE) | L38: =VLOOKUP($F38,raw_data_cargo!$1:$1048576,MATCH(L$1,raw_data_cargo!$1:$1,0),FALSE) | M38: =VLOOKUP($F38,raw_data_cargo!$1:$1048576,MATCH(M$1,raw_data_cargo!$1:$1,0),FALSE) | N38: =VLOOKUP($F38,raw_data_cargo!$1:$1048576,MATCH(N$1,raw_data_cargo!$1:$1,0),FALSE) | O38: =VLOOKUP($F38,raw_data_cargo!$1:$1048576,MATCH(O$1,raw_data_cargo!$1:$1,0),FALSE) | ... Q38: =VLOOKUP($F38,raw_data_cargo!$1:$1048576,MATCH(Q$1,raw_data_cargo!$1:$1,0),FALSE) | R38: =0.0021*R3^(-0.183)*$G$42 | S38: =0.0021*S3^(-0.183)*$G$42 | T38: =0.0021*T3^(-0.183)*$G$42 | U38: =0.0021*U3^(-0.183)*$G$42 | V38: =0.0021*V3^(-0.183)*$G$42 | W38: =0.0021*W3^(-0.183)*$G$42 | X38: =0.0021*X3^(-0.183)*$G$42 | Y38: =0.0021*Y3^(-0.183)*$G$42 | ... BA38: =0.0021*BA3^(-0.183)*$G$42
C39: - Movement H Factor(ADPM) | D39: float1 | F39: ADPM/movement/all/H팩터 | H39: =VLOOKUP($F39,raw_data_cargo!$1:$1048576,MATCH(H$1,raw_data_cargo!$1:$1,0),FALSE) | I39: =VLOOKUP($F39,raw_data_cargo!$1:$1048576,MATCH(I$1,raw_data_cargo!$1:$1,0),FALSE) | J39: =VLOOKUP($F39,raw_data_cargo!$1:$1048576,MATCH(J$1,raw_data_cargo!$1:$1,0),FALSE) | K39: =VLOOKUP($F39,raw_data_cargo!$1:$1048576,MATCH(K$1,raw_data_cargo!$1:$1,0),FALSE) | L39: =VLOOKUP($F39,raw_data_cargo!$1:$1048576,MATCH(L$1,raw_data_cargo!$1:$1,0),FALSE) | M39: =VLOOKUP($F39,raw_data_cargo!$1:$1048576,MATCH(M$1,raw_data_cargo!$1:$1,0),FALSE) | N39: =VLOOKUP($F39,raw_data_cargo!$1:$1048576,MATCH(N$1,raw_data_cargo!$1:$1,0),FALSE) | O39: =VLOOKUP($F39,raw_data_cargo!$1:$1048576,MATCH(O$1,raw_data_cargo!$1:$1,0),FALSE) | ... Q39: =VLOOKUP($F39,raw_data_cargo!$1:$1048576,MATCH(Q$1,raw_data_cargo!$1:$1,0),FALSE) | R39: =1/R38/R40 | S39: =1/S38/S40 | T39: =1/T38/T40 | U39: =1/U38/U40 | V39: =1/V38/V40 | W39: =1/W38/W40 | X39: =1/X38/X40 | Y39: =1/Y38/Y40 | ... BA39: =1/BA38/BA40
C40: - Movement D Factor(ADPM) | D40: float1 | F40: ADPM/movement/all/D팩터 | G40: =SUMIF($H$79:$Q$79,"O",H40:Q40)/COUNTIFS($H$79:$Q$79,"O",H40:Q40,"<>0") | H40: =VLOOKUP($F40,raw_data_cargo!$1:$1048576,MATCH(H$1,raw_data_cargo!$1:$1,0),FALSE) | I40: =VLOOKUP($F40,raw_data_cargo!$1:$1048576,MATCH(I$1,raw_data_cargo!$1:$1,0),FALSE) | J40: =VLOOKUP($F40,raw_data_cargo!$1:$1048576,MATCH(J$1,raw_data_cargo!$1:$1,0),FALSE) | K40: =VLOOKUP($F40,raw_data_cargo!$1:$1048576,MATCH(K$1,raw_data_cargo!$1:$1,0),FALSE) | L40: =VLOOKUP($F40,raw_data_cargo!$1:$1048576,MATCH(L$1,raw_data_cargo!$1:$1,0),FALSE) | M40: =VLOOKUP($F40,raw_data_cargo!$1:$1048576,MATCH(M$1,raw_data_cargo!$1:$1,0),FALSE) | N40: =VLOOKUP($F40,raw_data_cargo!$1:$1048576,MATCH(N$1,raw_data_cargo!$1:$1,0),FALSE) | O40: =VLOOKUP($F40,raw_data_cargo!$1:$1048576,MATCH(O$1,raw_data_cargo!$1:$1,0),FALSE) | ... Q40: =VLOOKUP($F40,raw_data_cargo!$1:$1048576,MATCH(Q$1,raw_data_cargo!$1:$1,0),FALSE) | R40: =$G$40 | S40: =$G$40 | T40: =$G$40 | U40: =$G$40 | V40: =$G$40 | W40: =$G$40 | X40: =$G$40 | Y40: =$G$40 | ... BA40: =$G$40
C41: Movement PHF(%) Model(ADPM) | D41: percent4 | F41: 모형 | H41: =0.0021*H3^(-0.183) | I41: =0.0021*I3^(-0.183) | J41: =0.0021*J3^(-0.183) | K41: =0.0021*K3^(-0.183) | L41: =0.0021*L3^(-0.183) | M41: =0.0021*M3^(-0.183) | N41: =0.0021*N3^(-0.183) | O41: =0.0021*O3^(-0.183) | ... Q41: =0.0021*Q3^(-0.183)
C42: Movement Model PHF / Movement PHF(ADPM) | D42: percent1 | F42: 모형PHF / 실제 PHF | G42: =SUMIF($H$78:$Q$78,"O",H42:Q42)/COUNTIFS($H$78:$Q$78,"O",H42:Q42,"<>0") | H42: =H38/H41 | I42: =I38/I41 | J42: =J38/J41 | K42: =K38/K41 | L42: =L38/L41 | M42: =M38/M41 | N42: =N38/N41 | O42: =O38/O41 | ... Q42: =Q38/Q41
C43: Peak Hour Movements(ADPM) | D43: float0 | F43: ADPM/movement/all/첨두시 | H43: =VLOOKUP($F43,raw_data_cargo!$1:$1048576,MATCH(H$1,raw_data_cargo!$1:$1,0),FALSE) | I43: =VLOOKUP($F43,raw_data_cargo!$1:$1048576,MATCH(I$1,raw_data_cargo!$1:$1,0),FALSE) | J43: =VLOOKUP($F43,raw_data_cargo!$1:$1048576,MATCH(J$1,raw_data_cargo!$1:$1,0),FALSE) | K43: =VLOOKUP($F43,raw_data_cargo!$1:$1048576,MATCH(K$1,raw_data_cargo!$1:$1,0),FALSE) | L43: =VLOOKUP($F43,raw_data_cargo!$1:$1048576,MATCH(L$1,raw_data_cargo!$1:$1,0),FALSE) | M43: =VLOOKUP($F43,raw_data_cargo!$1:$1048576,MATCH(M$1,raw_data_cargo!$1:$1,0),FALSE) | N43: =VLOOKUP($F43,raw_data_cargo!$1:$1048576,MATCH(N$1,raw_data_cargo!$1:$1,0),FALSE) | O43: =VLOOKUP($F43,raw_data_cargo!$1:$1048576,MATCH(O$1,raw_data_cargo!$1:$1,0),FALSE) | ... Q43: =VLOOKUP($F43,raw_data_cargo!$1:$1048576,MATCH(Q$1,raw_data_cargo!$1:$1,0),FALSE) | R43: =R3*R38 | S43: =S3*S38 | T43: =T3*T38 | U43: =U3*U38 | V43: =V3*V38 | W43: =W3*W38 | X43: =X3*X38 | Y43: =Y3*Y38 | ... BA43: =BA3*BA38
C44: - Peak Hour departure Movement(ADPM) | D44: float0 | F44: ADPM/movement/d/첨두시 | H44: =MIN(VLOOKUP($F44,raw_data_cargo!$1:$1048576,MATCH(H$1,raw_data_cargo!$1:$1,0),FALSE),H43) | I44: =MIN(VLOOKUP($F44,raw_data_cargo!$1:$1048576,MATCH(I$1,raw_data_cargo!$1:$1,0),FALSE),I43) | J44: =MIN(VLOOKUP($F44,raw_data_cargo!$1:$1048576,MATCH(J$1,raw_data_cargo!$1:$1,0),FALSE),J43) | K44: =MIN(VLOOKUP($F44,raw_data_cargo!$1:$1048576,MATCH(K$1,raw_data_cargo!$1:$1,0),FALSE),K43) | L44: =MIN(VLOOKUP($F44,raw_data_cargo!$1:$1048576,MATCH(L$1,raw_data_cargo!$1:$1,0),FALSE),L43) | M44: =MIN(VLOOKUP($F44,raw_data_cargo!$1:$1048576,MATCH(M$1,raw_data_cargo!$1:$1,0),FALSE),M43) | N44: =MIN(VLOOKUP($F44,raw_data_cargo!$1:$1048576,MATCH(N$1,raw_data_cargo!$1:$1,0),FALSE),N43) | O44: =MIN(VLOOKUP($F44,raw_data_cargo!$1:$1048576,MATCH(O$1,raw_data_cargo!$1:$1,0),FALSE),O43) | ... Q44: =MIN(VLOOKUP($F44,raw_data_cargo!$1:$1048576,MATCH(Q$1,raw_data_cargo!$1:$1,0),FALSE),Q43) | R44: =R43*R46 | S44: =S43*S46 | T44: =T43*T46 | U44: =U43*U46 | V44: =V43*V46 | W44: =W43*W46 | X44: =X43*X46 | Y44: =Y43*Y46 | ... BA44: =BA43*BA46
C45: - Peak Hour aival Movement(ADPM) | D45: float0 | F45: ADPM/movement/a/첨두시 | H45: =MIN(VLOOKUP($F45,raw_data_cargo!$1:$1048576,MATCH(H$1,raw_data_cargo!$1:$1,0),FALSE),H43) | I45: =MIN(VLOOKUP($F45,raw_data_cargo!$1:$1048576,MATCH(I$1,raw_data_cargo!$1:$1,0),FALSE),I43) | J45: =MIN(VLOOKUP($F45,raw_data_cargo!$1:$1048576,MATCH(J$1,raw_data_cargo!$1:$1,0),FALSE),J43) | K45: =MIN(VLOOKUP($F45,raw_data_cargo!$1:$1048576,MATCH(K$1,raw_data_cargo!$1:$1,0),FALSE),K43) | L45: =MIN(VLOOKUP($F45,raw_data_cargo!$1:$1048576,MATCH(L$1,raw_data_cargo!$1:$1,0),FALSE),L43) | M45: =MIN(VLOOKUP($F45,raw_data_cargo!$1:$1048576,MATCH(M$1,raw_data_cargo!$1:$1,0),FALSE),M43) | N45: =MIN(VLOOKUP($F45,raw_data_cargo!$1:$1048576,MATCH(N$1,raw_data_cargo!$1:$1,0),FALSE),N43) | O45: =MIN(VLOOKUP($F45,raw_data_cargo!$1:$1048576,MATCH(O$1,raw_data_cargo!$1:$1,0),FALSE),O43) | ... Q45: =MIN(VLOOKUP($F45,raw_data_cargo!$1:$1048576,MATCH(Q$1,raw_data_cargo!$1:$1,0),FALSE),Q43) | R45: =R43*R47 | S45: =S43*S47 | T45: =T43*T47 | U45: =U43*U47 | V45: =V43*V47 | W45: =W43*W47 | X45: =X43*X47 | Y45: =Y43*Y47 | ... BA45: =BA43*BA47
A46: Directional Factor(ADPM) | B46: Movement Directional Factor(ADPM) | C46: departure Movement Directional Factor(%)(ADPM) | D46: percent1 | F46: ADPM/movement/d/중방향계수 | G46: =SUMIF($H$82:$Q$82,"O",H46:Q46)/COUNTIFS($H$82:$Q$82,"O",H46:Q46,"<>0") | H46: =H44/H43 | I46: =I44/I43 | J46: =J44/J43 | K46: =K44/K43 | L46: =L44/L43 | M46: =M44/M43 | N46: =N44/N43 | O46: =O44/O43 | ... Q46: =Q44/Q43 | R46: =$G46 | S46: =$G46 | T46: =$G46 | U46: =$G46 | V46: =$G46 | W46: =$G46 | X46: =$G46 | Y46: =$G46 | ... BA46: =$G46
C47: aival Movement Directional Factor(%)(ADPM) | D47: percent1 | F47: ADPM/movement/a/중방향계수 | G47: =SUMIF($H$82:$Q$82,"O",H47:Q47)/COUNTIFS($H$82:$Q$82,"O",H47:Q47,"<>0") | H47: =H45/H43 | I47: =I45/I43 | J47: =J45/J43 | K47: =K45/K43 | L47: =L45/L43 | M47: =M45/M43 | N47: =N45/N43 | O47: =O45/O43 | ... Q47: =Q45/Q43 | R47: =$G47 | S47: =$G47 | T47: =$G47 | U47: =$G47 | V47: =$G47 | W47: =$G47 | X47: =$G47 | Y47: =$G47 | ... BA47: =$G47
A51: top | B51: mid | C51: low | D51: decimal | E51: changeable | F51: 변수설명 | G51: Ref_Index | H51: =I51-1 | I51: =J51-1 | J51: =K51-1 | K51: =L51-1 | L51: =M51-1 | M51: =N51-1 | N51: =O51-1 | O51: =P51-1 | P51: =Q51-1 | Q51: =ref!B4 | R51: =Q51+1 | S51: =R51+1 | T51: =S51+1 | U51: =T51+1 | V51: =U51+1 | W51: =V51+1 | X51: =W51+1 | Y51: =X51+1 | ... BA51: =AZ51+1
A52: Airside(SBR) | B52: Passenger Flight Movements(SBR) | C52: Movement PHF(%)(SBR) | D52: percent4 | F52: SBR/movement/all/PHF | H52: =VLOOKUP($F52,raw_data_cargo!$1:$1048576,MATCH(H$1,raw_data_cargo!$1:$1,0),FALSE) | I52: =VLOOKUP($F52,raw_data_cargo!$1:$1048576,MATCH(I$1,raw_data_cargo!$1:$1,0),FALSE) | J52: =VLOOKUP($F52,raw_data_cargo!$1:$1048576,MATCH(J$1,raw_data_cargo!$1:$1,0),FALSE) | K52: =VLOOKUP($F52,raw_data_cargo!$1:$1048576,MATCH(K$1,raw_data_cargo!$1:$1,0),FALSE) | L52: =VLOOKUP($F52,raw_data_cargo!$1:$1048576,MATCH(L$1,raw_data_cargo!$1:$1,0),FALSE) | M52: =VLOOKUP($F52,raw_data_cargo!$1:$1048576,MATCH(M$1,raw_data_cargo!$1:$1,0),FALSE) | N52: =VLOOKUP($F52,raw_data_cargo!$1:$1048576,MATCH(N$1,raw_data_cargo!$1:$1,0),FALSE) | O52: =VLOOKUP($F52,raw_data_cargo!$1:$1048576,MATCH(O$1,raw_data_cargo!$1:$1,0),FALSE) | ... Q52: =VLOOKUP($F52,raw_data_cargo!$1:$1048576,MATCH(Q$1,raw_data_cargo!$1:$1,0),FALSE) | R52: =0.0021*R3^(-0.183)*$G$54 | S52: =0.0021*S3^(-0.183)*$G$54 | T52: =0.0021*T3^(-0.183)*$G$54 | U52: =0.0021*U3^(-0.183)*$G$54 | V52: =0.0021*V3^(-0.183)*$G$54 | W52: =0.0021*W3^(-0.183)*$G$54 | X52: =0.0021*X3^(-0.183)*$G$54 | Y52: =0.0021*Y3^(-0.183)*$G$54 | ... BA52: =0.0021*BA3^(-0.183)*$G$54
C53: Movement PHF(%) Model(SBR) | D53: percent4 | F53: 모형 | H53: =0.0021*H3^(-0.183) | I53: =0.0021*I3^(-0.183) | J53: =0.0021*J3^(-0.183) | K53: =0.0021*K3^(-0.183) | L53: =0.0021*L3^(-0.183) | M53: =0.0021*M3^(-0.183) | N53: =0.0021*N3^(-0.183) | O53: =0.0021*O3^(-0.183) | ... Q53: =0.0021*Q3^(-0.183)
C54: Movement Model PHF / Movement PHF(SBR) | D54: percent1 | F54: 모형PHF / 실제 PHF | G54: =SUMIF($H$78:$Q$78,"O",H54:Q54)/COUNTIFS($H$78:$Q$78,"O",H54:Q54,"<>0") | H54: =H52/H53 | I54: =I52/I53 | J54: =J52/J53 | K54: =K52/K53 | L54: =L52/L53 | M54: =M52/M53 | N54: =N52/N53 | O54: =O52/O53 | ... Q54: =Q52/Q53
C55: Peak Hour Movements(SBR) | D55: float0 | F55: SBR/movement/all/첨두시 | H55: =VLOOKUP($F55,raw_data_cargo!$1:$1048576,MATCH(H$1,raw_data_cargo!$1:$1,0),FALSE) | I55: =VLOOKUP($F55,raw_data_cargo!$1:$1048576,MATCH(I$1,raw_data_cargo!$1:$1,0),FALSE) | J55: =VLOOKUP($F55,raw_data_cargo!$1:$1048576,MATCH(J$1,raw_data_cargo!$1:$1,0),FALSE) | K55: =VLOOKUP($F55,raw_data_cargo!$1:$1048576,MATCH(K$1,raw_data_cargo!$1:$1,0),FALSE) | L55: =VLOOKUP($F55,raw_data_cargo!$1:$1048576,MATCH(L$1,raw_data_cargo!$1:$1,0),FALSE) | M55: =VLOOKUP($F55,raw_data_cargo!$1:$1048576,MATCH(M$1,raw_data_cargo!$1:$1,0),FALSE) | N55: =VLOOKUP($F55,raw_data_cargo!$1:$1048576,MATCH(N$1,raw_data_cargo!$1:$1,0),FALSE) | O55: =VLOOKUP($F55,raw_data_cargo!$1:$1048576,MATCH(O$1,raw_data_cargo!$1:$1,0),FALSE) | ... Q55: =VLOOKUP($F55,raw_data_cargo!$1:$1048576,MATCH(Q$1,raw_data_cargo!$1:$1,0),FALSE) | R55: =R3*R52 | S55: =S3*S52 | T55: =T3*T52 | U55: =U3*U52 | V55: =V3*V52 | W55: =W3*W52 | X55: =X3*X52 | Y55: =Y3*Y52 | ... BA55: =BA3*BA52
C56: - Peak Hour departure Movement(SBR) | D56: float0 | F56: SBR/movement/d/첨두시 | H56: =VLOOKUP($F56,raw_data_cargo!$1:$1048576,MATCH(H$1,raw_data_cargo!$1:$1,0),FALSE) | I56: =VLOOKUP($F56,raw_data_cargo!$1:$1048576,MATCH(I$1,raw_data_cargo!$1:$1,0),FALSE) | J56: =VLOOKUP($F56,raw_data_cargo!$1:$1048576,MATCH(J$1,raw_data_cargo!$1:$1,0),FALSE) | K56: =VLOOKUP($F56,raw_data_cargo!$1:$1048576,MATCH(K$1,raw_data_cargo!$1:$1,0),FALSE) | L56: =VLOOKUP($F56,raw_data_cargo!$1:$1048576,MATCH(L$1,raw_data_cargo!$1:$1,0),FALSE) | M56: =VLOOKUP($F56,raw_data_cargo!$1:$1048576,MATCH(M$1,raw_data_cargo!$1:$1,0),FALSE) | N56: =VLOOKUP($F56,raw_data_cargo!$1:$1048576,MATCH(N$1,raw_data_cargo!$1:$1,0),FALSE) | O56: =VLOOKUP($F56,raw_data_cargo!$1:$1048576,MATCH(O$1,raw_data_cargo!$1:$1,0),FALSE) | ... Q56: =VLOOKUP($F56,raw_data_cargo!$1:$1048576,MATCH(Q$1,raw_data_cargo!$1:$1,0),FALSE) | R56: =R55*R58 | S56: =S55*S58 | T56: =T55*T58 | U56: =U55*U58 | V56: =V55*V58 | W56: =W55*W58 | X56: =X55*X58 | Y56: =Y55*Y58 | ... BA56: =BA55*BA58
C57: - Peak Hour aival Movement(SBR) | D57: float0 | F57: SBR/movement/a/첨두시 | H57: =VLOOKUP($F57,raw_data_cargo!$1:$1048576,MATCH(H$1,raw_data_cargo!$1:$1,0),FALSE) | I57: =VLOOKUP($F57,raw_data_cargo!$1:$1048576,MATCH(I$1,raw_data_cargo!$1:$1,0),FALSE) | J57: =VLOOKUP($F57,raw_data_cargo!$1:$1048576,MATCH(J$1,raw_data_cargo!$1:$1,0),FALSE) | K57: =VLOOKUP($F57,raw_data_cargo!$1:$1048576,MATCH(K$1,raw_data_cargo!$1:$1,0),FALSE) | L57: =VLOOKUP($F57,raw_data_cargo!$1:$1048576,MATCH(L$1,raw_data_cargo!$1:$1,0),FALSE) | M57: =VLOOKUP($F57,raw_data_cargo!$1:$1048576,MATCH(M$1,raw_data_cargo!$1:$1,0),FALSE) | N57: =VLOOKUP($F57,raw_data_cargo!$1:$1048576,MATCH(N$1,raw_data_cargo!$1:$1,0),FALSE) | O57: =VLOOKUP($F57,raw_data_cargo!$1:$1048576,MATCH(O$1,raw_data_cargo!$1:$1,0),FALSE) | ... Q57: =VLOOKUP($F57,raw_data_cargo!$1:$1048576,MATCH(Q$1,raw_data_cargo!$1:$1,0),FALSE) | R57: =R55*R59 | S57: =S55*S59 | T57: =T55*T59 | U57: =U55*U59 | V57: =V55*V59 | W57: =W55*W59 | X57: =X55*X59 | Y57: =Y55*Y59 | ... BA57: =BA55*BA59
A58: Directional Factor(SBR) | B58: Movement Directional Factor(SBR) | C58: departure Movement Directional Factor(%)(SBR) | D58: percent1 | F58: ADPM/movement/d/중방향계수 | G58: =SUMIF($H$82:$Q$82,"O",H58:Q58)/COUNTIFS($H$82:$Q$82,"O",H58:Q58,"<>0") | H58: =H56/H55 | I58: =I56/I55 | J58: =J56/J55 | K58: =K56/K55 | L58: =L56/L55 | M58: =M56/M55 | N58: =N56/N55 | O58: =O56/O55 | ... Q58: =Q56/Q55 | R58: =$G58 | S58: =$G58 | T58: =$G58 | U58: =$G58 | V58: =$G58 | W58: =$G58 | X58: =$G58 | Y58: =$G58 | ... BA58: =$G58
C59: aival Movement Directional Factor(%)(SBR) | D59: percent1 | F59: ADPM/movement/a/중방향계수 | G59: =SUMIF($H$82:$Q$82,"O",H59:Q59)/COUNTIFS($H$82:$Q$82,"O",H59:Q59,"<>0") | H59: =H57/H55 | I59: =I57/I55 | J59: =J57/J55 | K59: =K57/K55 | L59: =L57/L55 | M59: =M57/M55 | N59: =N57/N55 | O59: =O57/O55 | ... Q59: =Q57/Q55 | R59: =$G59 | S59: =$G59 | T59: =$G59 | U59: =$G59 | V59: =$G59 | W59: =$G59 | X59: =$G59 | Y59: =$G59 | ... BA59: =$G59
C61: Aircraft_category
C62: (Widebody Jets)
C63: (Narrowbody Jets)
C64: (Regional Jets)
C65: (Business Jets)
G69: 참조지표 제작 | H69: =I69-1 | I69: =J69-1 | J69: =K69-1 | K69: =L69-1 | L69: =M69-1 | M69: =N69-1 | N69: =O69-1 | O69: =P69-1 | P69: =Q69-1 | Q69: =ref!B4
G70: Demand | H70: =IF(VLOOKUP($G70,ref!$A$12:$AT$35,MATCH(H$1,ref!$12:$12,0),FALSE),"O","") | I70: =IF(VLOOKUP($G70,ref!$A$12:$AT$35,MATCH(I$1,ref!$12:$12,0),FALSE),"O","") | J70: =IF(VLOOKUP($G70,ref!$A$12:$AT$35,MATCH(J$1,ref!$12:$12,0),FALSE),"O","") | K70: =IF(VLOOKUP($G70,ref!$A$12:$AT$35,MATCH(K$1,ref!$12:$12,0),FALSE),"O","") | L70: =IF(VLOOKUP($G70,ref!$A$12:$AT$35,MATCH(L$1,ref!$12:$12,0),FALSE),"O","") | M70: =IF(VLOOKUP($G70,ref!$A$12:$AT$35,MATCH(M$1,ref!$12:$12,0),FALSE),"O","") | N70: =IF(VLOOKUP($G70,ref!$A$12:$AT$35,MATCH(N$1,ref!$12:$12,0),FALSE),"O","") | O70: =IF(VLOOKUP($G70,ref!$A$12:$AT$35,MATCH(O$1,ref!$12:$12,0),FALSE),"O","") | ... Q70: =IF(VLOOKUP($G70,ref!$A$12:$AT$35,MATCH(Q$1,ref!$12:$12,0),FALSE),"O","")
G71: Load_Factor | H71: =IF(VLOOKUP($G71,ref!$A$12:$AT$35,MATCH(H$1,ref!$12:$12,0),FALSE),"O","") | I71: =IF(VLOOKUP($G71,ref!$A$12:$AT$35,MATCH(I$1,ref!$12:$12,0),FALSE),"O","") | J71: =IF(VLOOKUP($G71,ref!$A$12:$AT$35,MATCH(J$1,ref!$12:$12,0),FALSE),"O","") | K71: =IF(VLOOKUP($G71,ref!$A$12:$AT$35,MATCH(K$1,ref!$12:$12,0),FALSE),"O","") | L71: =IF(VLOOKUP($G71,ref!$A$12:$AT$35,MATCH(L$1,ref!$12:$12,0),FALSE),"O","") | M71: =IF(VLOOKUP($G71,ref!$A$12:$AT$35,MATCH(M$1,ref!$12:$12,0),FALSE),"O","") | N71: =IF(VLOOKUP($G71,ref!$A$12:$AT$35,MATCH(N$1,ref!$12:$12,0),FALSE),"O","") | O71: =IF(VLOOKUP($G71,ref!$A$12:$AT$35,MATCH(O$1,ref!$12:$12,0),FALSE),"O","") | ... Q71: =IF(VLOOKUP($G71,ref!$A$12:$AT$35,MATCH(Q$1,ref!$12:$12,0),FALSE),"O","")
G72: Transfer_Rate | H72: =IF(VLOOKUP($G72,ref!$A$12:$AT$35,MATCH(H$1,ref!$12:$12,0),FALSE),"O","") | I72: =IF(VLOOKUP($G72,ref!$A$12:$AT$35,MATCH(I$1,ref!$12:$12,0),FALSE),"O","") | J72: =IF(VLOOKUP($G72,ref!$A$12:$AT$35,MATCH(J$1,ref!$12:$12,0),FALSE),"O","") | K72: =IF(VLOOKUP($G72,ref!$A$12:$AT$35,MATCH(K$1,ref!$12:$12,0),FALSE),"O","") | L72: =IF(VLOOKUP($G72,ref!$A$12:$AT$35,MATCH(L$1,ref!$12:$12,0),FALSE),"O","") | M72: =IF(VLOOKUP($G72,ref!$A$12:$AT$35,MATCH(M$1,ref!$12:$12,0),FALSE),"O","") | N72: =IF(VLOOKUP($G72,ref!$A$12:$AT$35,MATCH(N$1,ref!$12:$12,0),FALSE),"O","") | O72: =IF(VLOOKUP($G72,ref!$A$12:$AT$35,MATCH(O$1,ref!$12:$12,0),FALSE),"O","") | ... Q72: =IF(VLOOKUP($G72,ref!$A$12:$AT$35,MATCH(Q$1,ref!$12:$12,0),FALSE),"O","")
G73: FleetMix_Rate | H73: =IF(VLOOKUP($G73,ref!$A$12:$AT$35,MATCH(H$1,ref!$12:$12,0),FALSE),"O","") | I73: =IF(VLOOKUP($G73,ref!$A$12:$AT$35,MATCH(I$1,ref!$12:$12,0),FALSE),"O","") | J73: =IF(VLOOKUP($G73,ref!$A$12:$AT$35,MATCH(J$1,ref!$12:$12,0),FALSE),"O","") | K73: =IF(VLOOKUP($G73,ref!$A$12:$AT$35,MATCH(K$1,ref!$12:$12,0),FALSE),"O","") | L73: =IF(VLOOKUP($G73,ref!$A$12:$AT$35,MATCH(L$1,ref!$12:$12,0),FALSE),"O","") | M73: =IF(VLOOKUP($G73,ref!$A$12:$AT$35,MATCH(M$1,ref!$12:$12,0),FALSE),"O","") | N73: =IF(VLOOKUP($G73,ref!$A$12:$AT$35,MATCH(N$1,ref!$12:$12,0),FALSE),"O","") | O73: =IF(VLOOKUP($G73,ref!$A$12:$AT$35,MATCH(O$1,ref!$12:$12,0),FALSE),"O","") | ... Q73: =IF(VLOOKUP($G73,ref!$A$12:$AT$35,MATCH(Q$1,ref!$12:$12,0),FALSE),"O","")
G74: Seats_Per_Aircraft | H74: =IF(VLOOKUP($G74,ref!$A$12:$AT$35,MATCH(H$1,ref!$12:$12,0),FALSE),"O","") | I74: =IF(VLOOKUP($G74,ref!$A$12:$AT$35,MATCH(I$1,ref!$12:$12,0),FALSE),"O","") | J74: =IF(VLOOKUP($G74,ref!$A$12:$AT$35,MATCH(J$1,ref!$12:$12,0),FALSE),"O","") | K74: =IF(VLOOKUP($G74,ref!$A$12:$AT$35,MATCH(K$1,ref!$12:$12,0),FALSE),"O","") | L74: =IF(VLOOKUP($G74,ref!$A$12:$AT$35,MATCH(L$1,ref!$12:$12,0),FALSE),"O","") | M74: =IF(VLOOKUP($G74,ref!$A$12:$AT$35,MATCH(M$1,ref!$12:$12,0),FALSE),"O","") | N74: =IF(VLOOKUP($G74,ref!$A$12:$AT$35,MATCH(N$1,ref!$12:$12,0),FALSE),"O","") | O74: =IF(VLOOKUP($G74,ref!$A$12:$AT$35,MATCH(O$1,ref!$12:$12,0),FALSE),"O","") | ... Q74: =IF(VLOOKUP($G74,ref!$A$12:$AT$35,MATCH(Q$1,ref!$12:$12,0),FALSE),"O","")
